Workbook
Name AreaDePersonal: [1]Listas!$E$4:$E$9
Name ClasificacionOSHA: [1]Listas!$L$4:$L$7
Name CRITERIOS_ESTADISTICAS: [2]AUXILIARES!$M$1:$Q$2
Name DESTINO: [2]AUXILIARES!$M$4
Name DIASDMR_ALICORP: '[2]DIAS DMR'!$U$2:$AL$2
Name DIASDMR_NOALICORP: '[2]DIAS DMR'!$AM$2:$BD$2
Name DIASPERD_ALICORP: '[2]DIAS PERDIDOS'!$U$2:$AL$2
Name DIASPERD_NOALICORP: '[2]DIAS PERDIDOS'!$AM$2:$BD$2
Name Doctores: [1]Listas!$A$4:$A$13
Name ENCABEZADO: [2]ACCIDENTES!$A$2:$K$2
Name EntidadNosologica: [1]Listas!$G$4:$G$38
Name GENERADORES_CRITERIOS: [2]AUXILIARES!$N$5:$P$9
Name INDICES: [2]AUXILIARES!$C$2:$F$12
Name LESDMR_ALICORP: '[2]LESIONES CON DMR'!$U$2:$AL$2
Name LESDMR_NOALICORP: '[2]LESIONES CON DMR'!$AM$2:$BD$2
Name LESINCAP_ALICORP: '[2]LESIONES INCAPACITANTES'!$U$2:$AL$2
Name LESINCAP_NOALICORP: '[2]LESIONES INCAPACITANTES'!$AM$2:$BD$2
Name LESNOINCAP_ALICORP: '[2]LESIONES NO INCAPACITANTES'!$U$2:$AK$2
Name LESNOINCAP_NOALICORP: '[2]LESIONES NO INCAPACITANTES'!$AM$2:$BD$2
Name Medicamentos: [1]Medicamentos!$C$6:$C$107
Name MESES: [2]AUXILIARES!$H$2:$H$13
Name OPCIONES: [2]AUXILIARES!$J$9:$J$12
Name Paramedicos: [1]Listas!$C$4:$C$12
Name PLANTAS: [2]AUXILIARES!$A$15:$A$32
Name PROGRAMAS: [2]AUXILIARES!$A$2:$A$12
Name SETEO: [2]AUXILIARES!$K$2:$K$7
Name SubdivisionPersonal: [1]Listas!$J$4:$J$22
Name TipoAccidente: [1]Listas!$N$12:$N$16
Name TipoAtencion: [1]Listas!$N$4:$N$7

Sheet PROGRAMA 2010
A1: Item | B1: Actividad | C1: %Avance | D1: Responsable | E1: Comentarios | F1: P/R | G1: Ene | H1: Feb | I1: Mar | J1: Abr | K1: May | L1: Jun | M1: Jul | N1: Ago | O1: Sep | P1: Oct | Q1: Nov | R1: Dic
A2: 1 | B2: Reestructurar Plan IGP | C2: 1 | D2: J.Briceño/D.Lucana | E2: Agregar a programa de IGP: Sist.Seguridad, Utiles/Materiales, Inv.Herramientas, Casilleros, SSEE (R.Aleman) | F2: P
F3: R
A4: 2 | B4: Charlas Resultados CP 2009 al personal | C4: 1 | D4: Directores/J.Briceño | E4: MSR: 19/04 y 26/04 de 04:00 a 05:00 pm. MFA: 21/04 (02:00 a 03:00 pm y de 03:00 a 04:00 pm) 22/04 (02:00 a 03:00 pm) 28/04 (02:00 a 03:00 pm y de 03:00 a 04:00 pm) MCA: 03/05 8:00 a 09:30 pm 26/04 05:00 a 06:00 pm 03/05 05:00 a 06:00 pm Se modificar'a material de acuerdo a revision con C.Navarro. La charla se acomp;ar'a con un video (Rudi) | F4: P
F5: R
B6: Preparar Material | C6: 1 | F6: P
F7: R
B8: Definir programa de charlas | C8: 1 | F8: P
F9: R
B10: Dictado en MCA | F10: P
F11: R
B12: Dictado en MFA | F12: P
F13: R
B14: Dictado en MSR | F14: P
F15: R
A16: 3 | B16: Revisión del sistema de Permisos de Trabajo | C16: 0.28 | D16: C.Navarro/J.Antezana/J.Briceño | E16: Se presento plan de trabajo al comite ejecutivo (15/03). Se emitio nueva versi'on Normas Contratistas. | F16: P
F17: R
B18: Desarrollar plan de trabajo | C18: 1 | D18: C.Navarro/J.Antezana/J.Briceño | E18: Presentado en Comité Ejecutivo de Febrero el 15/03 | F18: P
F19: R
B20: Actualizar Normas Contratistas | C20: 1 | D20: J.Briceño | E20: Versión 03 del Documento ALI-C-CP-E8-004 (Obselescencia de cartilla Uso EPP Contratista-Visitante) | F20: P
F21: R
B22: Elaborar Manual Contratistas | D22: J.Briceño | E22: Se envió Manual corregido a C.Navarro | F22: P
F23: R
B24: Rediseñar tarjetas Permisos de Trabajo | D24: J.Briceño | E24: Se definieron cambios con Sup.Mnto 11/06 | F24: P
F25: R
B26: Revisar sistema de control acceso | D26: J.Briceño | E26: Se contacto con Programadora (Soledad Castañeda) para reunirnos y revisar sistema | F26: P
F27: R
B28: Revisar Procedimiento de Permisos de Trabajo | C28: 1 | D28: C.Navarro/J.Antezana/J.Briceño | E28: Se acordaron cambios en reunión. | F28: P
F29: R
B30: Capacitar al personal nivel liderazgo en nuevo procedimiento | D30: J.Briceño | F30: P
F31: R
B32: Inducción a Contratistas en nuevo procedimiento | D32: J.Antezana | F32: P
F33: R
B34: Ampliar alcance a demás áreas (Administración, Transportistas, Estibadores) | D34: C.Navarro/J.Antezana/J.Briceño | F34: P
F35: R
B36: Revisar proceso de homologación | D36: C.Navarro/J.Antezana/J.Briceño | F36: P
F37: R
B38: Evaluar sanciones de amonestación escrita a las jefaturas ante incumplimiento | D38: C.Navarro/J.Antezana/J.Briceño | F38: P
F39: R
A40: 4 | B40: Revisión de Identificacion Peligros, Evaluac.Riesgos, Det.Controles Necesarios | C40: 0.16 | D40: C.Navarro/J.Seguridad | E40: Viernes 18/06 se termina piloto de nueva metodología IPER (Lab.Copsa). Se han definido Reglas Generales y Específicas por áreas del MFA para el personal LIMTEK. | F40: P
F41: R
B42: Proponer nueva metodología IPER | C42: 1 | D42: J.Briceño | E42: Se presentó propuesta nuevo formato. Prueba piloto Junio Lab.Copsa | F42: P
F43: R
B44: Revisión de Procedimiento IPER | D44: C.Navarro/J.Seguridad | F44: P
F45: R
B46: Capacitar al personal nivel liderazgo en nuevo procedimiento | D46: J.Seguridad | F46: P
F47: R
B48: Actualización 2010 IPER | D48: Responsable de Area | F48: P
F49: R
B50: Revisión IPER LIMTEK | C50: 0.3 | D50: C.Endo/OL.Azanero/J.Briceño | E50: Ya se tiene IPER de LIMTEK para MFA . Se han definido Reglas Generales y Específicas por áreas. Trabajándose para MCA y MSR. | F50: P
F51: R
B52: Revisión IPER ORUS | D52: C.Endo/OL.Azanero/J.Briceño | F52: P
F53: R
B54: Revisión IPER CONSESIONARIO | D54: C.Endo/OL.Azanero/J.Briceño | F54: P
F55: R
B56: Revisión IPER WIN | D56: C.Endo/OL.Azanero/J.Briceño | F56: P
F57: R
A58: 5 | B58: Aumentar participación del personal en Observación Tareas | C58: 0 | D58: Responsable de Area/J.Briceño | F58: P
F59: R
B60: Seleccionar al personal Observador | D60: Responsable de Area | F60: P
F61: R
B62: Capacitar al personal | D62: J.Briceño | F62: P
F63: R
A64: 6 | B64: Revisión del Sistema ROM | C64: 0 | D64: C.Navarro/C.Navarro | F64: P
F65: R
A66: 7 | B66: Revisión del proceso de Identificación Emergencias, Planes Emergencias, Entrenamiento Brigadas | C66: 0.05 | D66: J.Seguridad/Inspectores Seg | E66: Acta reunión semanal | F66: P
F67: R
A68: 8 | B68: Levantamiento inspección SSEE | C68: 0.4 | D68: Supervisor Mantenimiento | F68: P
F69: R
B70: MCA | C70: 0.3 | D70: J.L.Barrera | F70: P
F71: R
B72: MFA | C72: 0.46 | D72: A.Cordova | F72: P
F73: R
B74: MSR | C74: 0.43 | D74: H.Zegarra | F74: P
F75: R
A76: 9 | B76: Levantamiento NCm de auditor'ia G.Lloyd | C76: 0.56 | D76: J.Producción/J.Producción | F76: P
F77: R
B78: MCA | D78: J.Mendoza/J.Briceño | F78: P
F79: R
B80: MFA | D80: O.Fajardo/J.Briceño | F80: P
F81: R
B82: MSR | D82: C.Cuadros/J.Briceño | F82: P
F83: R
A84: 10 | B84: Levantamiento Hallazgos inspección INDECI | C84: 0.12 | D84: Supervisor Mantenimiento | F84: P
F85: R
B86: MCA | D86: J.L.Barrera | F86: P
F87: R
B88: MSR | D88: A.Cordova | F88: P
F89: R
B90: PATIOS | D90: H.Malca | F90: P
F91: R
A92: 11 | B92: Red Contraincendio MCA | C92: 0.9 | D92: Mario Adrían Castañeda | E92: Se termino prueba Hidrostatica de la Red a 150 PSI. | F92: P
F93: R
B94: Conlcuir instalación y prueba de pozo a tierra (5 Ohms). | C94: 1 | D94: Fire Test | F94: P
F95: R
B96: Definir sistema de desagüe para TK de agua CI. | C96: 1 | D96: C.Hernández/G.Quinteros | F96: P
F97: R
B98: Luz de emergencia en el interior de la caseta. | D98: JL.Barrera/D.Lucana | E98: Falta instalación de Luz. | F98: P
F99: R
B100: Extintor PQS, CO2 en caseta. | C100: 1 | D100: JL.Zegrra | E100: Reponer los colocados en caseta | F100: P
...

Sheet ENE
B1: TSPM A ENERO 2010
B3: Elem | C3: Indicador | D3: Peso Ponderado | E3: MCA | F3: MFA | G3: MSR | H3: Molinos Lima | I3: OBJ MAX | K3: Mol Lima 2009 | L3: MCA | M3: MFA | N3: MSR | O3: Molinos Lima | Q3: Alicorp | R3: 2009 | T3: Comentarios Mol.Lima
B4: E2 | C4: Asistencia Capacitación | D4: 0.04 | E4: 0.59 | F4: 0.53 | G4: 0.57 | H4: 0.56 | I4: 0.9 | J4: =+I4*D4 -> 0.036 | K4: 0.91 | L4: =+E4*$D$4 -> 0.0236 | M4: =+F4*$D$4 -> 0.0212 | N4: =+G4*$D$4 -> 0.0228 | O4: =+H4*$D$4 -> 0.0224 | Q4: 0.9 | R4: 0.9
B5: E3 | C5: %Cumplimiento IGP´s | D5: 0.04 | E5: 0.5 | F5: 0.8 | G5: 1 | H5: 0.75 | I5: 1 | J5: =+I5*D5 -> 0.04 | K5: 0.9754 | L5: =+E5*D5 -> 0.02 | M5: =+F5*D5 -> 0.032 | N5: =+G5*D5 -> 0.04 | O5: =+H5*D5 -> 0.03 | Q5: 0.7529 | R5: 0.9822
C6: %Identif.Actos Sub.IGP | D6: 0 | E6: 0.36 | F6: 0.25 | G6: 0.67 | H6: 0.3461 | I6: 0.45 | J6: =+I6*D6 -> 0 | K6: 0.3549 | L6: =+E6*D6 -> 0 | M6: =+F6*D6 -> 0 | N6: =+G6*D6 -> 0 | O6: =+H6*D6 -> 0 | Q6: 0.4 | R6: 0.358
B7: E4 | C7: %Cumplimiento ITAR | D7: 0 | E7: 1 | F7: 1 | G7: 1 | H7: 1 | I7: 0.95 | J7: =+I7*D7 -> 0 | K7: 1 | L7: =+E7*D7 -> 0 | M7: =+F7*D7 -> 0 | N7: =+G7*D7 -> 0 | O7: =+H7*D7 -> 0
C8: %Implementación CV | D8: 0 | E8: 0 | F8: 1 | G8: 1 | H8: 0.66 | I8: 1 | J8: =+I8*D8 -> 0 | K8: 1 | L8: =+E8*D8 -> 0 | M8: =+F8*D8 -> 0 | N8: =+G8*D8 -> 0 | O8: =+H8*D8 -> 0
C9: Mapa de riesgo | D9: 0.04 | E9: 1 | F9: 1 | G9: 1 | H9: 1 | I9: 0.95 | J9: =+I9*D9 -> 0.038 | K9: 1 | L9: =+$D$9*E9 -> 0.04 | M9: =+$D$9*F9 -> 0.04 | N9: =+$D$9*G9 -> 0.04 | O9: =+$D$9*H9 -> 0.04 | Q9: 0.97 | R9: 0.97
B10: E5 | C10: Accid.Incapacitantes | E10: 0 | F10: 1 | G10: 0 | H10: 1 | I10: 6 | K10: 7 | Q10: 6 | R10: 36
C11: Accid.DMR | E11: 0 | F11: 0 | G11: 0 | H11: 0 | I11: 0 | K11: 0 | Q11: 0 | R11: 9
C12: Lesión Menor | E12: 0 | F12: 0 | G12: 0 | H12: 0 | I12: 7 | K12: 8 | Q12: 11 | R12: 94
C13: Días de Descanso | E13: 0 | F13: 15 | G13: 0 | H13: 15 | I13: 77 | K13: 6068 | Q13: 51 | R13: 8202
C14: Ind.Frecuencia (1 año) | D14: 0.1 | E14: 6.85 | F14: 10.2 | G14: 0 | H14: 6.39 | I14: 4.75 | J14: =+D14 -> 0.1 | K14: 5.57 | L14: =5.06/E14*D14 -> 0.073868613 | M14: =4.97/F14*D14 -> 0.04872549 | N14: 0.1 | O14: =I14/H14*D14 -> 0.074334898 | Q14: 2.31 | R14: 3.05
C15: Ind.Severidad (1 año) | D15: 0.1 | E15: 10303.79 | F15: 163.21 | G15: 0 | H15: 4860.15 | I15: 60.98 | J15: =+D15 -> 0.1 | K15: 4828.05 | L15: =50.59/E15*D15 -> 0.00049098439 | M15: =96.93/F15*D15 -> 0.059389743 | N15: 0.1 | O15: =I15/H15*D15 -> 0.0012546938 | Q15: 698.45 | R15: 694.94
C16: OSHA incident rate | D16: 0.1 | E16: 1.71 | F16: 5.1 | G16: 0.73 | H16: 2.56 | I16: 2.06 | J16: =+D16 -> 0.1 | K16: 2.55 | L16: =1.35/1.71*D16 -> 0.078947368 | M16: =2.98/F16*D16 -> 0.058431373 | N16: 0.1 | O16: =I16/H16*D16 -> 0.08046875 | Q16: 3.14 | R16: 2.36
C17: Calidad Investigación | D17: 0.08 | E17: 0.66 | F17: 0.82 | G17: 0.79 | H17: 0.69 | I17: 0.85 | J17: =+I17*D17 -> 0.068 | K17: 0.7473 | L17: =+$D$17*E17 -> 0.0528 | M17: =+$D$17*F17 -> 0.0656 | N17: =+$D$17*G17 -> 0.0632 | O17: =+$D$17*H17 -> 0.0552 | R17: 0.743
C18: %Levantamiento ROM´s | D18: 0.08 | E18: 0.69 | F18: 0.47 | G18: 0.38 | H18: 0.5556 | I18: 0.95 | J18: =+I18*D18 -> 0.076 | K18: 0.9129 | L18: =+E18*D18 -> 0.0552 | M18: =+F18*D18 -> 0.0376 | N18: =+G18*D18 -> 0.0304 | O18: =+H18*D18 -> 0.044448 | Q18: 0.52 | R18: 0.934
C19: %Identif.Actos Sub.ROM´s | D19: 0 | E19: 0.58 | F19: 0.62 | G19: 0.25 | H19: 0.44 | I19: 0.85 | J19: =+I19*D19 -> 0 | K19: 0.7812 | L19: =+E19*D19 -> 0 | M19: =+F19*D19 -> 0 | N19: =+G19*D19 -> 0 | O19: =+H19*D19 -> 0 | Q19: 0.47 | R19: 0.57
C20: %Particip.ROM´s (en el Semestre) | D20: 0 | E20: 0.14 | F20: 0.17 | G20: 0.04 | H20: 0.13 | I20: 0.6 | J20: =+I20*D20 -> 0 | K20: 0.7 | L20: =+E20*D20 -> 0 | M20: =+F20*D20 -> 0 | N20: =+G20*D20 -> 0 | O20: =+H20*D20 -> 0 | R20: 0.64
C21: %ROM´s Autofinalizadas | D21: 0 | E21: 0.56 | F21: 0.36 | G21: 0.19 | H21: 0.43 | I21: 0.55 | J21: =+I21*D21 -> 0 | K21: 0.7169 | L21: =+E21*D21 -> 0 | M21: =+F21*D21 -> 0 | N21: =+G21*D21 -> 0 | O21: =+H21*D21 -> 0 | Q21: 0.34
B22: E6 | C22: Cumplimiento Prog.Observ | D22: 0.04 | E22: 1 | F22: 1 | G22: 1 | H22: 1 | I22: 0.95 | J22: =+I22*D22 -> 0.038 | K22: 1 | L22: =+E22*D22 -> 0.04 | M22: =+F22*D22 -> 0.04 | N22: =+G22*D22 -> 0.04 | O22: =+H22*D22 -> 0.04 | R22: 0.95
C23: %Comportam.Seguro | D23: 0.08 | E23: 1 | F23: 0.94 | G23: 1 | H23: 0.99 | I23: 1 | J23: =+I23*D23 -> 0.08 | K23: 0.99 | L23: =+E23*D23 -> 0.08 | M23: =+F23*D23 -> 0.0752 | N23: =+G23*D23 -> 0.08 | O23: =+H23*D23 -> 0.0792 | R23: 0.968
B24: E7 | C24: Evaluación Simulacros | D24: 0.05 | E24: 0.66 | F24: 0.82 | G24: 0.79 | H24: 0.69 | I24: 0.8 | J24: =+I24*D24 -> 0.04 | K24: 0.69 | L24: =+E24*D24 -> 0.033 | M24: =+F24*D24 -> 0.041 | N24: =+G24*D24 -> 0.0395 | O24: =+H24*D24 -> 0.0345 | R24: 0.89
C25: Participación Niv.Lid.Brigadas | D25: 0.02 | E25: 0.67 | F25: 0.83 | G25: 1 | H25: 0.83 | I25: 0.95 | J25: =+I25*D25 -> 0.019 | K25: 0.76 | L25: =+$H$25*$D$25 -> 0.0166 | M25: =+$H$25*$D$25 -> 0.0166 | N25: =+$H$25*$D$25 -> 0.0166 | O25: =+$H$25*$D$25 -> 0.0166 | R25: 0.75
B26: E8 | C26: Efectividad Perm.Trabajo | D26: 0.05 | E26: 1 | F26: 1 | G26: 0.98 | H26: 0.99 | I26: 1 | J26: =+I26*D26 -> 0.05 | K26: 1 | L26: =+E26*D26 -> 0.05 | M26: =+F26*D26 -> 0.05 | N26: =+G26*D26 -> 0.049 | O26: =+H26*D26 -> 0.0495 | R26: 0.977
C27: %Particip.Fiscalización Permisos | D27: 0 | E27: 0.66 | F27: 0.52 | G27: =5/45 -> 0.11111111 | H27: 0.5167 | I27: 0.7 | J27: =+I27*D27 -> 0 | K27: 0.6 | L27: =+E27*D27 -> 0 | M27: =+F27*D27 -> 0 | N27: =+G27*D27 -> 0 | O27: =+H27*D27 -> 0
B28: E11 | C28: %Cumplim.EPP | D28: 0.05 | E28: 0.88 | F28: 1 | G28: 0.84 | H28: 0.91 | I28: 1 | J28: =+I28*D28 -> 0.05 | K28: 0.99 | L28: =+E28*D28 -> 0.044 | M28: =+F28*D28 -> 0.05 | N28: =+G28*D28 -> 0.042 | O28: =+H28*D28 -> 0.0455 | R28: 0.98
B29: E12 | C29: Examen médico Ingresantes | D29: 0.03 | H29: 0.96 | I29: 0.95 | J29: =+I29*D29 -> 0.0285 | K29: 0.96 | L29: =+$H$29*$D$29 -> 0.0288 | M29: =+$H$29*$D$29 -> 0.0288 | N29: =+$H$29*$D$29 -> 0.0288 | O29: =+$H$29*$D$29 -> 0.0288 | Q29: 0.92 | R29: 0.92
C30: Examen preventivo | D30: 0.02 | H30: 0.97 | I30: 0.95 | J30: =+I30*D30 -> 0.019 | K30: 0.97 | L30: =+O30 -> 0.0194 | M30: =+O30 -> 0.0194 | N30: =+O30 -> 0.0194 | O30: =+H30*D30 -> 0.0194 | Q30: 0.98 | R30: 0.98
B31: E19 | C31: Homologación Proveedores | D31: 0.08 | H31: 0.79 | I31: 0.9 | J31: =+I31*D31 -> 0.072 | K31: 0.79 | L31: =+O31 -> 0.0632 | M31: =+O31 -> 0.0632 | N31: =+O31 -> 0.0632 | O31: =+H31*D31 -> 0.0632 | Q31: 0.8 | R31: 0.8
C32: Total %TSPM | D32: =SUM(D4:D31) -> 1 | E32: =+L32 -> 0.71990697 | F32: =+M32 -> 0.74714661 | G32: =+N32 -> 0.8749 | H32: =+O32 -> 0.72880634 | I32: =+J32 -> 0.9545 | J32: =SUM(J4:J31) -> 0.9545 | K32: 0.83395402 | L32: =SUM(L4:L31) -> 0.71990697 | M32: =SUM(M4:M31) -> 0.74714661 | N32: =SUM(N4:N31) -> 0.8749 | O32: =SUM(O4:O31)+0.004 -> 0.72880634 | R32: 0.718

Sheet FEB
B1: TSPM A FEBRERO 2010
B3: Elem | C3: Indicador | D3: Peso Ponderado | E3: MCA | F3: MFA | G3: MSR | H3: Molinos Lima | I3: OBJ MAX | K3: Mol Lima 2009 | L3: MCA | M3: MFA | N3: MSR | O3: Molinos Lima | Q3: Alicorp | R3: 2009 | T3: Comentarios Mol.Lima
B4: E2 | C4: Asistencia Capacitación | D4: 0.04 | E4: 0.69 | F4: 0.55 | G4: 0.76 | H4: 0.6469 | I4: 0.9 | J4: =+I4*D4 -> 0.036 | K4: 0.91 | L4: =+E4*$D$4 -> 0.0276 | M4: =+F4*$D$4 -> 0.022 | N4: =+G4*$D$4 -> 0.0304 | O4: =+H4*$D$4 -> 0.025876 | R4: 0.9
B5: E3 | C5: %Cumplimiento IGP´s | D5: 0.04 | E5: 0.83 | F5: 0.8 | G5: 0.9 | H5: 0.8438 | I5: 1 | J5: =+I5*D5 -> 0.04 | K5: 0.9754 | L5: =+E5*D5 -> 0.0332 | M5: =+F5*D5 -> 0.032 | N5: =+G5*D5 -> 0.036 | O5: =+H5*D5 -> 0.033752 | R5: 0.9822
C6: %Identif.Actos Sub.IGP | D6: 0 | E6: 0.2581 | F6: 0.3 | G6: 0.6471 | H6: 0.3676 | I6: 0.45 | J6: =+I6*D6 -> 0 | K6: 0.3549 | L6: =+E6*D6 -> 0 | M6: =+F6*D6 -> 0 | N6: =+G6*D6 -> 0 | O6: =+H6*D6 -> 0 | R6: 0.358
B7: E4 | C7: %Cumplimiento ITAR | D7: 0 | I7: 0.95 | J7: =+I7*D7 -> 0 | K7: 1 | L7: =+E7*D7 -> 0 | M7: =+F7*D7 -> 0 | N7: =+G7*D7 -> 0 | O7: =+H7*D7 -> 0
C8: %Implementación CV | D8: 0 | I8: 1 | J8: =+I8*D8 -> 0 | K8: 1 | L8: =+E8*D8 -> 0 | M8: =+F8*D8 -> 0 | N8: =+G8*D8 -> 0 | O8: =+H8*D8 -> 0
C9: Mapa de riesgo | D9: 0.04 | E9: 1 | F9: 1 | G9: 1 | H9: 1 | I9: 0.95 | J9: =+I9*D9 -> 0.038 | K9: 1 | L9: =+$D$9*E9 -> 0.04 | M9: =+$D$9*F9 -> 0.04 | N9: =+$D$9*G9 -> 0.04 | O9: =+$D$9*H9 -> 0.04 | R9: 0.97
B10: E5 | C10: Dias sin accidentes | E10: 292 | F10: 33 | G10: 476 | H10: 33
C11: Accid.Incapacitantes | E11: 0 | F11: 1 | G11: 0 | H11: 1 | I11: 6 | K11: 7 | Q11: 9 | R11: 36
C12: Accid.DMR | E12: 0 | F12: 0 | G12: 0 | H12: 0 | I12: 0 | K12: 0 | Q12: 1 | R12: 9
C13: Lesión Menor | E13: 1 | F13: 0 | G13: 0 | H13: 1 | I13: 9 | K13: 8 | Q13: 16 | R13: 94
C14: Días de Descanso | E14: 0 | F14: 54 | G14: 0 | H14: 15 | I14: 150 | K14: 6068 | Q14: 121 | R14: 8202
C15: Ind.Frecuencia (1 año) | D15: 0.1 | E15: 6.85 | F15: 7.65 | G15: 0 | H15: 5.67 | I15: 4.77 | J15: =+D15 -> 0.1 | K15: 5.57 | L15: =5.09/E15*D15 -> 0.074306569 | M15: =5.13/F15*D15 -> 0.067058824 | N15: =3.61/3.61*D15 -> 0.1 | O15: =I15/H15*D15 -> 0.084126984 | Q15: 3.21 | R15: 3.05 | T15: Con 7 accid. Incapac.2009 (4 MCA y 2 MFA) + 1 MFA 2010
C16: Ind.Severidad (1 año) | D16: 0.1 | E16: 10303.79 | F16: 163.21 | G16: 0 | H16: 4917.1 | I16: 119.3 | J16: =+D16 -> 0.1 | K16: 4828.05 | L16: =128.25/E16*D16 -> 0.0012446876 | M16: =128.25/F16*D16 -> 0.078579744 | N16: =90.19/90.19*D16 -> 0.1 | O16: =I16/H16*D16 -> 0.0024262268 | Q16: 717.5 | R16: 694.94
C17: OSHA incident rate | D17: 0.1 | E17: 1.71 | F17: 4.59 | G17: 0.73 | H17: 2.43 | I17: 2.39 | J17: =+D17 -> 0.1 | K17: 2.55 | L17: =2.37/2.37*D17 -> 0.1 | M17: =2.56/F17*D17 -> 0.05577342 | N17: =2.16/2.16*D17 -> 0.1 | O17: =I17/H17*D17 -> 0.098353909 | Q17: 2.34 | R17: 2.36
C18: Calidad Investigación | D18: 0.08 | E18: 0.66 | F18: 0.788 | G18: 0.79 | H18: 0.7467 | I18: 0.85 | J18: =+I18*D18 -> 0.068 | K18: 0.7473 | L18: =+$D$18*E18 -> 0.0528 | M18: =+$D$18*F18 -> 0.06304 | N18: =+$D$18*G18 -> 0.0632 | O18: =+$D$18*H18 -> 0.059736 | R18: 0.743
C19: %Levantamiento ROM´s | D19: 0.08 | E19: 0.63 | F19: 0.567 | G19: 0.5652 | H19: 0.5962 | I19: 0.95 | J19: =+I19*D19 -> 0.076 | K19: 0.9129 | L19: =+E19*D19 -> 0.0504 | M19: =+F19*D19 -> 0.04536 | N19: =+G19*D19 -> 0.045216 | O19: =+H19*D19 -> 0.047696 | R19: 0.934
C20: %Identif.Actos Sub.ROM´s | D20: 0 | E20: 0.49 | F20: 0.58 | G20: 0.39 | H20: 0.5 | I20: 0.85 | J20: =+I20*D20 -> 0 | K20: 0.7812 | L20: =+E20*D20 -> 0 | M20: =+F20*D20 -> 0 | N20: =+G20*D20 -> 0 | O20: =+H20*D20 -> 0 | R20: 0.57
C21: %Particip.ROM´s (en el Semestre) | D21: 0 | E21: 0.37 | F21: 0.35 | G21: 0.09 | H21: 0.3 | I21: 0.6 | J21: =+I21*D21 -> 0 | K21: 0.7 | L21: =+E21*D21 -> 0 | M21: =+F21*D21 -> 0 | N21: =+G21*D21 -> 0 | O21: =+H21*D21 -> 0 | R21: 0.64
C22: %ROM´s Autofinalizadas | D22: 0 | E22: 0.48 | F22: 0.3 | G22: 0.24 | H22: 0.37 | I22: 0.55 | J22: =+I22*D22 -> 0 | K22: 0.7169 | L22: =+E22*D22 -> 0 | M22: =+F22*D22 -> 0 | N22: =+G22*D22 -> 0 | O22: =+H22*D22 -> 0
B23: E6 | C23: Cumplimiento Prog.Observ | D23: 0.04 | E23: 1 | F23: 1 | G23: 1 | H23: 1 | I23: 0.95 | J23: =+I23*D23 -> 0.038 | K23: 1 | L23: =+E23*D23 -> 0.04 | M23: =+F23*D23 -> 0.04 | N23: =+G23*D23 -> 0.04 | O23: =+H23*D23 -> 0.04 | R23: 0.95
C24: %Comportam.Seguro | D24: 0.08 | E24: 1 | F24: 0.94 | G24: 1 | H24: 0.99 | I24: 1 | J24: =+I24*D24 -> 0.08 | K24: 0.99 | L24: =+E24*D24 -> 0.08 | M24: =+F24*D24 -> 0.0752 | N24: =+G24*D24 -> 0.08 | O24: =+H24*D24 -> 0.0792 | R24: 0.968
B25: E7 | C25: Evaluación Simulacros | D25: 0.05 | E25: 0.66 | F25: 0.82 | G25: 0.79 | H25: 0.69 | I25: 0.8 | J25: =+I25*D25 -> 0.04 | K25: 0.69 | L25: =+E25*D25 -> 0.033 | M25: =+F25*D25 -> 0.041 | N25: =+G25*D25 -> 0.0395 | O25: =+H25*D25 -> 0.0345 | R25: 0.89
C26: Participación Brigadas Niv.Liderazgo | D26: 0.02 | E26: 0.9 | F26: 0.77 | G26: 1 | H26: 0.92 | I26: 0.95 | J26: =+I26*D26 -> 0.019 | K26: 0.76 | L26: =+$H$26*$D$26 -> 0.0184 | M26: =+$H$26*$D$26 -> 0.0184 | N26: =+$H$26*$D$26 -> 0.0184 | O26: =+$H$26*$D$26 -> 0.0184 | R26: 0.75
B27: E8 | C27: Efectividad Perm.Trabajo | D27: 0.05 | E27: 1 | F27: 1 | G27: 0.99 | H27: 0.99 | I27: 1 | J27: =+I27*D27 -> 0.05 | K27: 1 | L27: =+E27*D27 -> 0.05 | M27: =+F27*D27 -> 0.05 | N27: =+G27*D27 -> 0.0495 | O27: =+H27*D27 -> 0.0495 | R27: 0.977
C28: %Particip.Fiscalización Permisos | D28: 0 | E28: 0.19 | F28: 0.51 | H28: 0.43 | I28: 0.7 | J28: =+I28*D28 -> 0 | K28: 0.6 | L28: =+E28*D28 -> 0 | M28: =+F28*D28 -> 0 | N28: =+G28*D28 -> 0 | O28: =+H28*D28 -> 0
B29: E11 | C29: %Cumplim.EPP | D29: 0.05 | E29: 0.91 | F29: 0.99 | G29: 0.91 | H29: 0.93 | I29: 1 | J29: =+I29*D29 -> 0.05 | K29: 0.99 | L29: =+E29*D29 -> 0.0455 | M29: =+F29*D29 -> 0.0495 | N29: =+G29*D29 -> 0.0455 | O29: =+H29*D29 -> 0.0465 | R29: 0.98
B30: E12 | C30: Examen médico Ingresantes | D30: 0.03 | H30: 0.96 | I30: 0.95 | J30: =+I30*D30 -> 0.0285 | K30: 0.96 | L30: =+$H$30*$D$30 -> 0.0288 | M30: =+$H$30*$D$30 -> 0.0288 | N30: =+$H$30*$D$30 -> 0.0288 | O30: =+$H$30*$D$30 -> 0.0288 | R30: 0.92
C31: Examen preventivo | D31: 0.02 | H31: 0.97 | I31: 0.95 | J31: =+I31*D31 -> 0.019 | K31: 0.97 | L31: =+O31 -> 0.0194 | M31: =+O31 -> 0.0194 | N31: =+O31 -> 0.0194 | O31: =+H31*D31 -> 0.0194 | R31: 0.98
B32: E19 | C32: Homologación Proveedores | D32: 0.08 | H32: 0.79 | I32: 0.9 | J32: =+I32*D32 -> 0.072 | K32: 0.79 | L32: =+O32 -> 0.0632 | M32: =+O32 -> 0.0632 | N32: =+O32 -> 0.0632 | O32: =+H32*D32 -> 0.0632 | R32: 0.8
C33: Total %TSPM | D33: =SUM(D4:D32) -> 1 | E33: =+L33 -> 0.75785126 | F33: =+M33 -> 0.78931199 | G33: =+N33 -> 0.899116 | H33: =+O33 -> 0.77546712 | I33: =+J33 -> 0.9545 | J33: =SUM(J4:J32) -> 0.9545 | K33: 0.83395402 | L33: =SUM(L4:L32) -> 0.75785126 | M33: =SUM(M4:M32) -> 0.78931199 | N33: =SUM(N4:N32) -> 0.899116 | O33: =SUM(O4:O32)+0.004 -> 0.77546712 | R33: 0.718
D35: Sin IF, IS | E35: 0.5823 | F35: 0.5879 | G35: 0.599116 | H35: 0.59056 | I35: 0.6545

Sheet MAR
B1: TSPM A MARZO 2010
B3: Elem | C3: Indicador | D3: Peso Ponderado | E3: MCA | F3: MFA | G3: MSR | H3: Molinos Lima | I3: OBJ MAX | K3: Mol Lima 2009 | L3: MCA | M3: MFA | N3: MSR | O3: Molinos Lima | Q3: Alicorp | R3: OBJ MAX | S3: 2009 | U3: Comentarios Mol.Lima
B4: E2 | C4: Asistencia Capacitación | D4: 0.04 | E4: 0.72 | F4: 0.53 | G4: 0.86 | H4: 0.7 | I4: 0.9 | J4: =+I4*D4 -> 0.036 | K4: 0.91 | L4: =+E4*$D$4 -> 0.0288 | M4: =+F4*$D$4 -> 0.0212 | N4: =+G4*$D$4 -> 0.0344 | O4: =+H4*$D$4 -> 0.028 | R4: 0.9 | S4: 0.9
B5: E3 | C5: %Cumplimiento IGP´s | D5: 0.04 | E5: 0.8333 | F5: 0.9444 | G5: 0.9375 | H5: 0.9038 | I5: 0.95 | J5: =+I5*D5 -> 0.038 | K5: 0.9754 | L5: =+E5*D5 -> 0.033332 | M5: =+F5*D5 -> 0.037776 | N5: =+G5*D5 -> 0.0375 | O5: =+H5*D5 -> 0.036152 | Q5: 0.781 | R5: 0.95 | S5: 0.9822
C6: %Identif.Actos Sub.IGP | D6: 0 | E6: 0.3255 | F6: 0.206 | G6: 0.4324 | H6: 0.3245 | I6: 0.4 | J6: =+I6*D6 -> 0 | K6: 0.3549 | L6: =+E6*D6 -> 0 | M6: =+F6*D6 -> 0 | N6: =+G6*D6 -> 0 | O6: =+H6*D6 -> 0 | Q6: 0.324 | R6: 0.4 | S6: 0.358
B7: E4 | C7: %Cumplimiento ITAR | D7: 0 | E7: 1 | F7: 1 | G7: 1 | H7: 1 | I7: 0.95 | J7: =+I7*D7 -> 0 | K7: 1 | L7: =+E7*D7 -> 0 | M7: =+F7*D7 -> 0 | N7: =+G7*D7 -> 0 | O7: =+H7*D7 -> 0 | R7: 0.95
C8: %Implementación CV | D8: 0 | I8: 1 | J8: =+I8*D8 -> 0 | K8: 1 | L8: =+E8*D8 -> 0 | M8: =+F8*D8 -> 0 | N8: =+G8*D8 -> 0 | O8: =+H8*D8 -> 0 | R8: 1
C9: Mapa de riesgo | D9: 0.04 | E9: 1 | F9: 1 | G9: 1 | H9: 1 | I9: 0.95 | J9: =+I9*D9 -> 0.038 | K9: 1 | L9: =+$D$9*E9 -> 0.04 | M9: =+$D$9*F9 -> 0.04 | N9: =+$D$9*G9 -> 0.04 | O9: =+$D$9*H9 -> 0.04 | R9: 0.95 | S9: 0.97
B10: E5 | C10: Accid.Incapacitantes 2010 | E10: 1 | F10: 1 | G10: 0 | H10: 2 | I10: 6 | K10: 7 | Q10: 13 | R10: 30 | S10: 36
C11: Accid.DMR 2010 | E11: 0 | F11: 0 | G11: 0 | H11: 0 | I11: 0 | K11: 0 | Q11: 1 | S11: 9
C12: Lesión Menor 2010 | E12: 1 | F12: 0 | G12: 0 | H12: 1 | I12: 9 | K12: 8 | Q12: 16 | R12: 97 | S12: 94
C13: Días de Descanso 2010 | E13: 30 | F13: 54 | G13: 0 | H13: 84 | I13: 150 | K13: 6068 | Q13: 271 | R13: 925 | S13: 8202
C14: HH trabajadas 2010 | E14: 153040 | F14: 108528 | G14: 61658 | H14: =SUM(E14:G14) -> 323226 | Q14: 2971176
C15: Ind.Frecuencia 2010 | E15: =+E10*1000000/E14 -> 6.5342394 | F15: =+F10*1000000/F14 -> 9.214212 | G15: =+G10*1000000/G14 -> 0 | H15: =+H10*1000000/H14 -> 6.187621 | I15: 4.77 | Q15: =+Q10*1000000/Q14 -> 4.3753719 | R15: 2.5
C16: Ind.Severidad 2010 | E16: =+E13*1000000/E14 -> 196.02718 | F16: =+F13*1000000/F14 -> 497.56745 | G16: =+G13*1000000/G14 -> 0 | H16: =+H13*1000000/H14 -> 259.88008 | I16: 119.3 | Q16: =+Q13*1000000/Q14 -> 91.209676 | R16: 78.22
C17: OSHA incident rate 2010 | E17: =(+E10+E11+E12)*200000/E14 -> 2.6136958 | F17: =(+F10+F11+F12)*200000/F14 -> 1.8428424 | G17: =(+G10+G11+G12)*200000/G14 -> 0 | H17: =(+H10+H11+H12)*200000/H14 -> 1.8562863 | I17: 2.39 | Q17: =+(Q10+Q11+Q12)*200000/Q14 -> 2.0194024 | R17: 2.2
C18: Accid.Incapacitantes (1 año) | E18: 5 | F18: 3 | G18: 0 | H18: 8 | Q18: 39
C19: Días de Descanso (1 año) | E19: 6049 | F19: 88 | G19: 0 | H19: =SUM(E19:G19) -> 6137 | Q19: 8389
C20: Total accidentes (1 año) | E20: 7 | F20: 7 | G20: 1 | H20: =SUM(E20:G20) -> 15 | Q20: =39+7+80 -> 126
C21: Ind.Frecuencia (1 año) | D21: 0.1 | E21: =5*1000000/E24 -> 8.3368765 | F21: =3*1000000/F24 -> 7.552813 | G21: =0*1000000/G24 -> 0 | H21: =+H18*1000000/H24 -> 6.2943357 | I21: 4.77 | J21: =+D21 -> 0.1 | K21: 5.57 | L21: =5.09/E21*D21 -> 0.061054041 | M21: =5.13/F21*D21 -> 0.067921713 | N21: =3.61/3.61*D21 -> 0.1 | O21: =I21/H21*D21 -> 0.075782421 | Q21: 3.3 | R21: 2.5 | S21: 3.05
C22: Ind.Severidad (1 año) | D22: 0.1 | E22: =6049*1000000/E24 -> 10085.953 | F22: =88*1000000/F24 -> 221.54918 | G22: =0*1000000/G24 -> 0 | H22: 4828.5 | I22: 119.3 | J22: =+D22 -> 0.1 | K22: 4828.05 | L22: =17.17/E22*D22 -> 0.00017023676 | M22: =128.25/F22*D22 -> 0.057887824 | N22: =90.19/90.19*D22 -> 0.1 | O22: =I22/H22*D22 -> 0.0024707466 | Q22: 710.8 | R22: 78.22 | S22: 694.94
C23: OSHA incident rate (1 año) | D23: 0.1 | E23: =E20*200000/E24 -> 2.3343254 | F23: =F20*200000/F24 -> 3.5246461 | G23: =G20*200000/G24 -> 0.72983112 | H23: 2.36 | I23: 2.39 | J23: =+D23 -> 0.1 | K23: 2.55 | L23: =2.37/2.37*D23 -> 0.1 | M23: =2.56/F23*D23 -> 0.072631406 | N23: =2.16/2.16*D23 -> 0.1 | O23: =I23/H23*D23 -> 0.10127119 | Q23: 2.1 | R23: 2.2 | S23: 2.36
C24: HH trabajadas (1 año) | E24: 599745 | F24: 397203 | G24: 274036 | H24: =SUM(E24:G24) -> 1270984 | Q24: 11801705
C25: Dias sin accidentes | E25: 8 | F25: 64 | G25: 507 | H25: 8 | Q25: 2
C26: Calidad Investigación | D26: 0.08 | E26: 0.8 | F26: 0.788 | G26: 1 | H26: 0.8 | I26: 0.85 | J26: =+I26*D26 -> 0.068 | K26: 0.7473 | L26: =+$D$26*E26 -> 0.064 | M26: =+$D$26*F26 -> 0.06304 | N26: =+$D$26*G26 -> 0.08 | O26: =+$D$26*H26 -> 0.064 | S26: 0.743
C27: %Levantamiento ROM´s | D27: 0.08 | E27: 0.75 | F27: 0.7714 | G27: 1 | H27: 0.7826 | I27: 0.95 | J27: =+I27*D27 -> 0.076 | K27: 0.9129 | L27: =+E27*D27 -> 0.06 | M27: =+F27*D27 -> 0.061712 | N27: =+G27*D27 -> 0.08 | O27: =+H27*D27 -> 0.062608 | Q27: 0.724 | R27: 0.95 | S27: 0.934
C28: %Identif.Actos Sub.ROM´s | D28: 0 | E28: 0.447 | F28: 0.8 | G28: 0.467 | H28: 0.5962 | I28: 0.5 | J28: =+I28*D28 -> 0 | K28: 0.7812 | L28: =+E28*D28 -> 0 | M28: =+F28*D28 -> 0 | N28: =+G28*D28 -> 0 | O28: =+H28*D28 -> 0 | R28: 0.5 | S28: 0.57
C29: %Particip.ROM´s (en el Semestre) | D29: 0 | E29: 0.4545 | F29: 0.4545 | G29: 0.22 | H29: 0.4047 | I29: 0.5 | J29: =+I29*D29 -> 0 | K29: 0.7 | L29: =+E29*D29 -> 0 | M29: =+F29*D29 -> 0 | N29: =+G29*D29 -> 0 | O29: =+H29*D29 -> 0 | Q29: 0.57 | R29: 0.5 | S29: 0.64
C30: %ROM´s Autofinalizadas | D30: 0 | E30: 0.43 | F30: 0.51 | G30: 0.25 | H30: 0.4506 | I30: 0.55 | J30: =+I30*D30 -> 0 | K30: 0.7169 | L30: =+E30*D30 -> 0 | M30: =+F30*D30 -> 0 | N30: =+G30*D30 -> 0 | O30: =+H30*D30 -> 0
B31: E6 | C31: Cumplimiento Prog.Observ | D31: 0.04 | E31: 1 | F31: 1 | G31: 1 | H31: 1 | I31: 0.95 | J31: =+I31*D31 -> 0.038 | K31: 1 | L31: =+E31*D31 -> 0.04 | M31: =+F31*D31 -> 0.04 | N31: =+G31*D31 -> 0.04 | O31: =+H31*D31 -> 0.04 | Q31: 0.88 | S31: 0.95
C32: %Comportam.Seguro | D32: 0.08 | E32: 1 | F32: 1 | G32: 0.95 | H32: 0.988 | I32: 0.9 | J32: =+I32*D32 -> 0.072 | K32: 0.99 | L32: =+E32*D32 -> 0.08 | M32: =+F32*D32 -> 0.08 | N32: =+G32*D32 -> 0.076 | O32: =+H32*D32 -> 0.07904 | Q32: 0.967 | R32: 0.9 | S32: 0.968
B33: E7 | C33: Evaluación Simulacros | D33: 0.05 | E33: 0.66 | F33: 0.82 | G33: 0.79 | H33: 0.69 | I33: 0.8 | J33: =+I33*D33 -> 0.04 | K33: 0.69 | L33: =+E33*D33 -> 0.033 | M33: =+F33*D33 -> 0.041 | N33: =+G33*D33 -> 0.0395 | O33: =+H33*D33 -> 0.0345 | S33: 0.89
C34: Participación Brigadas Niv.Liderazgo | D34: 0.02 | E34: 0.88 | F34: 0.64 | G34: 0.83 | H34: 0.78 | I34: 0.8 | J34: =+I34*D34 -> 0.016 | K34: 0.76 | L34: =+$H$34*$D$34 -> 0.0156 | M34: =+$H$34*$D$34 -> 0.0156 | N34: =+$H$34*$D$34 -> 0.0156 | O34: =+$H$34*$D$34 -> 0.0156 | R34: 0.8 | S34: 0.75
B35: E8 | C35: Efectividad Perm.Trabajo | D35: 0.05 | E35: 0.9881 | F35: 1 | G35: 0.9951 | H35: 0.9936 | I35: 0.95 | J35: =+I35*D35 -> 0.0475 | K35: 1 | L35: =+E35*D35 -> 0.049405 | M35: =+F35*D35 -> 0.05 | N35: =+G35*D35 -> 0.049755 | O35: =+H35*D35 -> 0.04968 | Q35: 0.964 | R35: 0.95 | S35: 0.977
C36: %Particip.Fiscalización Permisos | D36: 0 | E36: 0.27 | F36: 0.3636 | G36: 0.38 | H36: 0.3367 | I36: 0.7 | J36: =+I36*D36 -> 0 | K36: 0.6 | L36: =+E36*D36 -> 0 | M36: =+F36*D36 -> 0 | N36: =+G36*D36 -> 0 | O36: =+H36*D36 -> 0
B37: E11 | C37: %Cumplim.EPP | D37: 0.05 | E37: 0.9474 | F37: 0.9837 | G37: 0.909 | H37: 0.9399 | I37: 1 | J37: =+I37*D37 -> 0.05 | K37: 0.99 | L37: =+E37*D37 -> 0.04737 | M37: =+F37*D37 -> 0.049185 | N37: =+G37*D37 -> 0.04545 | O37: =+H37*D37 -> 0.046995 | S37: 0.98
B38: E12 | C38: Examen médico Ingresantes | D38: 0.03 | H38: 0.96 | I38: 0.95 | J38: =+I38*D38 -> 0.0285 | K38: 0.96 | L38: =+$H$38*$D$38 -> 0.0288 | M38: =+$H$38*$D$38 -> 0.0288 | N38: =+$H$38*$D$38 -> 0.0288 | O38: =+$H$38*$D$38 -> 0.0288 | S38: 0.92
C39: Examen preventivo | D39: 0.02 | H39: 0.97 | I39: 0.95 | J39: =+I39*D39 -> 0.019 | K39: 0.97 | L39: =+O39 -> 0.0194 | M39: =+O39 -> 0.0194 | N39: =+O39 -> 0.0194 | O39: =+H39*D39 -> 0.0194 | S39: 0.98
B40: E19 | C40: Homologación Proveedores | D40: 0.08 | H40: 0.79 | I40: 0.9 | J40: =+I40*D40 -> 0.072 | K40: 0.79 | L40: =+O40 -> 0.0632 | M40: =+O40 -> 0.0632 | N40: =+O40 -> 0.0632 | O40: =+H40*D40 -> 0.0632 | R40: 0.9 | S40: 0.8
C41: Total %TSPM | D41: =SUM(D4:D40) -> 1 | E41: =+L41 -> 0.76413128 | F41: =+M41 -> 0.80935394 | G41: =+N41 -> 0.949605 | H41: =+O41 -> 0.79149935 | I41: 0.95 | J41: =SUM(J4:J40) -> 0.939 | K41: 0.83395402 | L41: =SUM(L4:L40) -> 0.76413128 | M41: =SUM(M4:M40) -> 0.80935394 | N41: =SUM(N4:N40) -> 0.949605 | O41: =SUM(O4:O40)+0.004 -> 0.79149935 | R41: 0.9455 | S41: 0.718

Sheet NVO IOM
J1: ACUMULADO 2010 | N1: PROYECTADO 2010 | R1: DIC09 - NOV10
A2: MOL | C2: INCAPACIT | D2: DMR | E2: MENOR | F2: TOTAL | H2: DÍAS PERDIDOS | J2: IF | K2: IS | L2: OSHA | N2: IF | O2: IS | P2: OSHA | R2: IF | S2: IS | T2: OSHA | U2: Var.HH vs 2009
A3: MSR | B3: Dic | C3: 0 | D3: 0 | E3: 0 | F3: =+C3+D3+E3 -> 0 | H3: 0
B4: Acumulado | C4: 1 | D4: 0 | E4: 0 | F4: =+C4+D4+E4 -> 1 | H4: 30 | J4: 3.5334815 | K4: 106.00445 | L4: 0.7066963 | U4: 0.02
B5: obj 2010 | C5: 1 | D5: 0 | E5: 2 | F5: =+C5+D5+E5 -> 3 | H5: 25 | J5: 0.00 - 3.61 | K5: 0.00 - 90.19 | L5: 0.72 - 2.16
B6: 2009 | C6: 0 | D6: 0 | E6: 1 | F6: =+C6+D6+E6 -> 1 | H6: 0 | J6: 0 | K6: 0 | L6: 0.72
A7: MFA | B7: =+B3 -> Dic | C7: 1 | D7: 0 | E7: 0 | F7: =+E7+D7+C7 -> 1 | H7: 2
B8: Acumulado | C8: 4 | D8: 0 | E8: 1 | F8: =+C8+D8+E8 -> 5 | H8: 60 | J8: 8.77 | K8: 131.51 | L8: 2.19 | U8: 0.17
B9: obj 2010 | C9: 2 | D9: 0 | E9: 3 | F9: =+C9+D9+E9 -> 5 | H9: 50 | J9: 2.56 - 7.69 | K9: 64.1 - 192.4 | L9: 2.56 - 5.13
B10: 2009 | C10: 3 | D10: 0 | E10: 7 | F10: =+C10+D10+E10 -> 10 | H10: 49 | J10: 7.69 | K10: 125.68 | L10: 5.13
A11: MCA | B11: =+B3 -> Dic | C11: 0 | D11: 0 | E11: 1 | F11: =+C11+D11+E11 -> 1 | H11: 0
B12: Acumulado | C12: 4 | D12: 0 | E12: 4 | F12: =+C12+D12+E12 -> 8 | H12: 129 | J12: 6.29 | K12: 202.89 | L12: 2.52 | U12: 0.08
B13: obj 2010 | C13: 3 | D13: 0 | E13: 4 | F13: =+C13+D13+E13 -> 7 | H13: 75 | J13: 3.39 - 6.78 | K13: 84.8 - 169.6 | L13: 1.7 - 2.37
B14: 2009 | C14: 4 | D14: 0 | E14: 1 | F14: =+C14+D14+E14 -> 5 | H14: 6019 | J14: 6.78 | K14: 10205.67 | L14: 1.7
A15: Mol.Lima | B15: =+B3 -> Dic | C15: =+C11+C7+C3 -> 1 | D15: =+D11+D7+D3 -> 0 | E15: =+E11+E7+E3 -> 1 | F15: =+F11+F7+F3 -> 2 | H15: =+H11+H7+H3 -> 2
B16: Acumulado | C16: =+C12+C8+C4 -> 9 | D16: =+D12+D8+D4 -> 0 | E16: =+E4+E8+E12 -> 5 | F16: =+C16+D16+E16 -> 14 | H16: =+H12+H8+H4 -> 219 | J16: 6.55 | K16: 159.27 | L16: 2.04 | U16: 0.09
B17: obj 2010 | C17: =+C13+C9+C5 -> 6 | D17: =+D13+D9+D5 -> 0 | E17: =+E5+E9+E13 -> 9 | F17: =+C17+D17+E17 -> 15 | H17: =+H13+H9+H5 -> 150 | J17: 4.77 - 5.57 | K17: 54.10 - 119.3 | L17: 2.39 - 2.55
B18: 2009 | C18: =+C14+C10+C6 -> 7 | D18: =+D14+D10+D6 -> 0 | E18: =+E6+E10+E14 -> 9 | F18: =+C18+D18+E18 -> 16 | H18: =+H14+H10+H6 -> 6068 | J18: 5.57 | K18: 4828.1 | L18: 2.55

Sheet HISTORICO ACCIDENTES
A1: ROM | B1: PROGRAMA | C1: LUGAR | D1: AREA RESPONSABILIDAD | E1: NOMBRE | F1: Edad | G1: Puesto de Trabajo | H1: SEXO | I1: TURNO | J1: Experiencia en el Puesto Trabajo | K1: Fecha | L1: GG | M1: Descripción del Accidente de Trabajo | N1: Parte Cuerpo | O1: Año | P1: Mes | Q1: Días Perdidos x Lesión | R1: Cargo ANSI | S1: Dias + ansi | T1: FUENTE PELIGRO | U1: Actividad | V1: TIPO DE CONTACTO | W1: DAÑO | X1: Contrata | Y1: NOTA MIDOT | Z1: MODALIDAD
B2: SIDSUR | C2: SIDSUR | D2: DISTRIBUCIÓN | E2: Oswaldo Andrade Torres | F2: 46 | G2: Operador Montacarga Eléctrico Supervisor | H2: M | I2: 2do | K2: 28/04/2015 20:30 | L2: Accidente Incapacitante | M2: Esguince de tobillo durante un cambio de batería de elevador eléctrico | N2: PIE | O2: 2015 | P2: Abril | Q2: 7 | S2: 7 | T2: Batería | U2: Maniobras de equipos | W2: Esguince
B3: MOLINO SANTA ROSA | C3: MOLINO SANTA ROSA | D3: PROYECTOS | E3: Eder García Isla | F3: 29 | G3: TERCERO | H3: M | I3: 1ro | K3: 29/09/2015 13:30 | L3: Accidente Incapacitante | M3: Escobilla metálica impacta contra structura ocasionándo corte de guante y herida en el dedo índice durante limpieza mecánica. | N3: MANO | O3: 2015 | P3: Setiembre | Q3: 1 | S3: 1 | T3: Escobilla metálica | U3: proyectos | W3: Corte | X3: AC y M
B4: MOLINO FAC | C4: MOLINO FAUCETT | D4: MANTENIMIENTO | E4: Robert Anaya Esteban | F4: 42 | G4: Ayudante de Planta | H4: M | I4: 1ro | K4: 23/04/2015 13:30 | L4: Accidente Incapacitante | M4: Corte de antepalma mano izquierda por caída de vidrio. | N4: MANO | O4: 2015 | P4: Abril | Q4: 84 | S4: 84 | T4: Vidrio | U4: Durante operación productiva | W4: Corte
B5: TEAL | C5: CARAMELOS | D5: PRODUCCIÓN | E5: James Robert Choquehuanca Montalvo | F5: 50 | G5: Maquinista | H5: M | I5: 2do | K5: 17/04/2015 18:18 | L5: Accidente Incapacitante | M5: Herida cortante abierta 1ra falange dedo pulgar mano derecha | N5: MANO | O5: 2015 | P5: Abril | Q5: 51 | S5: 51 | T5: Equipo | U5: Calibrando/Regulando | W5: Corte
B6: si | C6: APT CERCADO | D6: DISTRIBUCIÓN | E6: Matías Alva Soto | F6: 55 | G6: TERCERO | H6: M | I6: 1ro | K6: 09/11/2015 13:45 | L6: Accidente Incapacitante | M6: Manipulación de stocka durante estiba en contenedor produce golpe en la pierna del accidentado. Herida abierta. | N6: PIERNA | O6: 2015 | P6: Noviembre | Q6: 3 | S6: 3 | T6: Stocka | U6: carga/descarga de camión | W6: Golpe | X6: IOLSA
B7: si | C7: CDC | D7: DISTRIBUCIÓN | E7: Edwin Roy Cabrera Chuquihuaccha | F7: 26 | G7: Ayudande de almacén B | H7: M | I7: 3ro | K7: 14/08/2015 04:05 | L7: Accidente Incapacitante | M7: Golpe en la pierna y tobillo por order piker | N7: PIE | O7: 2015 | P7: Agosto | Q7: 16 | S7: 16 | T7: Order Piker | U7: Manejando traspaleta/Montacarga | W7: Golpe
B8: si | C8: FIDEERIA LIMA | D8: PRODUCCIÓN | E8: Miguel Tolentino Escudero | F8: 45 | G8: Mecánico | H8: M | I8: 1ro | K8: 24/08/2015 09:05 | L8: Accidente Incapacitante | M8: Amputación tercio distal del dedo índice por cambio de rótula del regulador de fideos. | N8: MANO | O8: 2015 | P8: Agosto | Q8: 139 | R8: 100 | S8: 239 | T8: Equipo | U8: Mantenimiento | W8: Pérdida Falanges
B9: TEAL | C9: CARAMELO | D9: PRODUCCIÓN | E9: Julio Cesar Muñoz Garfias | F9: 32 | G9: Operario de producción | H9: M | I9: 1ro | K9: 05/08/2015 09:20 | L9: Accidente Incapacitante | M9: Herida contusa abierta en la 1ra y 2da falange del segundo dedo de la mano por atrapamiento en su intento de acomodar la masa de caramelo en la guia de la maquina | N9: MANO | O9: 2015 | P9: Agosto | Q9: 33 | S9: 33 | T9: Equipo | U9: Mantenimiento | W9: Corte
B10: TEAL | C10: PANETONES | D10: PRODUCCIÓN | E10: Precy Cesar Ruiz Secaira | F10: 41 | G10: Operario de producción | H10: M | I10: 2do | K10: 14/08/2015 15:20 | L10: Accidente Incapacitante | M10: Herida cortante abierta en 3er dedo de la mano derecha por contacto con cuchillo, mientras se manipulaba la masa de panetón hacia la olla. | N10: MANO | O10: 2015 | P10: Agosto | Q10: 15 | S10: 15 | T10: cuchillo | U10: Durante operación productiva | W10: Corte
B11: TEAL | C11: CARAMELOS | D11: PRODUCCIÓN | E11: Alex Mateo Aguilar Estrella | F11: 31 | G11: Operario de producción | H11: M | I11: 2do | K11: 24/08/2015 15:05 | L11: Accidente Incapacitante | M11: Amputación traumática parcial de la falange distal del tercer dedo de la mano izquierda por atrapamiento de dedo por mordaza accionada accidentalmente por el mismo accidentado. | N11: MANO | O11: 2015 | P11: Agosto | Q11: 144 | R11: 75 | S11: 219 | T11: Equipo | U11: Mantenimiento | W11: Pérdida Falanges
B12: si | C12: GALLETERA LIMA | D12: PROYECTOS | E12: Nicolás Mauricio Toledo Pachas | F12: 23 | G12: TERCERO | H12: M | I12: 1ro | K12: 10/06/2015 14:50 | L12: Accidente Incapacitante | M12: Baranda del primer nivel de andamio cae sobre casco del trabajador mientras retiraba una soga. | N12: CABEZA | O12: 2015 | P12: Junio | Q12: 1 | S12: 1 | T12: Andamio | U12: proyectos | W12: Golpe | X12: BUILMEP
B13: si | C13: NUTRICION ANIMAL TRUJILLO | D13: PRODUCCIÓN | E13: Juan Carlos Horna Bocanegra | G13: Operador de rociado | H13: M | I13: 3ro | K13: 20/08/2015 11:05 | L13: Accidente Incapacitante | M13: Esguince en el tobillo izquierdo al bajar de un montacargas | N13: PIE | O13: 2015 | P13: Agosto | Q13: 7 | S13: 7 | T13: Altura | U13: Manejando traspaleta/Montacarga | W13: Esguince
B14: TEAL | C14: GALLETAS | D14: OTROS | E14: Omar Jesus Silva Leyton | F14: 36 | G14: TERCERO | H14: M | I14: 1ro | J14: Accidente Incapacitante | K14: 18/04/2015 15:00 | L14: Accidente Incapacitante | M14: Herida contusa abierta en la frente, contusión parte posterior de la cabeza y luxación dedo medio de la mano derecha. | N14: CUERPO | O14: 2015 | P14: Abril | Q14: 21 | S14: 21 | T14: Andamio | U14: Mantenimiento | W14: Golpe
B15: si | C15: MOLINO SANTA ROSA | D15: PROYECTOS | E15: Rafael Fermin Rosales Mendoza | F15: 36 | G15: TERCERO | H15: M | I15: 1ro | K15: 09/07/2015 15:00 | L15: Accidente Incapacitante | M15: Fractura en 2°, 3° y 4° metacarpiano de la mano derecha y laceración del brazo izquierdo por impacto con listón de madera desprendida. | N15: BRAZO/HOMBRO | O15: 2015 | P15: Julio | Q15: 35 | S15: 35 | T15: Madero | U15: proyectos | W15: Golpe | X15: AC&M
B16: si | C16: COPSA | D16: PRODUCCIÓN | E16: Constante Mendocilla Diestra | F16: 63 | G16: LIDER LINEA EXTRACCION MECANICA | H16: M | I16: 1ro | K16: 27/08/2015 11:10 | L16: Accidente Incapacitante | M16: Traumatismo en cabeza y heridas en el rostro por choque con parte posterior de camión mientras manejaba bicicleta. | N16: CABEZA | O16: 2015 | P16: Agosto | Q16: 16 | S16: 16 | T16: Bicicleta | U16: Trasladandose | W16: Golpe
B17: si | C17: NUTRICION ANIMAL TRUJILLO | D17: VITAPRO | K17: 42356 | L17: Accidente Incapacitante | M17: Esquince en el hombro derecho durante el repaletizado de sacos de harina | N17: BRAZO/HOMBRO | O17: 2015 | P17: Diciembre | Q17: 5 | S17: 5 | T17: Sacos | U17: Durante operación productiva | W17: Esguince
B18: si | C18: DETERGENTES | D18: PRODUCCIÓN | E18: Benigno Huamán Corillo | F18: 29 | G18: Ayudante de Planta | H18: M | I18: 3ro | K18: 17/12/2015 05:46 | L18: Accidente Incapacitante | M18: Durante conducción en reversa de tranpaleta eléctrico, el trabajador se baja y su pie queda atrapado entre plataforma y ruma de paletas | N18: PIE | O18: 2015 | P18: Diciembre | Q18: 11 | S18: 11 | T18: ERE | U18: Manejando traspaleta/Montacarga | W18: Golpe
B19: si | C19: INSTANTANEOS | D19: PRODUCCIÓN | E19: Jhon Janic Vela Sandoval | F19: 32 | G19: Mezclador Instantáneos | H19: M | I19: 2do | J19: 7 años y 10 meses | K19: 17/01/2015 19:20 | L19: Accidente Incapacitante | M19: Contusión en pie derecho por aplastamiento con plataforma de acero (equipo de mezclado). Breña | N19: PIE | O19: 2015 | P19: Enero | Q19: 20 | S19: 20 | T19: Plataforma de acero | U19: Durante operación productiva | W19: Golpe
B20: si | C20: DETERGENTES | D20: ALMACEN DE INSUMOS | E20: Andrés Avelino Quispe Carhuaz | F20: 51 | G20: TERCERO | H20: M | I20: 1ro | J20: 3 años | K20: 14/01/2015 10:59 | L20: Accidente Incapacitante | M20: Golpe e inflamación de pierna izquierda por estoca de montacargas. Detergentes | N20: PIERNA | O20: 2015 | P20: Enero | Q20: 2 | S20: 2 | T20: Stocka | U20: Maniobras de equipos | W20: Golpe | X20: BAS PERUANA TRANSPORTES GIRASOLES
B21: si | C21: VITAPRO | D21: CENTRO EXPERIMENTAL - TUMBES | E21: Juan Pablo Moreno Peña | H21: M | K21: 42276.698 | L21: Accidente Incapacitante | M21: cintas metálicas del alimentador enrolladas a presión se rompe y se expande súbitamente, ocasionándole un corte en la parte superior de la mano derecha | N21: MANO | O21: 2015 | P21: Setiembre | Q21: 15 | S21: 15 | T21: Equipo | U21: Durante operación productiva | W21: Corte
B22: TEAL | C22: APT | D22: DISTRIBUCIÓN | E22: Eujenio Baldeon Cosme | F22: 0 | G22: TERCERO | H22: M | I22: 1ro | K22: 17/10/2015 16:10 | L22: Accidente Incapacitante | M22: Contusión en el hombro izquiero por impacto con liston de metal durante estibado de producto terminado | N22: BRAZO/HOMBRO | O22: 2015 | P22: Octubre | Q22: 4 | S22: 4 | T22: Camión | U22: carga/descarga de camión | W22: Golpe | X22: IOLSA
B23: si | C23: PROYECTOS | D23: PROYECTOS | E23: Freddy Rodriguez Chinchay | G23: TERCERO | H23: M | I23: 1ro | K23: 42353 | L23: Accidente Incapacitante | M23: Quemadura en dedo durante trabajo de soldadura | N23: MANO | O23: 2015 | P23: Diciembre | Q23: 16 | S23: 16 | T23: Soldadura | U23: proyectos | W23: Quemadura | X23: MANPAN
B24: si | C24: MOLINCA | D24: PRODUCCIÓN | E24: Pedro Ynfantes Vasquez | F24: 36 | G24: Preparador de Cremas | H24: M | I24: 2do | K24: 03/12/2015 20:05 | L24: Accidente Incapacitante | M24: Atrapamiento de mano y antebrazo derecho mientras realiza labores de dosificador de sal en máquina esparcidora | N24: MANO | O24: 2015 | P24: Diciembre | Q24: 60 | S24: 60 | T24: Equipo en Movimiento | U24: Limpiando equipo | W24: Fractura
B25: si | C25: SIDSUR | D25: PRODUCCIÓN | E25: Vitaliano Silloca Silloca | F25: 41 | G25: Pesador de ingredientes | H25: M | I25: 1ro | J25: 12 años y 8 meses | K25: 27/01/2015 08:30 | L25: Accidente Incapacitante | M25: Luxación-hombro por resbalón durante la limpieza y lavado de escalera de emergencia. Galletera | N25: BRAZO/HOMBRO | O25: 2015 | P25: Enero | Q25: 30 | S25: 30 | T25: Instalación | U25: Limpiando instalaciones | W25: Luxación
B26: si | C26: CDC | D26: DISTRIBUCIÓN | E26: Juan Jibaja Rojas | F26: 42 | G26: TERCERO | H26: M | I26: 1ro | J26: 10 años | K26: 30/01/2015 14:20 | L26: Accidente Incapacitante | M26: Impacto con neumático de montacargas en el tobillo genera una contusión. CDC | N26: PIERNA | O26: 2015 | P26: Enero | Q26: 261 | S26: 261 | T26: Montacargas | U26: Manejando traspaleta/Montacarga | W26: Golpe | X26: Transportes Pacífico
B27: si | C27: DETERGENTES | D27: MANTENIMIENTO | E27: José Danilo Llanos Mego | F27: 28 | G27: Técnico Mecánico | H27: M | I27: 1ro | K27: 17/01/2015 09:30 | L27: Accidente Incapacitante | M27: Fractura y corte de ligamento dedo meñique de mano derecha por atratamiento con compuerta de acero; máquina HH N°5 | N27: MANO | O27: 2015 | P27: Enero | Q27: 110 | S27: 110 | T27: Equipo | U27: Mantenimiento | W27: Fractura
B28: si | C28: COPSA | D28: PROYECTOS | E28: Samuel Chávez Tinoco | F28: 34 | G28: TERCERO | H28: M | I28: 1ro | K28: 28/01/2015 11:10 | L28: Accidente Incapacitante | M28: Exposición a gas (amoniaco) genera una afección respiratoria en azotea de planta Margarinas | N28: AFECCIÓN RESPIRATORIA | O28: 2015 | P28: Enero | Q28: 2 | S28: 2 | T28: Sustancia Quimica | U28: proyectos | W28: Contacto sustancia Quimica | X28: ALTA
B29: si | C29: COPSA | D29: PROYECTOS | E29: Cristian Javier Arias Medina | F29: 39 | G29: TERCERO | H29: M | I29: 1ro | K29: 28/01/2015 11:10 | L29: Accidente Incapacitante | M29: Exposición a gas (amoniaco) genera una cefalea en azotea de planta Margarinas | N29: AFECCIÓN RESPIRATORIA | O29: 2015 | P29: Enero | Q29: 1 | S29: 1 | T29: Sustancia Quimica | U29: proyectos | W29: Contacto sustancia Quimica | X29: ALTA
B30: si | C30: DETERGENTES | D30: PRODUCCIÓN | E30: Bruno Díaz | F30: 26 | G30: Ayudante | H30: M | I30: 3ro | K30: 04/02/2015 02:20 am | L30: Accidente Incapacitante | M30: Fractura de muñequa. Trabajador resbala y todo su peso cae sobre su cadera y muñequa. | N30: MANO | O30: 2015 | P30: Febrero | Q30: 24 | S30: 24 | T30: Piso | U30: Trasladandose | W30: Fractura
B31: si | C31: MOLINO CALLAO | D31: DISTRIBUCIÓN | E31: Joaquin Oscco Chati | F31: 47 | G31: TERCERO | H31: M | I31: 2do | K31: 22/12/2015 20:15 | L31: Accidente Incapacitante | M31: Durante operación de repaletizado trabajador siente un fuerte dolor en la rodilla izquierda. Esguince en menisco. | N31: PIERNA | O31: 2015 | P31: Diciembre | Q31: 8 | S31: 8 | T31: Saco | U31: Durante operación productiva | W31: Esguince | X31: IOLSA
C32: GALLETERA LIMA | D32: ADMINISTRACIÓN | E32: Hilda Vásquez Segovia | G32: TERCERO | H32: F | I32: 2do | K32: 17/03/2015 21:20 | L32: Accidente Incapacitante | M32: Policontusa al resbalarse en los SSHH | N32: CUERPO | O32: 2015 | P32: Marzo | Q32: 2 | S32: 2 | T32: Piso | U32: Trasladandose | W32: policontusa | X32: LIMTEK
B33: si | C33: DETERGENTES | D33: PRODUCCIÓN | E33: Percy Antonio Carranza Izaguirre | F33: 40 | G33: Operador de Máquina Envasadora | H33: M | I33: 3ro | K33: 25/02/2015 03:20 | L33: Accidente Incapacitante | M33: Atrapamiento con mordaza horizontal de máquina envasadora. Corte y quemadura 2do grado | N33: MANO | O33: 2015 | P33: Febrero | Q33: 59 | S33: 59 | T33: Equipo | U33: Calibrando/Regulando | W33: Atricción
B34: si | C34: NUTRICION ANIMAL TRUJILLO | D34: VITAPRO | E34: Iván Fuentes De La Cruz | F34: 19 | G34: TERCERO | H34: M | I34: 1ro | K34: 10/03/2015 13:45 | L34: Accidente Incapacitante | M34: Esguince 2do Grado Pulgar Mano Derecho durante limpieza en Lavatorio | N34: MANO | O34: 2015 | P34: Marzo | Q34: 7 | S34: 7 | T34: Equipo | U34: Limpiando equipo | W34: Esguince | X34: LIMTEK
B35: si | C35: CDC | D35: DISTRIBUCIÓN | E35: Franque Leonel Reluz Sosa | F35: 29 | G35: Ayudante de paletizador | H35: M | I35: 1ro | K35: 04/06/2015 14:20 | L35: Accidente Incapacitante | M35: coge uno de los fardos de detergentes apoyando el dorso de la mano derecha sobre la faja, esto ocasionó que la faja arrastre su mano en dirección del movimiento y quede atrapada entre el protector del rodillo y la faja | N35: MANO | O35: 2015 | P35: Junio | Q35: 26 | S35: 26 | T35: Faja en movimiento | U35: Durante operación productiva | W35: Quemadura
B36: si | C36: COPSA | D36: PRODUCCIÓN | E36: Hector Albites Neyra | F36: 41 | G36: Operador volante de aceites | H36: M | I36: 1ro | K36: 08/06/2015 15:00 | L36: Accidente Incapacitante | M36: corte en los dedos índice y medio de la mano izquierda con una cuchilla retráctil, debido a que la tenía sujetada con la hoja de corte expuesta, al momento de entregarla al Sr. Rojas. | N36: MANO | O36: 2015 | P36: Junio | Q36: 48 | S36: 48 | T36: Cuchilla | U36: Otros | W36: Corte
B37: si | C37: MOLINCA | D37: PRODUCCIÓN | E37: Anselmo Mendoza Acevedo | F37: 58 | H37: M | I37: 1ro | K37: 25/03/2015 07:35 | L37: Accidente Incapacitante | M37: Pérdida de falanges distales de dedo Índice y dedo medio de la mano derecha al intentar asegurar visor del volumétrico | N37: MANO | O37: 2015 | P37: Marzo | Q37: 90 | R37: 175 | S37: 265 | T37: Equipo | U37: Mantenimiento | W37: Pérdida Falanges
B38: si | C38: MOLINO CALLAO | D38: DISTRIBUCIÓN | E38: Juan José Chinguel Carhuayocllo | F38: 27 | G38: TERCERO | H38: M | I38: 2do | J38: Accidente Incapacitante | K38: 22/04/2015 16:00 | L38: Accidente Incapacitante | M38: Esguince Tobillo derecho (IOLSA) por golpe con montacarga durante carga del contenedor | N38: PIE | O38: 2015 | P38: Abril | Q38: 4 | S38: 4 | T38: Montacargas | U38: Manejando traspaleta/Montacarga | W38: Esguince | X38: IOLSA
B39: TEAL | C39: APT | D39: DISTRIBUCIÓN | E39: Edgar Gaber Turpo Quispe | F39: 41 | G39: TERCERO | H39: M | I39: 2do | K39: 05/06/2015 15:45 | L39: Accidente Incapacitante | M39: Chofer desplaza las puertas horizontalmente y dedo meñique queda atrapado entre puertas laterales. | N39: MANO | O39: 2015 | P39: Junio | Q39: 16 | S39: 16 | T39: Camión | U39: carga/descarga de camión | W39: Golpe | X39: Transportes CR
B40: TEAL | C40: CARAMELOS | D40: PRODUCCIÓN | E40: Augusto Vladimir Córdova | F40: 34 | G40: Operario de producción | H40: M | I40: 1ro | K40: 08/06/2015 12:18 | L40: Accidente Incapacitante | M40: Baja la compuerta con la mano izquierda dejando el dedo medio de la mano derecha expuesto en el marco de la compuerta aprisionando dicho dedo y causándole la lesión . | N40: MANO | O40: 2015 | P40: Junio | Q40: 95 | S40: 95 | T40: Equipo | U40: Durante operación productiva | W40: Golpe
B41: si | C41: COPSA | D41: PRODUCCIÓN | E41: Enrique Cuadrado Dominguez | F41: 49 | G41: Líder Planta Refinación Física | H41: M | I41: 3ro | K41: 09/06/2015 00:10 | L41: Accidente Incapacitante | M41: Quemaduras de 1er y 2do grado en manos y pantorrilla derecha por salpicadura de aciete caliente a través de visor. | N41: CUERPO | O41: 2015 | P41: Junio | Q41: 20 | S41: 20 | T41: Aceite | U41: Durante operación productiva | W41: Quemadura
B42: si | C42: MOLINO FAUCETT | D42: PRODUCCIÓN | E42: Mario Joya Chumpitaz | F42: 46 | G42: Coordinador de envasado | H42: M | I42: 3ro | K42: 09/03/2015 06:00 | L42: Accidente Incapacitante | M42: Herida en primer dedo de mano izquierda con daño de uña/ Fractura de dedo pulgar mano izquierda al revisar sensor en máquina SIG. | N42: MANO | O42: 2015 | P42: Marzo | Q42: 117 | S42: 117 | T42: Equipo | U42: Calibrando/Regulando | W42: Fractura
B43: si | C43: SIDSUR | D43: PRODUCCIÓN | E43: Gilmar Darwin Viza Ayquipa | F43: 22 | G43: Ayudante de Planta | H43: M | I43: 3ro | K43: 29/05/2015 01:45 | L43: Accidente Incapacitante | M43: la tarea de reproceso de harina, el trabajador Gilmar Viza Ayquipa se dobla el 1er dedo de mano izquierda con un saco con harina. | N43: MANO | O43: 2015 | P43: Mayo | Q43: 5 | S43: 5 | T43: Saco | U43: Durante operación productiva | W43: Esguince
B44: si | C44: COPSA | D44: MANTENIMIENTO | E44: Miguel Angel Marrujo Villanera | F44: 25 | G44: Instrumentista | H44: M | I44: 1ro | K44: 02/11/2015 09:00 | L44: Accidente Incapacitante | M44: Aprisión de falange distal al momento de montado de válvula neumática genera fractura de falange. | N44: MANO | O44: 2015 | P44: Noviembre | Q44: 109 | S44: 109 | T44: Equipo | U44: Mantenimiento | W44: Fractura
B45: si | C45: FIDEERIA LIMA | D45: PRODUCCIÓN | E45: Marco Santana | F45: 21 | G45: Ayudante de Producción | H45: M | I45: 3ro | K45: 13/11/2015 04:00 | L45: Accidente Incapacitante | M45: Fractura de falange durante cambio de molde por atrapamiento de dedo entre gancho de tecle y molde. | N45: MANO | O45: 2015 | P45: Noviembre | Q45: 62 | S45: 62 | T45: Molde | U45: Maniobras de equipos | W45: Fractura
B46: si | C46: FIDEERIA LIMA | D46: PRODUCCIÓN | E46: Diter Iván Liviapoma Nuñez | F46: 28 | G46: Operador Materias Primas | H46: M | I46: 2do | K46: 24/10/2015 19:08 | L46: Accidente Incapacitante | M46: Atricción de dedos entre cadena y molde en Línea L23 durante el cambio de molde genera herida contusa cortante | N46: MANO | O46: 2015 | P46: Octubre | Q46: 2 | S46: 2 | T46: Molde | U46: Durante operación productiva | W46: Atricción
B47: si | C47: MOLINO FAUCETT | D47: PRODUCCIÓN | E47: Josué Antonio Burgos Campos | F47: 23 | G47: Ayudante de Planta | H47: M | I47: 2do | K47: 22/09/2015 20:40 | L47: Accidente Incapacitante | M47: Contusión del pie izquierdo al quedar atrapado entre las maderas de una parihuela por saltar sobre ella. | N47: PIE | O47: 2015 | P47: Setiembre | Q47: 5 | S47: 5 | T47: Altura | U47: Durante operación productiva | W47: Golpe
C48: SIDSUR | D48: DISTRIBUCIÓN | E48: Heraldo Neyra Díaz | G48: TERCERO | H48: M | I48: 3ro | K48: 12/07/2014 06:55:00 a.m. | L48: Lesión Incapacitante | M48: Esguince en tobillo derecho por caida de paleta sobre su pierna durante carguio del camión | N48: PIERNA | O48: 2014 | P48: julio | Q48: 21 | S48: 21 | T48: Paleta | U48: carga/descarga de camión | W48: Golpe | X48: Transporte Pablo Nuñez
C49: CDC | D49: DISTRIBUCIÓN | E49: JUAN ALFONSO ZEVALLOS DIAZ | G49: TERCERO | H49: M | K49: 41844 | L49: Lesión Incapacitante | M49: Amputación de falange distal dedo índice mano derecha, corte y fractura falange distal dedo II durante el retiro de la bateria del montacarga para su recarga | N49: MANO | O49: 2014 | P49: julio | Q49: 349 | R49: 75 | S49: 424 | T49: Batería | U49: Maniobras de equipos | W49: Pérdida Falanges | X49: Agencia Alemana Del Peru
B50: si | C50: GALLETERA LIMA | D50: PROYECTOS | E50: ELLIO VILLAJUAN PRINCIPE | G50: TERCERO | H50: M | I50: 2do | K50: 13/10/2014 15:20 | L50: Lesión incapacitante | M50: En evaluación, fractura múltiple de antebrazo derecho al intentar limpiar polín con faja en movimiento | N50: BRAZO/HOMBRO | O50: 2014 | P50: Octubre | Q50: 208 | S50: 208 | T50: Faja en Movimiento | U50: Trajando en corrida de prueba | W50: Fractura | X50: ROMEWA
C51: MOLINO SANTA ROSA | D51: PRODUCCIÓN | E51: GILBERT EDUARDO ESPINO GUERRERO | F51: 46 | G51: Personal Alicorp | H51: M | I51: 2ro | J51: 17 años | K51: 07/11/2014 15:10 | L51: Lesión incapacitante | M51: Siendo la 15:15, luego de hacer la limpieza respectiva de fin de turno y estando la planta parada, el Sr. Gilbert Espino intenta cruzar por encima de la faja transportadora de sacos, enganchando su pie derecho con la baranda posterior, lo que origina que su rodilla derecha impacte con la baranda anterior. | N51: PIERNA | O51: 2014 | P51: Noviembre | Q51: 178 | S51: 178 | T51: Salto sobre equipo | U51: Otros | W51: Golpe
B52: TEAL | C52: APT | D52: DISTRIBUCIÓN | E52: LEANDRO ESTRADA SABINO | G52: TERCERO | H52: M | I52: 2do | K52: 31/12/2014 18:20 | L52: Lesión Incapacitante | M52: Al término de la carga de productos, los estibadores procedieron a bajar del camión, siendo el ultimo el estibador Sr. Leandro Estrada Sabino, quien para bajar de la ruma de parihuelas hacia el piso decide sentarse sobre la misma y apoyarse con la mano derecha sobre el filo posterior de la plataforma del camión, dando un pequeño salto hacia el piso, en forma paralela el Chofer de la Unidad de Transporte de la Empresa Megatrans S.R.L. Sr. Crescencio Alberca Huaman cierra la puerta posterior izquierda de manera intempestiva sin percatarse de la presencia del Sr. Estrada, aprisionando los dedos de su mano derecha entre la plataforma y la parte inferior de la puerta, provocándole una lesión que tuvo como consecuencia la amputación traumática parcial de la falange distal del tercer y cuarto dedo de dicha mano. | N52: MANO | O52: 2014 | P52: Diciembre | Q52: 263 | R52: 135 | S52: 398 | T52: Camión | U52: carga/descarga de camión | W52: Pérdida Falanges
B53: TEAL | C53: CARAMELO | D53: PRODUCCIÓN | E53: Rosmel Tenorio Ortiz | F53: 19 | G53: Personal TEAL | H53: M | I53: 2do | J53: 7 meses | K53: 04/01/2014 16:00 | L53: Lesión Incapacitante | M53: En circunstancias que el Sr. Tenorio había encendido la maquina envolvedora de caramelo perita para el inicio de las operaciones y procedía a guiar la lamina de envoltura con caramelo perita con sus dedos de su mano derecha entre las fajas de transporte hacia la mordaza, apoya inconscientemente su mano izquierda en el rodillo vertical que da movimiento a la faja en sentido anti horario, quedando la primera falange de su dedo anular aprisionado entre la faja y el rodillo en referencia, provocándole una herida contusa abierta en dicha zona. Cabe precisar que el Sr. Tenorio no estaba autorizado para la operación de esta maquina envolvedora, la misma que se utiliza esporádicamente (bimensualmente) y solamente es operado por los maquinistas Brenner Panta y Cesar Ore. En el momento del accidente, el Supervisor de Turno Oscar Orrego se encontraba relevándose con su compañero Sr. Urrutia. | N53: MANO | O53: 2014 | P53: enero | Q53: 9 | S53: 9 | T53: Equipo | U53: Calibrando/Regulando | W53: Atricción
B54: TEAL | C54: GALLETAS | D54: PRODUCCIÓN | G54: Personal TEAL | K54: 06/01/2014 | L54: Lesión Incapacitante | M54: Encajado Galletas Soda Granel.Atricción dedo polin y faja | N54: MANO | O54: 2014 | P54: enero | Q54: 6 | S54: 6 | T54: Faja en movimiento | U54: Durante operación productiva | W54: Atricción
B55: si | C55: GALLETERA LIMA | D55: PRODUCCIÓN | E55: Narciso Vergaray Enrique | F55: 39 | G55: Personal Alicorp | H55: M | I55: 2do Turno | J55: 6 años 3 meses | K55: 07/01/2014 15:30 | L55: Lesión incapacitante | M55: Perdida de falange distal del dedo indice de la mano derecha del señor Narciso Vergaray Enrique en circunstancia que introdujo su mano derecha a la transmision de la cadena de la maquina envasadora A1 de la linea 3. | N55: MANO | O55: 2014 | P55: enero | Q55: 93 | R55: 100 | S55: 193 | T55: Equipo | U55: Mantenimiento | W55: Pérdida Falanges
C56: SIDSUR | D56: PRODUCCIÓN | E56: RENZO SUAREZ OLARTE | F56: 28 | G56: Personal Alicorp | H56: M | I56: 2do | J56: 0 Años | K56: 41660.181 | L56: Lesión incapacitante | M56: Siendo aproximadamente las 4:20 pm, se suscita un corte de energía eléctrica de aproximadamente 4 segundos, el mismo que origina que el horno de la Galletería pare, cuando estos eventos suceden el personal acude al horno a dar manivela (como se ve en la foto adjunta), para que la malla del horno continúe avanzando y así poder sacar la galleta que aún permanece dentro del horno, esta operación se debe realizar con celeridad debido a que mientras más tiempo permanezca la galleta en el horno mayor será la probabilidad de que esta se incendie. El horno tiene dos manivelas una a cada lado, en el lado izquierdo se encontraba Renzo dando manivela y es en esta operación que la manivela se sale de su posición de trabajo y por inercia de la acción el colaborador se da un golpe en la nariz con la misma manivela | N56: CABEZA | O56: 2014 | P56: enero | Q56: 9 | S56: 9 | T56: Manivela horno | U56: Durante operación productiva | W56: Golpe
B57: TEAL | C57: CALIDAD | D57: CALIDAD | E57: Jenny Najarro Barrientos | F57: 35 | G57: Personal TEAL | H57: F | I57: 1ro | J57: 1 año 8 meses | K57: 41660 | L57: Lesión Incapacitante | M57: En circunstancias que la Srta. Jenny Najarro realizaba el corte de una hoja de papel bond A4 utilizando un cortador con cierre de deslizamiento de toque único con la mano derecha sobre una base metálica (móvil) y una guía de regla metálica, el cortador se desliza sobre la regla impactando sobre el dedo pulgar de la mano izquierda con el cual fijaba la hoja de papel sobre la base metálica, originándole un corte profundo en dicha zona. Cabe precisar que la Srta. Jenny estaba rotulando archivadores con etiquetas de papel bond y para facilitar su trabajo de corte de papel, utilizo en vez de una tijera, el cortador con cierre de deslizamiento de toque único que es utilizado para el corte de cartones y embalajes. | N57: MANO | O57: 2014 | P57: enero | Q57: 10 | S57: 10 | T57: Cuchilla | U57: Otros | W57: Corte
C58: INSTANTANEOS | D58: PRODUCCIÓN | E58: Marco Barandarian Jimenez | F58: 34 | G58: Personal Alicorp | H58: M | I58: 1ro | J58: 4 años | K58: 41661.41 | L58: Lesión incapacitante | M58: El colaborador se encontraba alimentando azúcar a la Tolva 1 y al realizar el traspaso de sacos de azúcar de 50 kg. de la paleta hacia la plataforma de alimentación sin ayuda es cuando siente una molestia en el hombro del brazo izquierdo y avisó al coordinador. | N58: BRAZO/HOMBRO | O58: 2014 | P58: enero | Q58: 6 | S58: 6 | T58: Sacos | U58: Manipulación Materiales/Herramientas | W58: Esguince
C59: DETERGENTES | D59: PRODUCCIÓN | E59: PEÑA VILCHEZ MIGUEL ANGEL | F59: 25 | G59: Personal Alicorp | H59: M | I59: 2do | J59: 8 meses | K59: 18/02/2014 21:30 | L59: Lesión Incapacitante | M59: EL Trabajador Miguel Peña Vilchez se encontraba regulando el film de Bolívar Matic 1.5 kg luego de haberla bloqueado la Envasadora y al estar con la mano izquierda jalando el film a la altura de las mordazas, con la derecha se apoya en la mordaza cerrándola sobre los dedos de su mano izquierda sufriendo las quemaduras ( cuando la máquina está bloqueada las mordazas están sueltas, pueden correr con la mano. No tienen presión ) . | N59: MANO | O59: 2014 | P59: febrero | Q59: 16 | S59: 16 | T59: Equipo | U59: Calibrando/Regulando | W59: Quemadura
B60: si | C60: MOLINO CALLAO | D60: PRODUCCIÓN | E60: Jose Chavez Sanchez | F60: 54 | G60: TERCERO | H60: M | I60: 1ro | J60: 16 años | K60: 41688.576 | L60: Lesión incapacitante | M60: Mientras se realizaba el reproceso de sacos rotos, el Sr. José Chavez, procedía a bajar uno de los sacos que se encontraba en la parte superior de la parihuela (6 camas de alto), dicha operación la realizaba sosteniendo una cuchilla en su mano derecha. En el momento de bajar el saco este se rompe originando un corte en su pierna derecha con la cuchilla que sostenía. | N60: PIERNA | O60: 2014 | P60: febrero | Q60: 10 | S60: 10 | T60: Cuchilla | U60: Recuperación producto terminado | W60: Corte | X60: OILSA
C61: GALLETERA LIMA | D61: RELACIONES LABORALES | E61: Reyna Casavilca Huatay | F61: 29 | G61: TERCERO | H61: F | I61: 1er Turno | J61: 1 mes y 15 dias | K61: 19/02/2014 11:00 | L61: Lesión incapacitante | M61: El día del accidente a la hora del almuerzo en pleno servicio, a falta de abastecimiento de verduras en el Salad Bar, la jefa del Concesionario REGIS “Ana Romero” le indicó a la moza que apoyara en el corte de lechuga. Mientras la moza realizaba el corte con un cuchillo es que se ocasiona a ella misma un corte en el dedo medio de la mano izquierda. | N61: MANO | O61: 2014 | P61: febrero | Q61: 2 | S61: 2 | T61: Cuchillo | U61: Cocinando | W61: Corte | X61: Regis
C62: INSTANTANEOS | D62: ADMINISTRACIÓN | E62: Jose Inca Quispe | F62: 19 | G62: TERCERO | H62: M | I62: 2do | J62: 2 mese | K62: 41694.823 | L62: Lesión incapacitante | M62: El operario Jose Luis Inca Condori se disponía a realizar el mechoneo del segundo piso de planta de producción (sector de abastos - a un lado del área de mezclado). Para cambiar el mechón, el operario usó una cuchilla hechiza para cortar los precintos de plástico con los cuales se había asegurado el mechón a la base. Mientras cortaba el precinto se produce un corte profundo en la palma izquierda. | N62: MANO | O62: 2014 | P62: febrero | Q62: 3 | S62: 3 | T62: Cuchilla | U62: Manipulación Materiales/Herramientas | W62: Corte | X62: Limtek
B63: si | C63: MOLINO CALLAO | D63: DISTRIBUCIÓN | E63: Daniel Fernandez Chavez | F63: 57 | G63: TERCERO | H63: M | I63: 3ro | J63: 2 años 5 meses | K63: 41694.208 | L63: Lesión incapacitante | M63: Debido a trabajos de pintado y reparación de techos en el CD NPI por recomendaciones de DIGESA, se había trasladado parte del producto al patio de maniobras. La madrugada del lunes 24-Feb comenzó a llover, el asistente de turno, Juan Sihuas, se da cuenta que parte del producto en patio se encontraba desmantado, para lo cual indica al operario de montacargas Marco Santos que revise el estado del material. Marco Santos, se acerca a la zona y solicita apoyo al personal de Limtek para mantear el producto, el Sr. Santos se retira de la zona dejando al personal de Limtek, Daniel Fernandez y Hamilton Canales, realizando la tarea. El Sr. Fernandez sube por sus propios medios sobre la ruma de 2.7 m de alto y termina de mantear el producto con ayuda del Sr. Canales quien se encontraba en la parte de abajo. Finalizada la tarea el Sr. Canales va a buscar apoyo para bajar a su compañero Fernandez y al volver lo encuentra en el piso producto de haber pisado un espacio vacío entre paletas. | N63: CABEZA | O63: 2014 | P63: febrero | Q63: 7 | S63: 7 | T63: Altura | U63: Manipulación Materiales/Herramientas | W63: Golpe | X63: Limtek
C64: SIDSUR | D64: PRODUCCIÓN | E64: MIGUEL CHOQUE TARIFA | F64: 47 | G64: Personal Alicorp | H64: M | I64: 2do | J64: 13 Años | K64: 41720.83 | L64: Lesión incapacitante | M64: A las 7:55 pm el colaborador Miguel Choque Tarifa detecta fuga de harina en el 4° piso del molino Victoria por la tubería de reproceso. Para acceder a la zona afectada utiliza una escalera de tijera, una vez eliminada la fuga se dispone a recoger la harina derramada y limpiar el piso. Mientras continua con la limpieza del sector, se da cuenta que la harina no fluye normalmente, por o que procede a acceder nuevamente a la zona afectada. Mientras esta subiendo por la escalera siente que esta se desliza lo que origina que Miguel se desestabilice, Miguel acentúa el pie derecho sobre la escalera originando que esta se voltee y él caiga al piso sobre su brazo izquierdo, Miguel llama por teléfono al coordinador del molino para informarle que sufrió un accidente , el coordinador procede a llamar a la ambulancia Rescate 11-11 para que sea atendido, seguidamente es evacuado a la Clínica San Juan de Dios, donde el traumatólogo de turno diagnostica fractura del húmero brazo izquierdo | N64: BRAZO/HOMBRO | O64: 2014 | P64: marzo | Q64: 120 | S64: 120 | T64: Escalera Tijera | U64: Durante operación productiva | W64: Fractura
B65: TEAL | C65: MANTENIMIENTO | D65: PRODUCCIÓN | G65: Personal TEAL | K65: 41732 | L65: Lesión Incapacitante | M65: contucion en el tobillo por rodaje que cae de altura | N65: PIERNA | O65: 2014 | P65: abril | Q65: 2 | S65: 2 | T65: Rodaje cae de altura | U65: Otros | W65: Golpe
B66: si | C66: FIDEERIA LIMA | D66: PROYECTOS | E66: Jarol Jonathan Huamán Tilce | G66: Tercero | H66: M | I66: 1ro | J66: 6 años | K66: 24/04/2014 09:00 | L66: Lesión incapacitante | M66: Siendo alrededor de las 09:00am del día jueves 24 de abril. El señor Jarol Huamán se encontraba vistiéndose para el inicio de actividades, cuando le preguntó a su compañero, el Sr. Vicente Guzmán; si el porta martillo de su cinturón podría ser cortado con la cizalla que el Sr. Guzmán portaba en ese momento. El Sr. Guzmán respondió que sí se podía, por lo que intento cortarlo. El señor Huamán se opone y comenzaron en un “juego” sobre si lo cortaba uno u otro. Producto de ello, el Sr. Guzmán intenta cortar el porta-martillo en el preciso momento en que el Sr. Huaman aproxima su mano a la cizalla ocasionándole el corte. | N66: MANO | O66: 2014 | P66: abril | Q66: 10 | S66: 10 | T66: Broma con Cizalla | U66: Otros | W66: Corte | X66: MMG
C67: COPSA | D67: PROYECTOS | E67: Roberto Rivera Ramos | F67: 63 | G67: Personal Alicorp | H67: M | I67: 1ro | J67: 7 años | K67: 27/04/2014 11:30 | L67: Lesión Incapacitante | M67: El colaborador se acerca a la zona de envasado de baldes para recoger una escoba que necesitaba para realizar limpieza de su área de trabajo. Según indica el accidentado, al ver que la escoba estaba siendo usada por unos contratistas que se encontraban en el área, procede a acercarse al módulo de la operadora de la línea LEOPAT para coger unos trapos. Es en ese momento que no se percata de la presencia del tobogán, que está en modificación por el Proyecto LINEA PATTYN ACEITES, se choca contra el mismo y sufre un corte en la región fronto – parietal. Los trabajadores del área al ver que el accidentado estaba sangrando lo asisten y activan la alarma de emergencia. | N67: CABEZA | O67: 2014 | P67: abril | Q67: 8 | S67: 8 | T67: Instalación | U67: Otros | W67: Golpe
C68: CDC | D68: DISTRIBUCIÓN | E68: ROBERTO SANTOS SUGUENZA CUEVA | G68: TERCERO | H68: M | I68: 3ro | J68: 3 meses | K68: 30/04/2014 04:00 | L68: Lesión incapacitante | M68: Resbalón en rampa Resbalón en rampa Esguince tobillo y lesión meniscal en rodilla derecha | N68: PIERNA | O68: 2014 | P68: abril | Q68: 4 | S68: 4 | T68: Piso | U68: Trasladandose | W68: Esguince | X68: Transporte Carranza
B69: si | C69: CDC | D69: DISTRIBUCIÓN | E69: JUAN CARLOS CORONADO YPANAQUE | G69: Personal Alicorp | H69: M | I69: 3ro | J69: 4 meses | K69: 06/05/2014 04:00 | L69: Lesión incapacitante | M69: Siendo las 04:00 a.m. aprox. el Sr. Juan Carlos Coronado Ypanaque, ayudante de almacén de la línea de detergente, quien se encontraba realizando sus labores de paletizador en dicha área, estaba verificando el estado de los paquetes que se desplazaban por la faja para separar los paquetes en mal estado (merma). Cuando se encontraba en su puesto fijo en la línea, final de la faja, se disponía a colocar uno de los paquetes en el pallet para paletizar, cuando lo encontró inflado con aire. Se dispuso a sacar el aire con la mano, dando palmadas, lo que ocasiona que le salpique detergente a su ojo izquierdo. Al creer que no era nada grave, acudió a los servicios higiénicos a lavarse, y no reportó lo ocurrido oportunamente. Al día siguiente evoluciono el dolor, aumentando el volumen de la hinchazón del ojo y disminución de la agudeza visual en el ojo izquierdo. Recién en ese momento acudió al tópico donde en una primera evaluación indican que posiblemente es una conjuntivis química, luego es derivado a la Clinica San Gabriel donde es examinado por el oftalmólogo quien determino que sufrió. Finalmente le dieron DM de 2 días y evolucionó favorablemente con la aplicación de gotas. | N69: OJO | O69: 2014 | P69: mayo | Q69: 2 | S69: 2 | T69: Detergente al ojo | U69: Durante operación productiva | W69: Producto al ojo
C70: FIDEERIA LIMA | D70: MANTENIMIENTO | E70: JERRY ESQUECHE | F70: 45 | G70: Personal Alicorp | H70: M | I70: 1ro | J70: 14 años | K70: 07/05/2014 09:00 | L70: Lesión incapacitante | M70: Siendo alrededor de las 09:00 am del día Miércoles 07 de Mayo , nos dirigimos con Sr. Jerry Esqueche al depósito de repuestos usados para buscar un elemento de una máquina. Al llegar al depósito (detrás de Galletera/ línea del tren) saco su llavero y se dispuso a abrir el candado , lo cual hizo y luego jaló de izquierda a derecha al final de la carrera de la puerta sufre el atrapamiento entre la puerta fija y la móvil. Al ver la parte herida (dedo índice derecho-ultima falange) muestra su uña estaba morado y salía sangre por los costados | N70: MANO | O70: 2014 | P70: mayo | Q70: 30 | S70: 30 | T70: Puerta | U70: Maniobras de equipos | W70: Atricción
B71: TEAL | C71: CARAMELOS | D71: PRODUCCIÓN | G71: Personal TEAL | K71: 41787 | L71: Lesión Incapacitante | M71: Caida por resbalón cargando balde 20lts solución láctea originando dolor lumbar | N71: CUERPO | O71: 2014 | P71: mayo | Q71: 3 | S71: 3 | T71: Piso | U71: Manipulación Materiales/Herramientas | W71: Golpe
C72: COPSA | D72: PROYECTOS | E72: Juan Jose Jave Burgos | G72: Tercero | H72: M | I72: 1ro | J72: 15 años | K72: 29/05/2014 14:15 | L72: Lesión Incapacitante | M72: El día en mención el trabajador de la empresa ALBARQ se encontraba junto a sus compañeros desmontando los vidrios templados de una mampara, es cuando al retirar el antepenúltimo paño de vidrio, la compresión de la estructura de acero inoxidable dificulta, y al forzarlo rompe el vidrio en fragmentos pequeños, produciendo dos cortes en la mano derecha del trabajador. | N72: MANO | O72: 2014 | P72: mayo | Q72: 1 | S72: 1 | T72: Vidrio | U72: Otros | W72: Corte | X72: Albarq
C73: MOLINO SANTA ROSA | D73: ALMACEN DE INSUMOS | E73: Gamarra Quinto Edwin | F73: 43 | G73: TERCERO | H73: M | I73: 1ro | J73: 25 años | K73: 41800.458 | L73: Lesión incapacitante | M73: Durante la operación de carga de parihuelas metálicas (ruma de 5 parihuelas de 180 kg. c/u); el Sr. Edwin Gamarra (chofer) ingresa al furgón del camión para dirigir esta carga. Cuando el operario de almacén acomodaba la ruma de parihuelas estas se deslizan, ocasionando que la rejilla (20 Kg. aprox.) de la paleta superior impacte sobre el pie izquierdo del chofer. | N73: PIE | O73: 2014 | P73: junio | Q73: 23 | S73: 23 | T73: Parihuela metalica | U73: Manejando traspaleta/Montacarga | W73: Golpe | X73: CHOFER
C74: COPSA | D74: PROYECTOS | E74: Jose Antonio Ramirez Condori | F74: 22 | G74: Tercero | H74: M | I74: 1ro | J74: 2 años | K74: 17/06/2014 12:00 | L74: Lesión Incapacitante | M74: El día en mención el trabajador de la empresa SIGE se encontraba junto a un compañero, cortando con maquina plasma (equipo con función similar al oxicorte y; funciona con energía eléctrica y aire comprimido) un tubo cuadrado de 5m de longitud, 16” de alto x 8” de ancho. En el transcurso de su labor, el trabajador accidentado no termina de cortar completamente el tubo cuadrado, quedando una pulgada de diferencia, por lo que en una decisión incorrecta levanta el tubo cuadrado para golpear contra la losa de concreto y así terminar de romper la pulgada de diferencia. Es ahí donde el tubo se abre y golpea el dedo pulgar izquierdo del trabajador contra la losa, causando una contusión en dicho dedo. | N74: MANO | O74: 2014 | P74: junio | Q74: 17 | S74: 17 | T74: Tubo durante corte | U74: Mantenimiento | W74: Fractura | X74: SIGE
C75: COPSA | D75: ALMACEN DE INSUMOS | E75: NAVARRO MIRANDA ALEJANDRO FELIX | F75: 42 | G75: Personal Alicorp | H75: M | I75: 1ro | J75: 7 años | K75: 04/07/2014 13:10 | L75: Lesión Incapacitante | M75: dispone a mover su silla giratoria, para lo cual la carga en la posición mostrada en la foto y al realizar un movimiento brusco y ejercer fuerza, tuerce su dedo meñique que estaba atrapado en la rendija del respaldo del asiento. | N75: MANO | O75: 2014 | P75: julio | Q75: 80 | S75: 80 | T75: Silla | U75: Moviendo silla | W75: Fractura
B76: TEAL | C76: CARAMELOS | D76: PRODUCCIÓN | G76: Personal TEAL | H76: M | I76: 1er | K76: 41473.472 | L76: Lesión Incapacitante | M76: Contusión brazo durante limpieza máquina amasadora no bloqueada | N76: BRAZO/HOMBRO | O76: 2014 | P76: julio | Q76: 2 | S76: 2 | T76: Equipo | U76: Durante operación productiva | W76: Golpe
C77: FIDEERIA LIMA | D77: PRODUCCIÓN | E77: SABOGAL CARBAJAL MOISES | F77: 36 | G77: Personal Alicorp | H77: M | I77: 2do | J77: 14 años | K77: 25/07/2014 20:00 | L77: Lesión incapacitante | M77: Corte en dedos mientras manipulaba herramienta hexagonal | N77: MANO | O77: 2014 | P77: julio | Q77: 22 | S77: 22 | T77: Herramienta | U77: Durante operación productiva | W77: Corte
B78: si | C78: FIDEERIA LIMA | D78: PRODUCCIÓN | E78: REYNER QUIROZ QUINTANA | F78: 21 | G78: TERCERO | H78: M | I78: 2do | J78: 3 meses | K78: 02/08/2014 15:15 | L78: Lesión incapacitante | M78: Atricción de antebrazo izquierdo. Herida excoriativa en antebrazo izquierdo entre faja y polin, retirando producto de la linea aun en pruebas | N78: BRAZO/HOMBRO | O78: 2014 | P78: Agosto | Q78: 10 | S78: 10 | T78: Faja en movimiento | U78: Trajando en corrida de prueba | W78: Atricción | X78: EIG
B79: si | C79: GALLETERA LIMA | D79: PRODUCCIÓN | E79: LADINES MILLA JOSE | F79: 44 | G79: Personal Alicorp | H79: M | I79: 1ro | J79: 12 años | K79: 04/08/2014 08:05 | L79: Lesión incapacitante | M79: golpe produciendo una herida en brazo izquierdo , herida de aprox 2 cm, sangrante , sin limitación funcional. | N79: MANO | O79: 2014 | P79: Agosto | Q79: 64 | S79: 64 | T79: Equipo | U79: Trasladandose | W79: Corte
B80: si | C80: GALLETERA LIMA | D80: PRODUCCIÓN | E80: Farith Bulnes Pinto | F80: 18 | G80: Personal Alicorp | H80: M | I80: 2do | J80: 5 dias | K80: 05/08/2014 15:30 | L80: Lesión incapacitante | M80: contusión frontal con la llave del agua, al momento de agacharse a recoger el shampoo en la ducha. | N80: CABEZA | O80: 2014 | P80: Agosto | Q80: 2 | S80: 2 | T80: Llave ducha | U80: Otros | W80: Golpe
B81: si | C81: GALLETERA LIMA | D81: PRODUCCIÓN | E81: HUMAN CASTILLO JIM LEONARDO | F81: 18 | G81: Personal Alicorp | H81: F | I81: 2do | J81: 6 meses | K81: 06/08/2014 16:00 | L81: Lesión incapacitante | M81: Paciente se encontraba en la zona de encajado en galletera manipulando una galleta sufre una atrición de dedo de la mano entre 2 fajas produciendo herida y daño en la uña. | N81: MANO | O81: 2014 | P81: Agosto | Q81: 7 | S81: 7 | T81: Faja en movimiento | U81: Desatorando línea | W81: Atricción
B82: TEAL | C82: SSHH | D82: PRODUCCIÓN | E82: PAREDES AMESQUITA, ROGER CIRILO | G82: Personal TEAL | H82: M | I82: 1ro | J82: 1 año | K82: 07/08/2014 14:00 | L82: Lesión incapacitante | M82: EN CIRCUNSTANCIA QUE EL OPERARIO PAREDES RETORNABA DE LOS SERVICIOS HIGIENICOS HACIA SU PUESTO DE TRABAJO, NO SE PERCATA QUE EL PISO SE ENCONTRABA MOJADO DEBIDO A LAS LABORES DE LIMPIEZA QUE SE ESTABAN REALIZANDO AL INGRESO DE LA PLANTA, POR LO CUAL RESBALA Y CAE DE ESPALDA GOLPEANDOSE LA PARTE POSTERIOR DE LA CABEZA Y COLUMNA DORSAL OCASIONANDOLE UNA HERIDA CONTUSA Y UN TRAUMATISMO ENCEFALO CRANEANO LEVE. | N82: CABEZA | O82: 2014 | P82: Agosto | Q82: 3 | S82: 3 | T82: Piso | U82: Trasladandose | W82: Golpe
B83: si | C83: NUTRICION ANIMAL TRUJILLO | D83: PRODUCCIÓN | E83: ANGEL RODRIGUEZ | G83: Personal Alicorp | H83: M | I83: 1ro | J83: 4 años | K83: 10/08/2014 08:25 | L83: Lesión incapacitante | M83: Atrición de dedo meñique mano izquierda desatorando tolva | N83: MANO | O83: 2014 | P83: Agosto | Q83: 7 | S83: 7 | T83: Equipo | U83: Desatorando línea | W83: Atricción
B84: si | C84: FIDEERIA LIMA | D84: PRODUCCIÓN | E84: Kelly Vilchez | G84: TERCERO | H84: F | I84: 2do | J84: 2 años | K84: 14/08/2014 19:15 | L84: Lesión incapacitante | M84: Luxacion en Tobillo pie derecho | N84: PIE | O84: 2014 | P84: Agosto | Q84: 1 | S84: 1 | T84: Otro | U84: Otros | W84: Luxación | X84: E&G
B85: TEAL | C85: GALLETAS | D85: PRODUCCIÓN | E85: CURILLA VILLAVERDE, PETER ADOLFO | G85: Personal TEAL | H85: M | I85: 1ro | J85: 15 dias | K85: 21/08/2014 13:15 | L85: Lesión incapacitante | M85: EN CIRCUNSTANCIAS QUE EL SEÑOR ADOLFO CURILLA VILLAVERDE PERSONAL DEL ÁREA DE LA CÁMARA DE FERMENTACIÓN DE GALLETA SODA, REALIZABA LA OPERACIÓN VOLCADO DE COCHE CON REMEZCLA DE MASA PARA GALLETA SODA, UNA VEZ QUE EL COCHE SE ENCUENTRA EN POSICIÓN HORIZONTAL DECIDE LIMPIAR CON UNA ESPÁTULA METÁLICA DE MANGO LARGO LAS PAREDES INTERNAS DEL COCHE DEBIDO A LA PRESENCIA DE RESTOS DE MASA ADHERIDAS, LUEGO PROCEDE A RECOGER LOS RESTOS DE MASA CON EL RECOGEDOR DEJANDO DENTRO DEL COCHE LA ESPÁTULA EN POSICIÓN VERTICAL, EL CUAL FUE IMPACTADO EN LA BASE CON EL RECOGEDOR EN LA OPERACIÓN DE RECOJO, EL CUAL HACE PALANCA Y SE VOLTEA, IMPACTANDO EL MANGO CON EL ROSTRO DEL OPERARIO, PROVOCÁNDOLE UNA HERIDA CONTUSA ABIERTA EN LA BOCA. | N85: CABEZA | O85: 2014 | P85: Agosto | Q85: 2 | S85: 2 | T85: Herramienta | U85: Limpiando equipo | W85: Golpe
C86: MOLINO CALLAO | D86: MANTENIMIENTO | E86: Manuel Veintimilla Noblecilla | F86: 24 | G86: TERCERO | H86: M | I86: 1ro | K86: 26/08/2014 11:30 | L86: Lesión incapacitante | M86: Realizando Mnto a los robots salta desde una cama de paletas y cae sobre un tubo perdiendo el equilibrio y cayendo sobre su brazo izquierdo. | N86: BRAZO/HOMBRO | O86: 2014 | P86: Agosto | Q86: 30 | S86: 30 | T86: Altura | U86: Mantenimiento | W86: Golpe | X86: Andes Technology SAC
B87: si | C87: COPSA | D87: RELACIONES LABORALES | E87: MAURICIO RAUL VIDAL | G87: TERCERO | H87: M | I87: 1ro | J87: 2 mese | K87: 10/09/2014 13:11 | L87: Lesión incapacitante | M87: Presenta herida cortante de 4 cm aprox rn dedo meñique de mano derecha con abundante sangrado. | N87: MANO | O87: 2014 | P87: Septiembre | Q87: 5 | S87: 5 | T87: Cuchillo | U87: Cocinando | W87: Corte | X87: Balvino
C88: CDC | D88: DISTRIBUCIÓN | E88: OCAMPO AGUILAR JHONNY | F88: 18 | G88: Personal Alicorp | H88: M | I88: 2do | J88: 4 meses | K88: 11/09/2014 21:20 | L88: Lesión incapacitante | M88: Atricción Pie Izquierdo entre paletas | N88: PIE | O88: 2014 | P88: Septiembre | Q88: 3 | S88: 3 | T88: Paleta | U88: Otros | W88: Atricción
B89: TEAL | C89: GALLETAS | D89: PRODUCCIÓN | E89: Richard Alonso Hinojosa Barbaron | G89: Personal TEAL | H89: M | I89: 1ro | K89: 12/09/2014 07:50 | L89: Lesión incapacitante | M89: Herida contusa abierta por aplastamiento del dedo con compuerta de la sig | N89: MANO | O89: 2014 | P89: Septiembre | Q89: 15 | S89: 15 | T89: Equipo | U89: Calibrando/Regulando | W89: Atricción
B90: si | C90: SIDSUR | D90: PRODUCCIÓN | E90: Carlos Manuel Gaona Torres | F90: 41 | G90: Personal Alicorp | H90: M | I90: 1ro | J90: 18 años | K90: 17/09/2014 09:00 | L90: Lesión incapacitante | M90: Realizando la limpieza del área de paletizado con el sistema mecanizado (Brazo robot), el colaborador Carlos Manuel Gaona Torres se sube sobre los polines de desplazamiento, instante en que se resbala y se golpea la pierna derecha sufriendo una herida contuso cortante. Se solicita la presencia de la ambulancia Rescate 11-11, quienes le dan las primeras atenciones . | N90: PIERNA | O90: 2014 | P90: Septiembre | Q90: 4 | S90: 4 | T90: Equipo | U90: Limpiando equipo | W90: Golpe
B91: TEAL | C91: PANETONES | D91: PRODUCCIÓN | E91: BUSTAMANTE RIVERA HENRRY | G91: TERCERO | H91: M | I91: 1ro | K91: 23/09/2014 12:30 | L91: Lesión incapacitante | M91: FRACTURA DE DEDO durante calibración del detector de metales | N91: MANO | O91: 2014 | P91: Septiembre | Q91: 9 | S91: 9 | T91: Equipo | U91: Calibrando/Regulando | W91: Fractura
B92: si | C92: NUTRICION ANIMAL TRUJILLO | D92: ALMACEN DE INSUMOS | E92: MARCO MENDOZA CORREA | G92: TERCERO | H92: M | I92: 1ro | J92: 4 meses | K92: 23/09/2014 08:00 | L92: Lesión incapacitante | M92: golpe en el hombro con bobina plastica | N92: BRAZO/HOMBRO | O92: 2014 | P92: Septiembre | Q92: 3 | S92: 3 | T92: bobina | U92: Manipulación Materiales/Herramientas | W92: Golpe
C93: PROYECTOS | D93: PROYECTOS | E93: ESPINO REYES ALEXIS | F93: 22 | G93: TERCERO | H93: M | I93: 2do | K93: 24/09/2014 15:20 | L93: Lesión incapacitante | M93: Dx traumatismo y aplastamiento de rodilla izq al bajar maquina de soldar por las escaleras | N93: PIERNA | O93: 2014 | P93: Septiembre | Q93: 26 | S93: 26 | T93: Caida objeto | U93: Maniobras de equipos | W93: Golpe
B94: TEAL | C94: PANETONES | D94: PRODUCCIÓN | E94: ELIAS RAMIREZ TORRES | G94: Personal TEAL | H94: M | I94: 1ro | K94: 02/10/2014 12:00 | L94: Lesión incapacitante | M94: Quemadura puntual de Segundo Grado por salpicadura de silicona (panetones) | N94: CABEZA | O94: 2014 | P94: Octubre | Q94: 5 | S94: 5 | T94: Silicona | U94: Durante operación productiva | W94: Quemadura
B95: TEAL | C95: GALLETAS | D95: PRODUCCIÓN | E95: DAVID JUSTAMANTE LUNA | G95: Personal TEAL | H95: M | I95: 1ro | K95: 06/10/2014 7:50 | L95: Lesión incapacitante | M95: realizaba la operación de limpieza y desinfección de la superficie externa de la banda sanitaria del transportador de apilado inclinado-Enfriado Línea-3, se percata de que uno de los polines internos presentaba restos de polvillo de galletas y decide limpiarlo cuando esta se encontraba en movimiento, inclinándose para introducir su mano Izquierda utilizando un trapo industrial, en ese momento el trapo es jalado y atrapado entre el polín y la banda que giraba en sentido horario; en ese instante el operario por tratar de retirar el trapo sus dedos índice y medio de su mano izquierda es aprisionado, ocasionándole una atricción severa (desgarramiento de piel) en dichos dedos. | N95: MANO | O95: 2014 | P95: Octubre | Q95: 13 | S95: 13 | T95: Faja en movimiento | U95: Limpiando equipo | W95: Atricción
C96: SIDSUR | D96: PRODUCCIÓN | E96: JAVIER PAREDES BECERRA | F96: 36 | G96: Personal Alicorp | H96: M | I96: 1ro | K96: 12/10/2014 9:20 | L96: Lesión incapacitante | M96: Pérdida de pieza dentaria cortes internos y externos labio inferior | N96: CABEZA | O96: 2014 | P96: Octubre | Q96: 7 | S96: 7 | T96: Piso | U96: Trasladandose | W96: Golpe
C97: BALANCEADOS LIMA | D97: ALMACEN DE INSUMOS | E97: AGURTO CORONADO JEXI | G97: TERCERO | H97: M | I97: 2do | K97: 14/10/2014 15:01 | L97: Lesión incapacitante | M97: Policontuso Contusión en rodilla d/c fractura descargando sacos de camión | N97: PIERNA | O97: 2014 | P97: Octubre | Q97: 38 | S97: 38 | T97: Sacos | U97: carga/descarga de camión | W97: Golpe
C98: CDI | D98: CDI | E98: ANDREA BALLARDO CUZCANO | F98: 29 | G98: Personal Alicorp | H98: M | I98: 1ro | K98: 15/10/2014 10:00 | L98: Lesión incapacitante | M98: Quemadura de II grado en manos | N98: MANO | O98: 2014 | P98: Octubre | Q98: 10 | S98: 10 | T98: Producto | U98: Cocinando | W98: Quemadura
C99: MOLINO SANTA ROSA | D99: PRODUCCIÓN | E99: EUSEBIO CHAPOÑAN SAN | F99: 44 | G99: Personal Alicorp | H99: M | I99: 1ro | K99: 30/10/2014 12:30 | L99: Lesión incapacitante | M99: contusion parte baja de la espalda al resbalar | N99: CUERPO | O99: 2014 | P99: Octubre | Q99: 5 | S99: 5 | T99: Piso | U99: Trasladandose | W99: Golpe
B100: TEAL | C100: GALLETAS | D100: PRODUCCIÓN | E100: ANGEL JESUS PRIETO LAZO | G100: Personal TEAL | H100: M | I100: 1ro | K100: 03/11/2014 11:35 | L100: Lesión incapacitante | M100: En circunstancias que el Operario de Producción Sr. Ángel Prieto Lazo realizaba el traslado del coche de masa de soda para ubicarlo en la parte posterior de la cámara de fermentación, por la estrechez del espacio la rueda del coche choca con la barra de protección de impacto de la pared lateral izquierdo de la cámara, haciendo que esta rebote, venciendo la fuerza del operario y choque con otro coche aledaño, aprisionándole su dedo índice de la mano derecha, provocándole una herida contusa abierta en dicha parte de la mano. | N100: MANO | O100: 2014 | P100: Noviembre | Q100: 13 | S100: 13 | T100: Coches masa galleta | U100: Durante operación productiva | W100: Golpe
...

Sheet HH 3EROS
A1: SEDES | B1: Ene | C1: Feb | D1: Mar | E1: Abr | F1: May | G1: Jun | H1: Jul | I1: Ago | J1: Set | K1: Oct | L1: Nov | M1: Dic
A2: Almacén Suc.Pucallpa | B2: 890 | C2: 1020 | D2: 960 | E2: 916 | F2: 924 | G2: 0 | H2: 0 | I2: 0 | J2: 0 | K2: 0 | L2: 0 | M2: 0 | N2: Los Jefes de DC
A3: Almacén Suc.Tarapoto | B3: 182 | C3: 168 | D3: 182 | E3: 632 | F3: 650 | G3: 0 | H3: 0 | I3: 0 | J3: 0 | K3: 0 | L3: 0 | M3: 0
A4: Almacén Suc.Chiclayo | B4: 9918 | C4: 8999 | D4: 9772 | E4: 9454 | F4: 10090 | G4: 9837 | H4: 9550 | I4: 9877 | J4: 9877 | K4: 9379 | L4: 9487 | M4: 9487
A5: Almacén Suc.Trujillo | B5: 6474 | C5: 6148 | D5: 6022 | E5: 5357 | F5: 5499 | G5: 5297 | H5: 5184 | I5: 5456 | J5: 5456 | K5: 4796 | L5: 4767 | M5: 4537
A6: Almacén Suc.Cusco | B6: 10000 | C6: 12000 | D6: 12200 | E6: 12200 | F6: 12200 | G6: 12200 | H6: 12200 | I6: 12200 | J6: 12200 | K6: 12200 | L6: 12200 | M6: 11500
A7: Almacén Suc.Huánuco | B7: 0 | C7: 0 | D7: 0 | E7: 0 | F7: 0 | G7: 0 | H7: 0 | I7: 0 | J7: 0 | K7: 0 | L7: 0 | M7: 0
A8: Almacén Suc.Piura | B8: 4542 | C8: 4648 | D8: 6003 | E8: 4973 | F8: 5729 | G8: 6215 | H8: 5937 | I8: 6188 | J8: 5997 | K8: 6039 | L8: 7641 | M8: 6648
A9: Almacén Suc.Iquitos | B9: 584 | C9: 645 | D9: 540 | E9: 584 | F9: 610 | G9: 610 | H9: 610 | I9: 0 | J9: 0 | K9: 0 | L9: 0
A10: Sidsur - Adm (SCAST) | B10: 0 | C10: 0 | D10: 0 | E10: 0 | F10: 0 | G10: 0 | H10: 0 | I10: 0 | J10: 0 | K10: 0 | L10: 0 | M10: 0
A11: Sidsur - RRLL (SCAST) | B11: 0 | C11: 0 | D11: 0 | E11: 0 | F11: 0 | G11: 0 | H11: 0 | I11: 0 | J11: 0 | K11: 0 | L11: 0 | M11: 0
A12: Sidsur - Producción (SCAST) | B12: 0 | C12: 0 | D12: 0 | E12: 0 | F12: 0 | G12: 0 | H12: 0 | I12: 0 | J12: 0 | K12: 0 | L12: 0 | M12: 0 | N12: X
A13: Sidsur - Proyectos (SCAST) | B13: 0 | C13: 0 | D13: 0 | E13: 0 | F13: 0 | G13: 0 | H13: 0 | I13: 0 | J13: 0 | K13: 0 | L13: 0 | M13: 0
A14: Sidsur - Distribución (SCAST) | B14: 0 | C14: 0 | D14: 0 | E14: 0 | F14: 0 | G14: 0 | H14: 0 | I14: 0 | J14: 0 | K14: 0 | L14: 0 | M14: 0
A15: Predio Central - Adm (SCAST) | B15: 35169.06 | C15: 28920.71 | D15: 33982.76 | E15: 35523.34 | F15: 32470.82 | G15: 44835.14 | H15: 38872.76 | I15: 45661.08 | J15: 52570.61 | K15: 56459.16 | L15: 47023.81 | M15: =22030.28+370+1097+726+7493 -> 31716.28 | N15: Nuevo SCAST 2.0
A16: Predio Central - RRLL (SCAST) | B16: 0 | C16: 0 | D16: 0 | E16: 0 | F16: 0 | G16: 0 | H16: 311.63 | I16: 264.74 | J16: 316.07 | K16: 409.58 | L16: 416.51 | M16: =182.13+613 -> 795.13
A17: Predio Central - Galleteria (SCAST) | B17: 7892.81 | C17: 7360.16 | D17: 10810.17 | E17: 10018.19 | F17: 18201.05 | G17: 17141.38 | H17: 18601.79 | I17: 16404.26 | J17: 10865.7 | K17: 14501.42 | L17: 9205.04 | M17: =4767.36+2806 -> 7573.36
A18: Predio Central - MFA (SCAST) | B18: 7043.87 | C18: 4818.61 | D18: 5749.88 | E18: 6576.86 | F18: 9054.64 | G18: 6909.47 | H18: 14315.56 | I18: 7197.9 | J18: 19320.1 | K18: 4943.91 | L18: 7161.62 | M18: =3292.03+5423 -> 8715.03
A19: Predio Central - Fideeria (SCAST) | B19: 7565.71 | C19: 11566.96 | D19: 12050.61 | E19: 13854.92 | F19: 11464.27 | G19: 15203.68 | H19: 7712.79 | I19: 10453.69 | J19: 11299.53 | K19: 7714.67 | L19: 9828.21 | M19: =4789.98+430 -> 5219.98
A20: Predio Central - Copsa (SCAST) | B20: 39399.65 | C20: 32294.81 | D20: 30396.56 | E20: 33838.53 | F20: 57060 | G20: 19013.49 | H20: 27679.37 | I20: 13181.85 | J20: 12234.48 | K20: 22938.93 | L20: 17675.27 | M20: =11911.9+11043 -> 22954.9
A21: Predio Central - Detergentes (SCAST) | B21: 7523.3 | C21: 6719.16 | D21: 7208.3 | E21: 8325.64 | F21: 8749.75 | G21: 8639.79 | H21: 6857.84 | I21: 3682.37 | J21: 5172.23 | K21: 6811.89 | L21: 3864.5 | M21: =114.35+552 -> 666.35
A22: Predio Central - Jaboneria (SCAST) | B22: 5.51 | C22: 0 | D22: 42.72 | E22: 1963.45 | F22: 44.65 | G22: 64.16 | H22: 2127.81 | I22: 1831.15 | J22: 30.31 | K22: 48.68 | L22: 1844.96 | M22: 221.36
A23: Predio Central - Proyectos (SCAST) | B23: 32478.94 | C23: 26241.3 | D23: 33890.53 | E23: 34188.98 | F23: 15053.48 | G23: 38346.18 | H23: 32240.63 | I23: 39739.84 | J23: 46508.94 | K23: 36744.2 | L23: 20489.6 | M23: =7906.31+90+5855+443+5890 -> 20184.31
A24: Predio Central - Distribución (SCAST) | B24: 9144.5 | C24: 9921.12 | D24: 12201.03 | E24: =401.23+6262.15 -> 6663.38 | F24: =220.03+8645.16 -> 8865.19 | G24: =223.84+13964.81 -> 14188.65 | H24: =351.75+9250.49 -> 9602.24 | I24: =912.48+704.43 -> 1616.91 | J24: =6514.44+435.27 -> 6949.71 | K24: =5963.54+572.92 -> 6536.46 | L24: =2009.61+8002.15 -> 10011.76 | M24: =860.33+4753.57+105+365+87 -> 6170.9
A25: MSR - Adm (SCAST) | B25: 2591 | C25: 3177.79 | D25: 3598.47 | E25: 3601.91 | F25: 1968.56 | G25: 5176.15 | H25: 5704.97 | I25: 4968.03 | J25: 6161.68 | K25: 6684.38 | L25: 6229.86 | M25: =3630.9+606 -> 4236.9
A26: MSR - RRLL (SCAST) | B26: 0 | C26: 0 | D26: 0 | E26: 0 | F26: 0 | G26: 0 | H26: 0 | I26: 0 | J26: 0 | K26: 0 | L26: 0 | M26: 0
A27: MSR - Producción (SCAST) | B27: 1930.57 | C27: 1366.81 | D27: 2341.97 | E27: 2380.62 | F27: 5314.12 | G27: 1657.07 | H27: 1023.12 | I27: 1848.74 | J27: 2275.66 | K27: 1595.54 | L27: 2410.88 | M27: =1556.86+302 -> 1858.86
A28: MSR - Proyectos (SCAST) | B28: 0 | C28: 1.66 | D28: 20.05 | E28: 6.1 | F28: 56.05 | G28: 0 | H28: 61.99 | I28: 15.61 | J28: 0 | K28: 2.09 | L28: 0 | M28: 768
A29: MSR - Distribución (SCAST) | B29: 1090.71 | C29: 1300.03 | D29: 1582.41 | E29: 1472.28 | F29: 1221.1 | G29: 1717.18 | H29: 1405.66 | I29: 1445.88 | J29: 1577.69 | K29: 1217.48 | L29: 1333.9 | M29: =804.78+48 -> 852.78
A30: MCA - Adm (SCAST) | B30: 4794.17 | C30: 3879.2 | D30: 5439.09 | E30: 6893.39 | F30: 5861.07 | G30: 4418.82 | H30: 7651.55 | I30: 7611.89 | J30: 8274.43 | K30: 9274.2 | L30: 8645.18 | M30: =4650.06+3745 -> 8395.06
A31: MCA - RRLL (SCAST) | B31: 0 | C31: 0 | D31: 0 | E31: 0 | F31: 0 | G31: 0 | H31: 7.77 | I31: 44.77 | J31: 0 | K31: 24.77 | L31: 3.36 | M31: 0
A32: MCA - Producción (SCAST) | B32: 10463.12 | C32: 10861.54 | D32: 12978.18 | E32: 15685.1 | F32: 18397.81 | G32: 17706.45 | H32: 13459.4 | I32: 11426.02 | J32: 7068.01 | K32: 7468.44 | L32: 8283.75 | M32: =4529.43+5771 -> 10300.43
A33: MCA - Proyectos (SCAST) | B33: 6069.09 | C33: 4636.23 | D33: 4544.34 | E33: 3706.49 | F33: 6777.7 | G33: 3253.68 | H33: 3835.74 | I33: 2450.92 | J33: 4118.57 | K33: 1795.41 | L33: 5513.47 | M33: =4467.77+3319 -> 7786.77
A34: MCA - Distribución (SCAST) | B34: 5007.22 | C34: 3836.94 | D34: 5291.45 | E34: 4330.09 | F34: 5942.41 | G34: 5865.25 | H34: 5707.58 | I34: 5243.12 | J34: 6010.15 | K34: 6246.08 | L34: 4954.3 | M34: =2586.24+186 -> 2772.24
A35: CD HUACHIPA - Adm (SCAST) | B35: 2316.15 | C35: 7376.68 | D35: 3536.29 | E35: 6134.41 | F35: 6224.01 | G35: 7591.66 | H35: 8726.02 | I35: 8533.81 | J35: 6980.84 | K35: 7612.63 | L35: 6329.11 | M35: 4184.95
A36: CD HUACHIPA - RRLL (SCAST) | B36: 0 | C36: 0 | D36: 0 | E36: 0 | F36: 0 | G36: 0 | H36: 0 | I36: 46.27 | J36: 0 | K36: 0 | L36: 0 | M36: 0
A37: CD HUACHIPA - Producción (SCAST) | B37: 0 | C37: 56.48 | D37: 115.73 | E37: 0 | F37: 263.43 | G37: 2882.59 | H37: 207.07 | I37: 0 | J37: 12.64 | K37: 629.54 | L37: 159.4 | M37: 0
A38: CD HUACHIPA - Proyectos (SCAST) | B38: 0 | C38: 0 | D38: 77.46 | E38: 0 | F38: 7.16 | G38: 0 | H38: 0 | I38: 24.34 | J38: 453.61 | K38: 0 | L38: 0 | M38: 0
A39: CD HUACHIPA - Distribución (SCAST) | B39: 3585.44 | C39: 1088.24 | D39: 3234.88 | E39: 3723.64 | F39: 3130.3 | G39: 2624.08 | H39: 6082.39 | I39: 5159.91 | J39: 9847.16 | K39: 6869.38 | L39: 7191.71 | M39: 4557.62
A40: VIG MCA - VISITAS | B40: 584 | C40: 458 | D40: 384 | E40: 377 | F40: 671 | G40: 394 | H40: 393 | I40: 411 | J40: 360 | K40: 348 | L40: 379 | M40: 347 | N40: Enviado por vigilancia 5
A41: VIG MCA - CONTRATISTAS | B41: 6097 | C41: 6705 | D41: 4465 | E41: 3782 | F41: 5579 | G41: 4859 | H41: 3523 | I41: 6200 | J41: 2767 | K41: 2176 | L41: 2333 | M41: 4632
A42: VIG MCA - VIGILANCIA | B42: 3960 | C42: 3708 | D42: 4544 | E42: 4196 | F42: 4452 | G42: 4320 | H42: 4464 | I42: 4464 | J42: 4320 | K42: 4464 | L42: 4320 | M42: 4524
A43: VIG MCA - CONCESIONARIOS | B43: 719 | C43: 949 | D43: 725 | E43: 473 | F43: 728 | G43: 725 | H43: 573 | I43: 608 | J43: 589 | K43: 651 | L43: 565 | M43: 541
A44: VIG MCA - LIMTEK | B44: 622 | C44: 639 | D44: 797 | E44: 228 | F44: 877 | G44: 484 | H44: 329 | I44: 1288 | J44: 4951 | K44: 180 | L44: 344 | M44: 654
A45: VIG MCA - TRANSPORTES | B45: 4271 | C45: 3483 | D45: 3873 | E45: 3538 | F45: 3872 | G45: 5016 | H45: 4140 | I45: 4313 | J45: 4313 | K45: 4686 | L45: 3512 | M45: 3688
A46: VIG MSR - VISITAS | B46: 13 | C46: 5 | D46: 2 | E46: 0 | F46: 18 | G46: 33 | H46: 21 | I46: 69 | J46: 69 | K46: 69 | L46: 27 | M46: 32
A47: VIG MSR - CONTRATISTAS | B47: 617 | C47: 1050 | D47: 485 | E47: 484 | F47: 262 | G47: 160 | H47: 173 | I47: 169 | J47: 169 | K47: 169 | L47: 343 | M47: 273
A48: VIG MSR - VIGILANCIA | B48: 2232 | C48: 1656 | D48: 2423 | E48: 2268 | F48: 1428 | G48: 1188 | H48: 372 | I48: 636 | J48: 636 | K48: 636 | L48: 192 | M48: 2214
A49: VIG MSR - CONCESIONARIOS | B49: 0 | C49: 0 | D49: 0 | E49: 0 | F49: 0 | G49: 0 | H49: 0 | I49: 0 | J49: 0 | K49: 0 | L49: 0 | M49: 0
A50: VIG MSR - LIMTEK | B50: 0 | C50: 0 | D50: 0 | E50: 0 | F50: 0 | G50: 0 | H50: 0 | I50: 0 | J50: 0 | K50: 0 | L50: 0 | M50: 0
A51: VIG MSR - TRANSPORTES | B51: 347 | C51: 444 | D51: 511 | E51: 393 | F51: 637 | G51: 596 | H51: 614 | I51: 582 | J51: 582 | K51: 582 | L51: 794 | M51: 531
A52: VIG ALIANZA - VISITAS | B52: 0 | C52: 0 | D52: 0 | E52: 0 | F52: 0 | G52: 0 | H52: 0 | I52: 0 | J52: 0 | K52: 0 | L52: 0 | M52: 0
... A135: VIG BREÑA - TRANSPORTES | B135: 6 | C135: 9 | D135: 16 | E135: 8 | F135: 0 | G135: 0 | H135: 2 | I135: 3 | J135: 18 | K135: 13 | L135: 3 | M135: 2
A136: VIG SIDSUR | B136: 12893.99 | C136: 17586.16 | D136: 19033.32 | E136: 10738.13 | F136: 9894.05 | G136: 15345.56 | H136: 15055.4 | I136: 16509.19 | J136: 13377.25 | K136: 14300.24 | L136: 14903.1 | M136: 17471.46 | N136: Guillermo sidsur
A137: VIG MOL.AREQUIPA | B137: 1761.03 | C137: 2423.09 | D137: 2144.61 | E137: 2926.22 | F137: 3853.13 | G137: 2142.32 | H137: 1645.46 | I137: 2448.81 | J137: 1761.1 | K137: 1670 | L137: 2031.3 | M137: 786.52
A138: VIG CDA (SIDSUR + MOL. AREQUIPA) | B138: 11625.55 | C138: 14723.13 | D138: 16454 | E138: 10025 | F138: 9020.71 | G138: 12654.41 | H138: 12736.65 | I138: 13936.61 | J138: 15642.6 | K138: 16000 | L138: 15850.15 | M138: 16030.14 | O138: 15313.66
A139: VIG BSF | B139: 0 | C139: 0 | D139: 0 | E139: 0 | F139: 0 | G139: 0 | H139: 0 | I139: 0 | J139: 0 | K139: 0 | L139: 0 | M139: 0 | O139: 716.48
A140: VIG AGUSTINO | B140: 14134 | C140: 13236 | D140: 13236 | E140: 13236 | F140: 13236 | G140: 13236 | H140: 13236 | I140: 13236 | J140: 13236 | K140: 13236 | L140: 13236 | M140: 13236
A141: Vigilancia (Liderman)
A142: Limpieza (Limtek)
A143: Estiba (Iolsa)
A144: Transportista Reparto Local y LD
A145: Transportista Traslados
A146: Desinsectación de camiones (Flymsa)
A147: Contratista
A148: Cliente Recoge (Chofer)
A149: TOTAL | B149: =SUM(B2:B140) -> 330082.86 | C149: =SUM(C2:C140) -> 315276.15 | D149: =SUM(D2:D140) -> 349148.94 | E149: =SUM(E2:E140) -> 345372.56 | F149: =SUM(F2:F140) -> 362159.95 | G149: =SUM(G2:G140) -> 370815.23 | H149: =SUM(H2:H140) -> 367773.38 | I149: =SUM(I2:I140) -> 344355.67 | ... M149: =SUM(M2:M140) -> 302285.95 | N149: =SUM(B149:M149) -> 4134919.3
A151: RESUMEN DE DATOS
A152: MOL.STA ROSA | B152: =+B27+B46+B47 -> 2560.57 | C152: =+C27+C46+C47 -> 2421.81 | D152: =+D27+D46+D47 -> 2828.97 | E152: =+E27+E46+E47 -> 2864.62 | F152: =+F27+F46+F47 -> 5594.12 | G152: =+G27+G46+G47 -> 1850.07 | H152: =+H27+H46+H47 -> 1217.12 | I152: =+I27+I46+I47 -> 2086.74 | ... M152: =+M27+M46+M47 -> 2163.86 | N152: =SUM(B152:M152) -> 30715.96 | O152: X
A153: MOL. FAUCETT | B153: =+B18+B64+B65+B100+B101 -> 7587.02 | C153: =+C18+C64+C65+C100+C101 -> 5186.51 | D153: =+D18+D64+D65+D100+D101 -> 6326.37 | E153: =+E18+E64+E65+E100+E101 -> 7213.35 | F153: =+F18+F64+F65+F100+F101 -> 9456.7 | G153: =+G18+G64+G65+G100+G101 -> 7309.89 | H153: =+H18+H64+H65+H100+H101 -> 14756.7 | I153: =+I18+I64+I65+I100+I101 -> 7554.05 | ... M153: =+M18+M64+M65+M100+M101 -> 9089.28 | N153: =SUM(B153:M153) -> 107007.5 | O153: X
A154: MOL. CALLAO | B154: =+B32+B40+B41 -> 17144.12 | C154: =+C32+C40+C41 -> 18024.54 | D154: =+D32+D40+D41 -> 17827.18 | E154: =+E32+E40+E41 -> 19844.1 | F154: =+F32+F40+F41 -> 24647.81 | G154: =+G32+G40+G41 -> 22959.45 | H154: =+H32+H40+H41 -> 17375.4 | I154: =+I32+I40+I41 -> 18037.02 | ... M154: =+M32+M40+M41 -> 15279.43 | N154: =SUM(B154:M154) -> 202322.25 | O154: X
A155: GALLETERIA - INSTANT | B155: =+B17+B70+B71+B106+B107 -> 8305.04 | C155: =+C17+C70+C71+C106+C107 -> 7721.63 | D155: =+D17+D70+D71+D106+D107 -> 11144.57 | E155: =+E17+E70+E71+E106+E107 -> 10637.53 | F155: =+F17+F70+F71+F106+F107 -> 18656.2 | G155: =+G17+G70+G71+G106+G107 -> 17863.32 | H155: =+H17+H70+H71+H106+H107 -> 19400.5 | I155: =+I17+I70+I71+I106+I107 -> 17023.11 | ... M155: =+M17+M70+M71+M106+M107 -> 7895.09 | N155: =SUM(B155:M155) -> 154323.31 | O155: X
A156: FIDEERIA LIMA | B156: =+B19+B52+B53+B58+B59+B94+B95 -> 8021.52 | C156: =+C19+C52+C53+C58+C59+C94+C95 -> 11962.86 | D156: =+D19+D52+D53+D58+D59+D94+D95 -> 12919.66 | E156: =+E19+E52+E53+E58+E59+E94+E95 -> 14501.62 | F156: =+F19+F52+F53+F58+F59+F94+F95 -> 11981.01 | G156: =+G19+G52+G53+G58+G59++G94+G95 -> 15709.99 | H156: =+H19+H52+H53+H58+H59+H94+H95 -> 8251.33 | I156: =+I19+I52+I53+I58+I59+I94+I95 -> 10729.19 | J156: =+J19+J52+J53+J58+J59+J94+J95 -> 11528.85 | K156: =+K19+K52+K53+K58+K59+K94+K95 -> 7957.74 | L156: =+L19+L52+L53+L58+L59+L94+L95 -> 10119.15 | M156: =+M19+M52+M53+M58+M59+M94+M95 -> 5661.69 | N156: =SUM(B156:M156) -> 129344.61 | O156: X
A157: COPSA | B157: =+B20+B82+B83+B118+B119 -> 42344.27 | C157: =+C20+C82+C83+C118+C119 -> 34818.08 | D157: =+D20+D82+D83+D118+D119 -> 33264.33 | E157: =+E20+E82+E83+E118+E119 -> 36422.99 | F157: =+F20+F82+F83+F118+F119 -> 59465.83 | G157: =+G20+G82+G83+G118+G119 -> 21244.09 | H157: =+H20+H82+H83+H118+H119 -> 30106.52 | I157: =+I20+I82+I83+I118+I119 -> 15093.55 | ... M157: =+M20+M82+M83+M118+M119 -> 24800.47 | N157: =SUM(B157:M157) -> 357454.13 | O157: X
A158: JABONERIA | B158: =+B22 -> 5.51 | C158: =+C22 -> 0 | D158: =+D22 -> 42.72 | E158: =+E22 -> 1963.45 | F158: =+F22 -> 44.65 | G158: =+G22 -> 64.16 | H158: =+H22 -> 2127.81 | I158: =+I22 -> 1831.15 | ... M158: =+M22 -> 221.36 | N158: =SUM(B158:M158) -> 8224.76 | O158: X
A159: DETERGENTES | B159: =+B21 -> 7523.3 | C159: =+C21 -> 6719.16 | D159: =+D21 -> 7208.3 | E159: =+E21 -> 8325.64 | F159: =+F21 -> 8749.75 | G159: =+G21 -> 8639.79 | H159: =+H22 -> 2127.81 | I159: =+I21 -> 3682.37 | J159: =+J21 -> 5172.23 | K159: =+K21 -> 6811.89 | L159: =+L21 -> 3864.5 | M159: =+M21 -> 666.35 | N159: =SUM(B159:M159) -> 69491.09 | O159: X
A160: SIDSUR | B160: =+B12+B136+B137 -> 14655.02 | C160: =+C12+C136+C137 -> 20009.25 | D160: =+D12+D136+D137 -> 21177.93 | E160: =+E12+E136+E137 -> 13664.35 | F160: =+F12+F136+F137 -> 13747.18 | G160: =+G12+G136+G137 -> 17487.88 | H160: =+H12+H136+H137 -> 16700.86 | I160: =+I12+I136+I137 -> 18958 | ... M160: =+M12+M136+M137 -> 18257.98 | N160: =SUM(B160:M160) -> 202701.44 | O160: X
A161: DISTRIBUCION LIMA | B161: =+B24+B29+B34+B37+B39+B45+B51+B57+B63+B69+B75+B87+B88+B89+B93+B99+B105+B111+B117+B123+B124+B125+B129+B135+B140+B139 -> 39129.77 | C161: =+C24+C29+C34+C37+C39+C45+C51+C57+C63+C69+C75+C87+C88+C89+C93+C99+C105+C111+C117+C123+C124+C125+C129+C135+C140+C139 -> 34927.16 | D161: =+D24+D29+D34+D37+D39+D45+D51+D57+D63+D69+D75+D87+D88+D89+D93+D99+D105+D111+D117+D123+D124+D125+D129+D135+D140+D139 -> 41484.4 | E161: =+E24+E29+E34+E37+E39+E45+E51+E57+E63+E69+E75+E87+E88+E89+E93+E99+E105+E111+E117+E123+E124+E125+E129+E135+E140+E139 -> 38740.54 | F161: =+F24+F29+F34+F37+F39+F45+F51+F57+F63+F69+F75+F87+F88+F89+F93+F99+F105+F111+F117+F123+F124+F125+F129+F135+F140+F139 -> 38825.53 | G161: =+G24+G29+G34+G37+G39+G45+G51+G57+G63+G69+G75+G87+G88+G89+G93+G99+G105+G111+G117+G123+G124+G125+G129+G135+G140+G139 -> 47408.56 | H161: =+H24+H29+H34+H37+H39+H45+H51+H57+H63+H69+H75+H87+H88+H89+H93+H99+H105+H111+H117+H123+H124+H125+H129+H135+H140+H139 -> 42933.86 | I161: =+I24+I29+I34+I37+I39+I45+I51+I57+I63+I69+I75+I87+I88+I89+I93+I99+I105+I111+I117+I123+I124+I125+I129+I135+I140+I139 -> 33104.55 | ... M161: =+M24+M29+M34+M37+M39+M45+M51+M57+M63+M69+M75+M87+M88+M89+M93+M99+M105+M111+M117+M123+M124+M125+M129+M135+M140+M139 -> 33183.39 | N161: =SUM(B161:M161) -> 478253.99 | O161: X
A162: DISTRIBUCION PROVINCIAS | B162: =SUM(B2:B9)+B14+B138 -> 44215.55 | C162: =SUM(C2:C9)+C14+C138 -> 48351.13 | D162: =SUM(D2:D9)+D14+D138 -> 52133 | E162: =SUM(E2:E9)+E14+E138 -> 44141 | F162: =SUM(F2:F9)+F14+F138 -> 44722.71 | G162: =SUM(G2:G9)+G14+G138 -> 46813.41 | H162: =SUM(H2:H9)+H14+H138 -> 46217.65 | I162: =SUM(I2:I9)+I14+I138 -> 47657.61 | ... M162: =SUM(M2:M9)+M14+M138 -> 48202.14 | N162: =SUM(B162:M162) -> 569985.95 | O162: X
A163: ADMINISTRACION | B163: =+B10+B15+B25+B30+B35+B42+B44+B48+B50+B54+B56+B60+B62+B66+B68+B72+B74++B76+B77+B78++B80+B81+B84+B86+B90+B92+B96+B98+B102+B104+B108+B110+B112++B113+B114+B116+B117+B120+B122+B126+B128+B130+B131+B132+B133+B134+B135 -> 83262.14 | C163: =+C10+C15+C25+C30+C35+C42+C44+C48+C50+C54+C56+C60+C62+C66+C68+C72+C74++C76+C77+C78++C80+C81+C84+C86+C90+C92+C96+C98+C102+C104+C108+C110+C112++C113+C114+C116+C117+C120+C122+C126+C128+C130+C131+C132+C133+C134+C135 -> 78530.83 | D163: =+D10+D15+D25+D30+D35+D42+D44+D48+D50+D54+D56+D60+D62+D66+D68+D72+D74++D76+D77+D78++D80+D81+D84+D86+D90+D92+D96+D98+D102+D104+D108+D110+D112++D113+D114+D116+D117+D120+D122+D126+D128+D130+D131+D132+D133+D134+D135 -> 86687.13 | E163: =+E10+E15+E25+E30+E35+E42+E44+E48+E50+E54+E56+E60+E62+E66+E68+E72+E74++E76+E77+E78++E80+E81+E84+E86+E90+E92+E96+E98+E102+E104+E108+E110+E112++E113+E114+E116+E117+E120+E122+E126+E128+E130+E131+E132+E133+E134+E135 -> 91846.8 | F163: =+F10+F15+F25+F30+F35+F42+F44+F48+F50+F54+F56+F60+F62+F66+F68+F72+F74++F76+F77+F78++F80+F81+F84+F86+F90+F92+F96+F98+F102+F104+F108+F110+F112++F113+F114+F116+F117+F120+F122+F126+F128+F130+F131+F132+F133+F134+F135 -> 86626.07 | G163: =+G10+G15+G25+G30+G35+G42+G44+G48+G50+G54+G56+G60+G62+G66+G68+G72+G74++G76+G77+G78++G80+G81+G84+G86+G90+G92+G96+G98+G102+G104+G108+G110+G112++G113+G114+G116+G117+G120+G122+G126+G128+G130+G131+G132+G133+G134+G135 -> 104459.76 | H163: =+H10+H15+H25+H30+H35+H42+H44+H48+H50+H54+H56+H60+H62+H66+H68+H72+H74++H76+H77+H78++H80+H81+H84+H86+H90+H92+H96+H98+H102+H104+H108+H110+H112++H113+H114+H116+H117+H120+H122+H126+H128+H130+H131+H132+H133+H134+H135 -> 105228.03 | I163: =+I10+I15+I25+I30+I35+I42+I44+I48+I50+I54+I56+I60+I62+I66+I68+I72+I74++I76+I77+I78++I80+I81+I84+I86+I90+I92+I96+I98+I102+I104+I108+I110+I112++I113+I114+I116+I117+I120+I122+I126+I128+I130+I131+I132+I133+I134+I135 -> 108046.84 | ... M163: =+M10+M15+M25+M30+M35+M42+M44+M48+M50+M54+M56+M60+M62+M66+M68+M72+M74++M76+M77+M78++M80+M81+M84+M86+M90+M92+M96+M98+M102+M104+M108+M110+M112++M113+M114+M116+M117+M120+M122+M126+M128+M130+M131+M132+M133+M134+M135 -> 91047.7 | N163: =SUM(B163:M163) -> 1181357.2 | O163: X
A164: RRLL | B164: =+B11+B16+B26+B31+B36+B43+B49+B55+B61+B67+B73+B79+B85+B91+B97+B103+B109+B115+B121+B127+B133 -> 16787 | C164: =+C11+C16+C26+C31+C36+C43+C49+C55+C61+C67+C73+C85+C91+C97+C103+C109+C115+C121+C127+C133+C79 -> 15733 | D164: =+D11+D16+D26+D31+D36+D43+D49+D55+D61+D67+D73+D85+D91+D97+D103+D109+D115+D121+D127+D133+D79 -> 17589 | E164: =+E11+E16+E26+E31+E36+E43+E49+E55+E61+E67+E73+E85+E91+E97+E103+E109+E115+E121+E127+E133+E79 -> 17313 | F164: =+F11+F16+F26+F31+F36+F43+F49+F55+F61+F67+F73+F85+F91+F97+F103+F109+F115+F121+F127+F133+F79 -> 17748 | G164: =+G11+G16+G26+G31+G36+G43+G49+G55+G61+G67+G73+G85+G91+G97+G103+G109+G115+G121+G127+G133+G79 -> 17405 | H164: =+H11+H16+H26+H31+H36+H43+H49+H55+H61+H67+H73+H85+H91+H97+H103+H109+H115+H121+H127+H133+H79 -> 20464.4 | I164: =+I11+I16+I26+I31+I36+I43+I49+I55+I61+I67+I73+I85+I91+I97+I103+I109+I115+I121+I127+I133+I79 -> 18327.78 | J164: =+J11+J16+J26+J31+J36+J43+J49+J55+J61+J67+J73+J85+J91+J97+J103+J109+J115+J121+J127+J133+J79 -> 16154.07 | ... M164: =+M11+M16+M26+M31+M36+M43+M49+M55+M61+M67+M73+M85+M91+M97+M103+M109+M115+M121+M127+M133+M79 -> 17080.13 | N164: =SUM(B164:M164) -> 207050.6 | O164: X
A165: PROYECTOS | B165: =+B13+B23+B28+B33+B38 -> 38548.03 | C165: =+C13+C23+C28+C33+C38 -> 30879.19 | D165: =+D13+D23+D28+D33+D38 -> 38532.38 | E165: =+E13+E23+E28+E33+E38 -> 37901.57 | F165: =+F13+F23+F28+F33+F38 -> 21894.39 | G165: =+G13+G23+G28+G33+G38 -> 41599.86 | H165: =+H13+H23+H28+H33+H38 -> 36138.36 | I165: =+I13+I23+I28+I33+I38 -> 42230.71 | ... M165: =+M13+M23+M28+M33+M38 -> 28739.08 | N165: =SUM(B165:M165) -> 432089.46 | O165: X | P165: =+H166-H149 -> -4727.03
B166: =SUM(B152:B165) -> 330088.86 | C166: =SUM(C152:C165) -> 315285.15 | D166: =SUM(D152:D165) -> 349165.94 | E166: =SUM(E152:E165) -> 345380.56 | F166: =SUM(F152:F165) -> 362159.95 | G166: =SUM(G152:G165) -> 370815.23 | H166: =SUM(H152:H165) -> 363046.35 | I166: =SUM(I152:I165) -> 344362.67 | ... N166: =SUM(N152:N165) -> 4130322.3 | Q166: =+I166-I149 -> 7
A168: OTROS (TERCEROS) | B168: =SUM(B169:B173) -> 6348 | C168: =SUM(C169:C173) -> 6348 | D168: =SUM(D169:D173) -> 6348 | E168: =SUM(E169:E173) -> 6348 | F168: =SUM(F169:F173) -> 6348 | G168: =SUM(G169:G173) -> 3744 | H168: =SUM(H169:H173) -> 3744 | I168: =SUM(I169:I173) -> 3744 | ... M168: =SUM(M169:M173) -> 3744 | N168: =SUM(B168:M168) -> 57948
A169: Cardio Movil | B169: 1488 | C169: 1488 | D169: 1488 | E169: 1488 | F169: 1488 | G169: 1488 | H169: 1488 | I169: 1488 | J169: 1488 | K169: 1488 | L169: 1488 | M169: 1488
A170: Medico Ocupacional Lima | B170: 2080 | C170: 2080 | D170: 2080 | E170: 2080 | F170: 2080 | G170: 2080 | H170: 2080 | I170: 2080 | J170: 2080 | K170: 2080 | L170: 2080 | M170: 2080
A171: Manfer Ponce
A172: Apoyo Informatico | B172: 176 | C172: 176 | D172: 176 | E172: 176 | F172: 176 | G172: 176 | H172: 176 | I172: 176 | J172: 176 | K172: 176 | L172: 176 | M172: 176
A173: LICENCIADAS ENFERMERIA | B173: 2604 | C173: 2604 | D173: 2604 | E173: 2604 | F173: 2604 | G173: 0 | H173: 0 | I173: 0 | J173: 0 | K173: 0 | L173: 0 | M173: 0 | N173: SOLO HASTA MAYO 2023 | R173: 4.4 | S173: 1538.77 | T173: =+S173+R173 -> 1543.17
R174: 0 | S174: 1330.67 | T174: =+S174+R174 -> 1330.67
A175: PROYECTOS GLOBAL | B175: 2788 | C175: 2299 | D175: 1556 | E175: 454 | F175: 27 | G175: 51 | H175: 0 | I175: 104 | J175: 177 | K175: 159 | L175: 0 | M175: 0 | N175: =SUM(B175:M175) -> 7615 | O175: DATO DE SAUL | R175: 7.38 | S175: 1585.32 | T175: =+S175+R175 -> 1592.7
A176: PROYECTOS TEAL | B176: 1732 | C176: 451 | D176: 449 | E176: 34 | F176: 1143 | G176: 2394 | H176: 1073 | I176: 0 | J176: 0 | K176: 0 | L176: 0 | M176: 0 | N176: =SUM(B176:M176) -> 7276 | O176: DATO DE SAUL | R176: 5 | S176: 1398.93 | T176: =+S176+R176 -> 1403.93
A177: DISTRIBUCION TEAL | N177: =SUM(B177:M177) -> 0 | R177: 2.55 | S177: 1598.28 | T177: =+S177+R177 -> 1600.83
A178: DISTRIBUCIÓN PAITA | B178: 2359.15 | C178: 2028.97 | D178: 2341.17 | E178: 2026.38 | F178: 2427.95 | G178: 2234.27 | H178: 2376.6 | I178: 2662.67 | J178: 2288.8 | K178: 2038.45 | L178: 2155.42 | M178: 2197.05 | N178: =SUM(B178:M178) -> 27136.88 | O178: DATO PEDRO | R178: 8.52 | S178: 1716.95 | T178: =+S178+R178 -> 1725.47
A179: DISTRIBUCION GLOBAL MANPOWER | B179: 4418 | C179: 4324 | D179: 4753 | E179: 4700 | F179: 1352 | G179: 1216 | H179: 1384 | I179: 1120 | J179: 976 | K179: 979 | L179: 951 | M179: 951 | N179: =SUM(B179:M179) -> 27124 | O179: DATO GIAN FRANCO | R179: 0 | S179: 1538.83 | T179: =+S179+R179 -> 1538.83
A180: DISTRIBUCIÓN ITDC | B180: 62489 | C180: 58919 | D180: 40624 | E180: 40624 | F180: 40624 | G180: 40624 | H180: 40624 | I180: 40624 | J180: 40624 | K180: 40624 | L180: 40624 | M180: 40624 | N180: =SUM(B180:M180) -> 527648
A181: PROYECTOS ITDC | B181: 19420 | C181: 16435 | D181: 12715 | E181: 12412 | F181: 15960 | G181: 13015 | H181: 2703 | I181: 2703 | J181: 2703 | K181: 2703 | L181: 2703 | M181: 2703 | N181: =SUM(B181:M181) -> 106175 | O181: DATO DE SAUL
A182: LATAM | B182: 20598 | C182: 20909 | D182: 20909 | E182: 20909 | F182: 20909 | G182: 20909 | H182: 20909 | I182: 20909 | J182: 20909 | K182: 20909 | L182: 20909 | M182: 20909 | N182: =SUM(B182:M182) -> 250597
A183: PROYECTOS LATAM | B183: 6408 | C183: 4753 | D183: 1640 | E183: 0 | F183: 0 | G183: 0 | H183: 0 | I183: 0 | J183: 0 | K183: 0 | L183: 0 | M183: 0 | N183: =SUM(B183:M183) -> 12801 | O183: DATO DE SAUL
A184: APUDEX | B184: 34615 | C184: 34615 | D184: 34615 | E184: 34615 | F184: 34615 | G184: 34615 | H184: 34615 | I184: 34615 | J184: 34615 | K184: 34615 | L184: 34615 | M184: 34615 | N184: =SUM(B184:M184) -> 415380

Sheet HH ALICORP
A2: Sede | B2: Enero | C2: Febrero | D2: Marzo | E2: Abril | F2: Mayo | G2: Junio | H2: Julio | I2: Agosto | J2: Setiembre | K2: Octubre | L2: Noviembre | M2: Diciembre
A3: MOL. STA. ROSA | N3: Equipo de Gloria Maza
A4: MOL. FAUCETT | B4: 24796.5 | C4: 24634.5 | D4: 26511 | E4: 24890 | F4: 27204 | G4: 27075.5 | H4: 23368.5 | I4: 25739 | J4: 25870.5 | K4: 25839 | L4: 25207 | M4: 25286
A5: MOL. CALLAO | B5: 28198.5 | C5: 25303.33 | D5: 30074 | E5: 29095 | F5: 31260 | G5: 29938 | H5: 27813.95 | I5: 29947.35 | J5: 28619.77 | K5: 27409 | L5: 26309 | M5: 26620
A6: FIDEERIA LIMA | B6: 23226 | C6: 21309.5 | D6: 23675.5 | E6: 21809 | F6: 23963.5 | G6: 24721.5 | H6: 21160 | I6: 23829 | J6: 23275 | K6: 22075 | L6: 23900 | M6: 22458
A7: FIDEERIA ALIANZA
A8: DETERGENTES | B8: 26353 | C8: 21935 | D8: 27289 | E8: 23576 | F8: 26466 | G8: 27811 | H8: 26207.5 | I8: 27985 | J8: 25943 | K8: 26693 | L8: 25683 | M8: 26078
A9: SIDSUR | B9: 37583.5 | C9: 30917.5 | D9: 40576 | E9: 36556.5 | F9: 42297.5 | G9: 41371.3 | H9: 45526 | I9: 47979 | J9: 47529 | K9: 46601 | L9: 44652 | M9: 46791
A10: GALLETERA CALLAO | B10: 68717.6 | C10: 52553.65 | D10: 69514.02 | E10: 53527 | F10: 70541.05 | G10: 61611.74 | H10: 66082.5 | I10: 83672 | J10: 80963.41 | K10: 79662 | L10: 75868 | M10: 65877
A11: BAL. LIMA
A12: BAL. TRUJILLO
A13: BAL. TUMBES
A14: COPSA | B14: 156121.92 | C14: 144662.85 | D14: 166573.3 | E14: 149238.45 | F14: 167711.35 | G14: 160490.55 | H14: 147957.95 | I14: 148480.25 | J14: 156737.72 | K14: 150586 | L14: 149171 | M14: 152542
A15: CDC | B15: 120873.32 | C15: 111404.67 | D15: 123690 | E15: 116773 | F15: 126212.58 | G15: 109746.01 | H15: 114328.75 | I15: 119207.67 | J15: 124279.02 | K15: 125367 | L15: 124519 | M15: 125180
A16: CDR AREQUIPA | B16: 19316.3 | C16: 18066 | D16: 19160.25 | E16: 16959 | F16: 18965.25 | G16: 18928.5 | H16: 17740.5 | I16: 18109 | J16: 17948 | K16: 17546 | L16: 17237 | M16: 17108
A17: CDR PIURA | B17: 4520 | C17: 4510 | D17: 4797 | E17: 4707 | F17: 4822 | G17: 4754 | H17: 4674 | I17: 5239 | J17: 2466 | K17: 4556 | L17: 4410 | M17: 4990
A18: CDR TRUJILLO | B18: 7192 | C18: 6730 | D18: 7020 | E18: 6217 | F18: 6762 | G18: 6857 | H18: 6635 | I18: 6742 | J18: 7010 | K18: 7099 | L18: 6461 | M18: 6761
A19: Otras Sucursales | B19: 19850.5 | C19: 18348 | D19: 19551 | E19: 19217 | F19: 18783.5 | G19: 19022 | H19: 18391.1 | I19: 17915 | J19: 18336.55 | K19: 17739 | L19: 17363 | M19: 18279
A20: Ventas | B20: 1064 | C20: 1064 | D20: 1064 | E20: 864 | F20: 864 | G20: 1064 | H20: 1196 | I20: 1064 | J20: 1064 | K20: 1064 | L20: 1064 | M20: 1064
A21: Marketing | B21: 1800 | C21: 1600 | D21: 2200 | E21: 2000 | F21: 2000 | H21: 1800 | I21: 1932 | J21: 1732 | K21: 1732 | L21: 1732 | M21: 1732
A22: Oficina Central | B22: 276508 | C22: 277368 | D22: 279628 | E22: 281424 | F22: 284956 | G22: 289488 | H22: 288680 | I22: 288148 | J22: 289820 | K22: 288330 | L22: 274740 | M22: 276857
A25: Total | B25: =SUM(B3:B24) -> 816121.14 | C25: =SUM(C3:C24) -> 760407 | D25: =SUM(D3:D24) -> 841323.07 | E25: =SUM(E3:E24) -> 786852.95 | F25: =SUM(F3:F24) -> 852808.73 | G25: =SUM(G3:G24) -> 822879.1 | H25: =SUM(H3:H24) -> 811561.75 | I25: =SUM(I3:I24) -> 845988.27 | ... M25: =SUM(M3:M24) -> 817623 | N25: Copiar tal cual archivo de Gloria . No descontar Detergentes
A27: Jaboneria | B27: 8353 | C27: 8353 | D27: 8353 | E27: 8353 | F27: 8353 | G27: 8353 | H27: 8353 | I27: 8353 | J27: 8353 | K27: 8353 | L27: 8353 | M27: 8353
A28: Almacenes | B28: 15371.25 | C28: 13784.75 | D28: 16963.1 | E28: 14391 | F28: 16481.5 | G28: 15582 | H28: 14164.6 | I28: 14618 | J28: 14872.8 | K28: 14872.8 | L28: 13569 | M28: 14970 | N28: =SUM(B28:M28) -> 179640.8
N29: total
A30: VITAPRO TUMBES | N30: =SUM(B30:M30) -> 0
N31: total
A32: DISTRIBUCION PAITA | B32: 1543.17 | C32: 1330.67 | D32: 1592.7 | E32: 1403.93 | F32: 1600.83 | G32: 1725.47 | H32: 1538.83 | I32: 1547.15 | J32: 1448.66 | K32: 1393.2 | L32: 1492.94 | M32: 1516.8 | N32: =SUM(B32:M32) -> 18134.35
A34: Almacen Insumos&Envases-MB | B34: 230 | C34: 202 | D34: 216 | E34: 216 | F34: 0 | G34: 0 | H34: 0 | I34: 0 | J34: 0 | K34: 0 | L34: 0 | M34: 0 | N34: =SUM(B34:M34) -> 864 | O34: =+N34+N35 -> 21479.04 | P34: =+O34*6 -> 128874.24
A35: Almacen Insumos&Envases-TEAL | B35: 1714.48 | C35: 1445.83 | D35: 145.5 | E35: 1165.38 | F35: 1736.08 | G35: 2263.3 | H35: 2171.73 | I35: 2263.3 | J35: 1948.78 | K35: 2023.07 | L35: 1869 | M35: 1868.59 | N35: =SUM(B35:M35) -> 20615.04
A36: DISTRIBUCION TEAL | B36: 3623.77 | C36: 2663.25 | D36: 205.52 | E36: 2102.61 | F36: 3133.37 | G36: 2906.52 | H36: 2442.82 | I36: 2906.52 | J36: 2609.15 | K36: 2719.16 | L36: 1687 | M36: 1687 | N36: =SUM(B36:M36) -> 28686.69 | O36: =+N36*6 -> 172120.14
A37: DISTRIBUCION ITDC | B37: 6252 | C37: 6252 | D37: 6872 | E37: 6872 | F37: 6872 | G37: 6872 | H37: 6872 | I37: 6872 | J37: 6872 | K37: 6872 | L37: 6872 | M37: 6872 | N37: =SUM(B37:M37) -> 81224
A38: Almacen Insumos&Envases-ITDC | B38: 41054.93 | C38: 40646.93 | D38: 39913.2 | E38: 39913.2 | F38: 39913.2 | G38: 39913.2 | H38: 39913.2 | I38: 39913.2 | J38: 39913.2 | K38: 39913.2 | L38: 39913.2 | M38: 39913.2 | N38: =SUM(B38:M38) -> 480833.86
A39: APUDEX | B39: 14984 | C39: 15689 | D39: 15689 | E39: 15689 | F39: 15689 | G39: 15689 | H39: 15689 | I39: 15689 | J39: 15689 | K39: 15689 | L39: 15689 | M39: 15689 | N39: =SUM(B39:M39) -> 187563

Sheet HORAS HOMBRE
B1: T O T A L | BO1: P E R S O N A L T E R C E R O S (SCAST + Registros Vigilancia)
B2: MOL.STA ROSA | C2: MOL. FAUCETT | D2: MOL. CALLAO | E2: GALLETERIA - INSTANT | F2: FIDEERIA LIMA | G2: COPSA | H2: JABONERIA | I2: DETERGENTES | J2: SIDSUR | K2: DISTRIBUCION LIMA | L2: DISTRBUCION PROV | M2: ADMINISTRACION | N2: RELACION LABORAL | O2: PROYECTOS | P2: ALMACENES | Q2: OTROS | R2: Horas | S2: MOLINO PAITA | T2: TEAL | U2: VITAPRO | V2: MASTERBREAD | W2: GLOBAL | X2: INTRADEVCO | Y2: ECUADOR | Z2: BRASIL | AA2: SAN JUSTO | AB2: MORON | AC2: GARIN | AD2: CHILE | AE2: FINO WARNES | AF2: FINO CBBS | AG2: SAO | AH2: HONDURAS | AI2: MOL.STA ROSA | AJ2: MOL. FAUCETT | AK2: MOL. CALLAO | AL2: GALLETERIA - INSTANT | AM2: FIDEERIA LIMA | AN2: COPSA | AO2: JABONERIA | AP2: DETERGENTES | AQ2: SIDSUR | AR2: DISTRIBUCION LIMA | AS2: DISTRBUCION PROV | AT2: ADMINISTRACION | AU2: RELACION LABORAL | AV2: PROYECTOS | AW2: ALMACENES | AX2: OTROS | AY2: MOL PAITA | AZ2: TEAL | BA2: VITAPRO | BB2: MASTERBREAD | BC2: GLOBAL | BD2: INTRADEVCO | BE2: ECUADOR (INCLUYE BICIS 2) | BF2: BRASIL | BG2: SAN JUSTO | BH2: MORON | BI2: GARIN | BJ2: CHILE | BK2: FINO WARNES (PDF) | BL2: CBBA (COCHABAMBA) | BM2: SAO (PARQUE INDUSTRIAL) | BN2: HONDURAS | BO2: MOL.STA ROSA | BP2: MOL. FAUCETT | BQ2: MOL. CALLAO | BR2: GALLETERIA - INSTANT | BS2: FIDEERIA LIMA | BT2: COPSA | BU2: JABONERIA | BV2: DETERGENTES | BW2: SIDSUR | BX2: DISTRIBUCION LIMA | BY2: DISTRBUCION PROV | BZ2: ADMINISTRACION | CA2: RELACION LABORAL | CB2: PROYECTOS | CC2: ALMACENES | CD2: OTROS (Fenix consultores/Lic.Enfermeria) | CE2: MOL PAITA | CF2: TEAL | CG2: VITAPRO | CH2: MASTERBREAD | CI2: GLOBAL (Manpower + 3eros) | CJ2: INTRADEVCO | CK2: ECUADORN (INCLUYE BICIS 2) | CL2: BRASIL | CM2: SAN JUSTO | CN2: MORON | CO2: GARIN | CP2: CHILE | CQ2: FINO WARNES (PDF) | CR2: CBBA (COCHABAMBA) | CS2: SAO (PARQUE INDUSTRIAL) | CT2: HONDURAS | CU2: TOTAL PERU | CV2: Propios | CW2: Terceros | CX2: PERU CON ITDC | CY2: EXTRANJERSO | CZ2: ITDC
A3: 43101 | B3: =+AI3+BO3 -> 15675.76 | C3: =+AJ3+BP3 -> 53402.66 | D3: =+AK3+BQ3 -> 29679.08 | E3: =+AL3+BR3 -> 82048.43 | F3: =+AM3+BS3 -> 29198.82 | G3: =+AN3+BT3 -> 176351.3 | H3: =+AO3+BU3 -> 8003.57 | I3: =+AP3+BV3 -> 26817.9 | ... O3: =+AV3+CB3 -> 30155.32 | P3: =+AW3+CD3 -> 0 | S3: =+AY3+CE3 -> 12062.13 | T3: =+AZ3+CF3 -> 109699.44 | U3: =+BA3+CG3 -> 91073.3 | V3: =+BB3+CH3 -> 7620 | W3: =+BC3+CI3 -> 66589 | X3: =+BD3+CJ3 -> 375762.82 | Y3: =+BE3+CK3 -> 44220 | Z3: =+BF3+CL3 -> 137229.32 | ... AH3: =+BN3+CT3 -> 13217 | AI3: 10106.16 | AJ3: 43561.89 | AK3: 23869.92 | AL3: 67423.61 | AM3: 22271.65 | AN3: 148019.3 | AO3: 7186.09 | AP3: 24931 | AQ3: 36318.5 | AR3: 74971.64 | AS3: 49134.5 | AT3: 122968 | AY3: 8376.1 | AZ3: 84966.44 | BA3: 61632.3 | BB3: 7620 | BC3: 22550 | BD3: =1706909.82/12 -> 142242.49 | BE3: 44220 | BF3: 137229.32 | BG3: 77966 | BH3: 7242 | BI3: 23054 | BJ3: 48423 | BK3: 48097.73 | BL3: 45443.38 | BM3: 123650 | BN3: =158604/12 -> 13217 | BO3: 5569.6 | BP3: 9840.77 | BQ3: 5809.16 | BR3: 14624.82 | BS3: 6927.17 | BT3: 28332 | BU3: 817.48 | BV3: 1886.9 | BW3: 5065.75 | BX3: 28555.58 | BY3: 72623 | BZ3: 91047.88 | CA3: 19538.62 | CB3: 30155.32 | CE3: 3686.03 | CF3: 24733 | CG3: 29441 | CI3: 44039 | CJ3: =2802244/12 -> 233520.33 | CM3: 6900 | CN3: 4564 | CO3: 9653
A4: 43132 | B4: =+AI4+BO4 -> 16061.25 | C4: =+AJ4+BP4 -> 56472.73 | D4: =+AK4+BQ4 -> 27895.51 | E4: =+AL4+BR4 -> 96726.9 | F4: =+AM4+BS4 -> 27555.61 | G4: =+AN4+BT4 -> 171298.87 | H4: =+AO4+BU4 -> 7999.72 | I4: =+AP4+BV4 -> 31737.72 | ... O4: =+AV4+CB4 -> 27213.75 | P4: =+AW4+CD4 -> 0 | S4: =+AY4+CE4 -> 11741.7 | T4: =+AZ4+CF4 -> 98361.881 | U4: =+BA4+CG4 -> 91394.75 | V4: =+BB4+CH4 -> 7084 | W4: =+BC4+CI4 -> 68210 | X4: =+BD4+CJ4 -> 375762.82 | Y4: =+BE4+CK4 -> 39709 | Z4: =+BF4+CL4 -> 150948.33 | ... AH4: =+BN4+CT4 -> 13217 | AI4: 9970.49 | AJ4: 47338.64 | AK4: 24638.53 | AL4: 81240.68 | AM4: 22923.6 | AN4: 146921.5 | AO4: 7182.24 | AP4: 29468 | AQ4: 37985.5 | AR4: 102000.64 | AS4: 49015.5 | AT4: 122968 | AY4: 7694.19 | AZ4: 76743.881 | BA4: 60603.75 | BB4: 7084 | BC4: 27963 | BD4: =1706909.82/12 -> 142242.49 | BE4: 39709 | BF4: 150948.33 | BG4: 65062 | BH4: 16993 | BI4: 19635 | BJ4: 48423 | BK4: 35915.34 | BL4: 57732.49 | BM4: 141275 | BN4: =158604/12 -> 13217 | BO4: 6090.76 | BP4: 9134.09 | BQ4: 3256.98 | BR4: 15486.22 | BS4: 4632.01 | BT4: 24377.37 | BU4: 817.48 | BV4: 2269.72 | BW4: 3305.36 | BX4: 29217.21 | BY4: 71902 | BZ4: 94498 | CA4: 24970.047 | CB4: 27213.75 | CE4: 4047.51 | CF4: 21618 | CG4: 30791 | CI4: 40247 | CJ4: =2802244/12 -> 233520.33 | CM4: 6900 | CN4: 3928.5 | CO4: 13122.06
A5: 43160 | B5: =+AI5+BO5 -> 14166.26 | C5: =+AJ5+BP5 -> 54470.15 | D5: =+AK5+BQ5 -> 29175.42 | E5: =+AL5+BR5 -> 90204.56 | F5: =+AM5+BS5 -> 26108.68 | G5: =+AN5+BT5 -> 162591.2 | H5: =+AO5+BU5 -> 6908.74 | I5: =+AP5+BV5 -> 29946.6 | ... O5: =+AV5+CB5 -> 23887.59 | P5: =+AW5+CD5 -> 0 | S5: =+AY5+CE5 -> 11215.03 | T5: =+AZ5+CF5 -> 114941.6 | U5: =+BA5+CG5 -> 93984.85 | V5: =+BB5+CH5 -> 7636 | W5: =+BC5+CI5 -> 70919 | X5: =+BD5+CJ5 -> 375762.82 | Y5: =+BE5+CK5 -> 45803 | Z5: =+BF5+CL5 -> 148835 | ... AH5: =+BN5+CT5 -> 13217 | AI5: 8904 | AJ5: 45222.15 | AK5: 22600.25 | AL5: 82192.32 | AM5: 20580.87 | AN5: 137728.58 | AO5: 6091.26 | AP5: 26576 | AQ5: 36711 | AR5: 94230.32 | AS5: 46837.5 | AT5: 126916 | AY5: 7523.65 | AZ5: 90922.6 | BA5: 64244.75 | BB5: 7636 | BC5: 27616 | BD5: =1706909.82/12 -> 142242.49 | BE5: 45803 | BF5: 148835 | BG5: 67488 | BH5: 17934 | BI5: 23623 | BJ5: 49153 | BK5: 52281.69 | BL5: 48816.98 | BM5: 151200 | BN5: =158604/12 -> 13217 | BO5: 5262.26 | BP5: 9248 | BQ5: 6575.17 | BR5: 8012.24 | BS5: 5527.81 | BT5: =24310.62+552 -> 24862.62 | BU5: 817.48 | BV5: 3370.6 | BW5: 8125.35 | BX5: 31476.11 | BY5: 66126 | BZ5: 128706.94 | CA5: 24650.781 | CB5: 23887.59 | CE5: 3691.38 | CF5: 24019 | CG5: 29740.1 | CI5: 43303 | CJ5: =2802244/12 -> 233520.33 | CM5: 6900 | CN5: 5206.5 | CO5: 15809
A6: 43191 | B6: =+AI6+BO6 -> 16264.5 | C6: =+AJ6+BP6 -> 56354.03 | D6: =+AK6+BQ6 -> 29480.83 | E6: =+AL6+BR6 -> 102244.66 | F6: =+AM6+BS6 -> 30980.34 | G6: =+AN6+BT6 -> 177556.51 | H6: =+AO6+BU6 -> 7988.18 | I6: =+AP6+BV6 -> 31247.14 | ... O6: =+AV6+CB6 -> 20942.19 | P6: =+AW6+CD6 -> 0 | S6: =+AY6+CE6 -> 12507.73 | T6: =+AZ6+CF6 -> 112425.58 | U6: =+BA6+CG6 -> 90808.71 | V6: =+BB6+CH6 -> 8479 | W6: =+BC6+CI6 -> 73355 | X6: =+BD6+CJ6 -> 375762.82 | Y6: =+BE6+CK6 -> 42858 | Z6: =+BF6+CL6 -> 155840.63 | ... AH6: =+BN6+CT6 -> 13217 | AI6: 11135 | AJ6: 46676.66 | AK6: 23157.59 | AL6: 90284.82 | AM6: 24163.17 | AN6: 152026.51 | AO6: 7170.7 | AP6: 28417 | AQ6: 40565 | AR6: 106002.78 | AS6: 49156 | AT6: 128632 | AY6: 8525.65 | AZ6: 95085.58 | BA6: 63050 | BB6: 8479 | BC6: 22596 | BD6: =1706909.82/12 -> 142242.49 | BE6: 42858 | BF6: 155840.63 | BG6: 64965 | BH6: 18373 | BI6: 22900 | BJ6: 53666 | BK6: 52410.28 | BL6: 57383.34 | BM6: 152148 | BN6: =158604/12 -> 13217 | BO6: 5129.5 | BP6: 9677.37 | BQ6: 6323.24 | BR6: 11959.84 | BS6: 6817.17 | BT6: 25530 | BU6: 817.48 | BV6: 2830.14 | BW6: 6046.08 | BX6: 30958.84 | BY6: 76124.111 | BZ6: 102771.97 | CA6: 18735.069 | CB6: 20942.19 | CE6: 3982.08 | CF6: 17340 | CG6: 27758.71 | CI6: 50759 | CJ6: =2802244/12 -> 233520.33 | CM6: 6900 | CN6: 4669 | CO6: 15334
A7: 43221 | B7: =+AI7+BO7 -> 20570.2 | C7: =+AJ7+BP7 -> 62740.2 | D7: =+AK7+BQ7 -> 33179.85 | E7: =+AL7+BR7 -> 102753.53 | F7: =+AM7+BS7 -> 29067.58 | G7: =+AN7+BT7 -> 185606.92 | H7: =+AO7+BU7 -> 7594.21 | I7: =+AP7+BV7 -> 34061.33 | ... O7: =+AV7+CB7 -> 16434.18 | P7: =+AW7+CD7 -> 0 | S7: =+AY7+CE7 -> 12755.33 | T7: =+AZ7+CF7 -> 135812.32 | U7: =+BA7+CG7 -> 91815 | V7: =+BB7+CH7 -> 8107 | W7: =+BC7+CI7 -> 78330 | X7: =+BD7+CJ7 -> 375762.82 | Y7: =+BE7+CK7 -> 46410 | Z7: =+BF7+CL7 -> 156615 | ... AH7: =+BN7+CT7 -> 13217 | AI7: 11741.95 | AJ7: 47745.04 | AK7: 25214.71 | AL7: 90987.5 | AM7: 24141.18 | AN7: 159324.92 | AO7: 6776.73 | AP7: 30115 | AQ7: 40375 | AR7: 104565.26 | AS7: 49400.5 | AT7: 128680 | AY7: 8706.35 | AZ7: 109643.32 | BA7: 62383 | BB7: 8107 | BC7: 29502 | BD7: =1706909.82/12 -> 142242.49 | BE7: 46410 | BF7: 156615 | BG7: 64965 | BH7: 18373 | BI7: 22900 | BJ7: 54428 | BK7: 52229.61 | BL7: 56830.08 | BM7: 133640 | BN7: =158604/12 -> 13217 | BO7: 8828.25 | BP7: 14995.16 | BQ7: 7965.14 | BR7: 11766.03 | BS7: 4926.4 | BT7: =26280+2 -> 26282 | BU7: 817.48 | BV7: 3946.33 | BW7: 6394.18 | BX7: 32177 | BY7: 60804 | BZ7: 108419 | CA7: 12519.929 | CB7: 16434.18 | CE7: 4048.98 | CF7: 26169 | CG7: 29432 | CI7: 48828 | CJ7: =2802244/12 -> 233520.33 | CM7: 6900 | CN7: 4669 | CO7: 13414
A8: 43252 | B8: =+AI8+BO8 -> 19410.81 | C8: =+AJ8+BP8 -> 59558.03 | D8: =+AK8+BQ8 -> 31284.86 | E8: =+AL8+BR8 -> 110491.6 | F8: =+AM8+BS8 -> 32427.03 | G8: =+AN8+BT8 -> 189536.14 | H8: =+AO8+BU8 -> 8037.63 | I8: =+AP8+BV8 -> 35739.9 | ... O8: =+AV8+CB8 -> 14913 | P8: =+AW8+CD8 -> 0 | S8: =+AY8+CE8 -> 17364.85 | T8: =+AZ8+CF8 -> 126434.43 | U8: =+BA8+CG8 -> 100448.19 | V8: =+BB8+CH8 -> 8309 | W8: =+BC8+CI8 -> 88217 | X8: =+BD8+CJ8 -> 375762.82 | Y8: =+BE8+CK8 -> 51329 | Z8: =+BF8+CL8 -> 159202 | ... AH8: =+BN8+CT8 -> 13217 | AI8: 12089.69 | AJ8: 49436.83 | AK8: 25921 | AL8: 98869.25 | AM8: 25053.58 | AN8: 165484.78 | AO8: 7220.15 | AP8: 31032 | AQ8: 41720.5 | AR8: 108562.5 | AS8: 48301 | AT8: 131364 | AY8: 9127.65 | AZ8: 105567.43 | BA8: 66005 | BB8: 8309 | BC8: 32187 | BD8: =1706909.82/12 -> 142242.49 | BE8: 51329 | BF8: 159202 | BG8: 67975 | BH8: 17437.5 | BI8: 21844 | BJ8: 52942 | BK8: 49039.33 | BL8: 55783.74 | BM8: 128440 | BN8: =158604/12 -> 13217 | BO8: 7321.12 | BP8: 10121.2 | BQ8: 5363.86 | BR8: 11622.35 | BS8: 7373.45 | BT8: 24051.36 | BU8: 817.48 | BV8: 4707.9 | BW8: 4479 | BX8: 36515.2 | BY8: 76603 | BZ8: 102920.05 | CA8: 14700.992 | CB8: 14913 | CE8: 8237.2 | CF8: 20867 | CG8: 34443.19 | CI8: 56030 | CJ8: =2802244/12 -> 233520.33 | CM8: 6900 | CN8: 4321 | CO8: 13414
A9: 43282 | B9: =+AI9+BO9 -> 16544.49 | C9: =+AJ9+BP9 -> 62513.93 | D9: =+AK9+BQ9 -> 29507.39 | E9: =+AL9+BR9 -> 107427.13 | F9: =+AM9+BS9 -> 30225.94 | G9: =+AN9+BT9 -> 190294.19 | H9: =+AO9+BU9 -> 7859.58 | I9: =+AP9+BV9 -> 34841.91 | ... O9: =+AV9+CB9 -> 21108 | P9: =+AW9+CD9 -> 0 | S9: =+AY9+CE9 -> 16660.55 | T9: =+AZ9+CF9 -> 175783.52 | U9: =+BA9+CG9 -> 111701.8 | V9: =+BB9+CH9 -> 8531 | W9: =+BC9+CI9 -> 92814 | X9: =+BD9+CJ9 -> 375762.82 | Y9: =+BE9+CK9 -> 52442 | Z9: =+BF9+CL9 -> 154025 | ... AH9: =+BN9+CT9 -> 13217 | AI9: 10797.06 | AJ9: 49725.43 | AK9: 24608.8 | AL9: 96692.72 | AM9: 24598.15 | AN9: 162200.83 | AO9: 7042.1 | AP9: 29114 | AQ9: 40062 | AR9: 106064.72 | AS9: 49101.3 | AT9: 131692 | AY9: 8466.65 | AZ9: 154655.52 | BA9: 67406.5 | BB9: 8531 | BC9: 40461 | BD9: =1706909.82/12 -> 142242.49 | BE9: 52442 | BF9: 154025 | BG9: 70957 | BH9: 17940 | BI9: 22201 | BJ9: 52942 | BK9: 41958.14 | BL9: 67370.95 | BM9: 130312 | BN9: =158604/12 -> 13217 | BO9: 5747.43 | BP9: 12788.5 | BQ9: 4898.59 | BR9: 10734.41 | BS9: 5627.79 | BT9: 28093.36 | BU9: 817.48 | BV9: 5727.91 | BW9: 4407.4144 | BX9: 31551.15 | BY9: 64685 | BZ9: 101273.9 | CA9: 10363.962 | CB9: 21108 | CE9: 8193.9 | CF9: 21128 | CG9: 44295.3 | CI9: 52353 | CJ9: =2802244/12 -> 233520.33 | CM9: 6900 | CN9: 3858 | CO9: 12868
A10: 43313 | B10: =+AI10+BO10 -> 16136.44 | C10: =+AJ10+BP10 -> 56690.1 | D10: =+AK10+BQ10 -> 28589.15 | E10: =+AL10+BR10 -> 102393.33 | F10: =+AM10+BS10 -> 36573.84 | G10: =+AN10+BT10 -> 190162.92 | H10: =+AO10+BU10 -> 7731.63 | I10: =+AP10+BV10 -> 35818.59 | ... O10: =+AV10+CB10 -> 19386.5 | P10: =+AW10+CD10 -> 0 | S10: =+AY10+CE10 -> 18620.43 | T10: =+AZ10+CF10 -> 197868.99 | U10: =+BA10+CG10 -> 94001.22 | V10: =+BB10+CH10 -> 8531 | W10: =+BC10+CI10 -> 86600 | X10: =+BD10+CJ10 -> 375762.82 | Y10: =+BE10+CK10 -> 54712 | Z10: =+BF10+CL10 -> 157690 | ... AH10: =+BN10+CT10 -> 13217 | AI10: 11679.68 | AJ10: 47295.25 | AK10: 24443.34 | AL10: 96531.8 | AM10: 23938.48 | AN10: 163469.64 | AO10: 6914.15 | AP10: 29286 | AQ10: 38846 | AR10: 106173.06 | AS10: 49431 | AT10: 132592 | AY10: 8715.5 | AZ10: 174978.99 | BA10: 68314.25 | BB10: 8531 | BC10: 38715 | BD10: =1706909.82/12 -> 142242.49 | BE10: 54712 | BF10: 157690 | BG10: 69139.5 | BH10: 18558 | BI10: 23043 | BJ10: 52942 | BK10: 47469.39 | BL10: 62032.96 | BM10: 133744 | BN10: =158604/12 -> 13217 | BO10: 4456.76 | BP10: 9394.85 | BQ10: 4145.81 | BR10: 5861.53 | BS10: 12635.36 | BT10: 26693.28 | BU10: 817.48 | BV10: 6532.59 | BW10: 4224.4 | BX10: 32583.12 | BY10: 68200.883 | BZ10: 100629.26 | CA10: 6677.92 | CB10: 19386.5 | CE10: 9904.93 | CF10: 22890 | CG10: 25686.97 | CI10: 47885 | CJ10: =2802244/12 -> 233520.33 | CM10: 6900 | CN10: 4788.5 | CO10: 11456.5
A11: 43344 | B11: =+AI11+BO11 -> 16669.12 | C11: =+AJ11+BP11 -> 54254 | D11: =+AK11+BQ11 -> 33971.07 | E11: =+AL11+BR11 -> 114873.67 | F11: =+AM11+BS11 -> 31481.6 | G11: =+AN11+BT11 -> 198075.65 | H11: =+AO11+BU11 -> 7193.48 | I11: =+AP11+BV11 -> 34404 | ... O11: =+AV11+CB11 -> 22086.24 | P11: =+AW11+CD11 -> 0 | S11: =+AY11+CE11 -> 17415.73 | T11: =+AZ11+CF11 -> 188671.01 | U11: =+BA11+CG11 -> 106678.99 | V11: =+BB11+CH11 -> 8531 | W11: =+BC11+CI11 -> 94862 | X11: =+BD11+CJ11 -> 375762.82 | Y11: =+BE11+CK11 -> 48862 | Z11: =+BF11+CL11 -> 151999 | ... AH11: =+BN11+CT11 -> 13217 | AI11: 11726.54 | AJ11: 47363.8 | AK11: 26142.6 | AL11: 101568.43 | AM11: 25017.58 | AN11: 172047.65 | AO11: 6376 | AP11: 29742 | AQ11: 40412 | AR11: 108072.61 | AS11: 49991 | AT11: 134588 | AY11: 8759.75 | AZ11: 166560.01 | BA11: 66338.15 | BB11: 8531 | BC11: 46977 | BD11: =1706909.82/12 -> 142242.49 | BE11: 48862 | BF11: 151999 | BG11: 67182 | BH11: 12759 | BI11: 21859 | BJ11: 52177 | BK11: 50704.37 | BL11: 64171.49 | BM11: 137176 | BN11: =158604/12 -> 13217 | BO11: 4942.58 | BP11: 6890.2 | BQ11: 7828.47 | BR11: 13305.24 | BS11: 6464.02 | BT11: 26028 | BU11: 817.48 | BV11: 4662 | BW11: 4302.68 | BX11: 37067.68 | BY11: 68126 | BZ11: 100692.29 | CA11: 7672 | CB11: 22086.24 | CE11: 8655.98 | CF11: 22111 | CG11: 40340.84 | CI11: 47885 | CJ11: =2802244/12 -> 233520.33 | CM11: 6900 | CN11: 2436 | CO11: 11775
A12: 43374 | B12: =+AI12+BO12 -> 15516.94 | C12: =+AJ12+BP12 -> 54955.07 | D12: =+AK12+BQ12 -> 28715.71 | E12: =+AL12+BR12 -> 116466.76 | F12: =+AM12+BS12 -> 32039.37 | G12: =+AN12+BT12 -> 200406.65 | H12: =+AO12+BU12 -> 7107.48 | I12: =+AP12+BV12 -> 35004.72 | ... O12: =+AV12+CB12 -> 19994.7 | P12: =+AW12+CD12 -> 0 | S12: =+AY12+CE12 -> 14069.42 | T12: =+AZ12+CF12 -> 188863.43 | U12: =+BA12+CG12 -> 108602 | V12: =+BB12+CH12 -> 8531 | W12: =+BC12+CI12 -> 87459 | X12: =+BD12+CJ12 -> 375762.82 | Y12: =+BE12+CK12 -> 52856 | Z12: =+BF12+CL12 -> 148634 | ... AH12: =+BN12+CT12 -> 13217 | AI12: 11205.34 | AJ12: 46814.01 | AK12: 25364.81 | AL12: 101033.24 | AM12: 24393.8 | AN12: 171429.72 | AO12: 6290 | AP12: 30449 | AQ12: 40500 | AR12: 107326.39 | AS12: 48662.8 | AT12: 137872 | AY12: 9472.63 | AZ12: 165467.43 | BA12: 64997 | BB12: 8531 | BC12: 39574 | BD12: =1706909.82/12 -> 142242.49 | BE12: 52856 | BF12: 148634 | BG12: 67182 | BH12: 12759 | BI12: 21859 | BJ12: 52177 | BK12: 43688.61 | BL12: 66182.85 | BM12: 135512 | BN12: =158604/12 -> 13217 | BO12: 4311.6 | BP12: 8141.06 | BQ12: 3350.9 | BR12: 15433.52 | BS12: 7645.57 | BT12: 28976.93 | BU12: 817.48 | BV12: 4555.72 | BW12: 5439.95 | BX12: 31412 | BY12: 75914 | BZ12: 101215 | CA12: 6629.2047 | CB12: 19994.7 | CE12: 4596.79 | CF12: 23396 | CG12: 43605 | CI12: 47885 | CJ12: =2802244/12 -> 233520.33 | CM12: 6900 | CN12: 2436 | CO12: 11775
A13: 43405 | B13: =+AI13+BO13 -> 14871.08 | C13: =+AJ13+BP13 -> 55405.46 | D13: =+AK13+BQ13 -> 30465.39 | E13: =+AL13+BR13 -> 114721.39 | F13: =+AM13+BS13 -> 29154.46 | G13: =+AN13+BT13 -> 199103.94 | H13: =+AO13+BU13 -> 7039.45 | I13: =+AP13+BV13 -> 38151.03 | ... O13: =+AV13+CB13 -> 25507.5 | P13: =+AW13+CD13 -> 0 | S13: =+AY13+CE13 -> 13640.72 | T13: =+AZ13+CF13 -> 190594 | U13: =+BA13+CG13 -> 89215.77 | V13: =+BB13+CH13 -> 8531 | W13: =+BC13+CI13 -> 87545 | X13: =+BD13+CJ13 -> 375762.82 | Y13: =+BE13+CK13 -> 52856 | Z13: =+BF13+CL13 -> 151817 | ... AH13: =+BN13+CT13 -> 13217 | AI13: 11351.51 | AJ13: 47373.23 | AK13: 26015.08 | AL13: 103852.09 | AM13: 26021.42 | AN13: 172180.65 | AO13: 6221.97 | AP13: 31973 | AQ13: 40864.3 | AR13: 106613.95 | AS13: 49470 | AT13: 140684 | AY13: 9658.58 | AZ13: 167638 | BA13: 65391 | BB13: 8531 | BC13: 39660 | BD13: =1706909.82/12 -> 142242.49 | BE13: 52856 | BF13: 151817 | BG13: 67182 | BH13: 12759 | BI13: 21859 | BJ13: 52874 | BK13: 51709.34 | BL13: 72506.82 | BM13: 125424 | BN13: =158604/12 -> 13217 | BO13: 3519.57 | BP13: 8032.23 | BQ13: 4450.31 | BR13: 10869.3 | BS13: 3133.04 | BT13: 26923.29 | BU13: 817.48 | BV13: 6178.03 | BW13: 3760.36 | BX13: 28607.32 | BY13: 66528 | BZ13: 97402.86 | CA13: 12282.35 | CB13: 25507.5 | CE13: 3982.14 | CF13: 22956 | CG13: 23824.77 | CI13: 47885 | CJ13: =2802244/12 -> 233520.33 | CM13: 6900 | CN13: 2436 | CO13: 11775
A14: 43435 | B14: =+AI14+BO14 -> 14405.19 | C14: =+AJ14+BP14 -> 52166.72 | D14: =+AK14+BQ14 -> 29406.84 | E14: =+AL14+BR14 -> 124665.36 | F14: =+AM14+BS14 -> 29842.78 | G14: =+AN14+BT14 -> 194080.04 | H14: =+AO14+BU14 -> 7132.04 | I14: =+AP14+BV14 -> 36560 | ... O14: =+AV14+CB14 -> 27276 | P14: =+AW14+CD14 -> 0 | S14: =+AY14+CE14 -> 14174.72 | T14: =+AZ14+CF14 -> 123241 | U14: =+BA14+CG14 -> 91286.23 | V14: =+BB14+CH14 -> 8531 | W14: =+BC14+CI14 -> 89365 | X14: =+BD14+CJ14 -> 375762.82 | Y14: =+BE14+CK14 -> 52856 | Z14: =+BF14+CL14 -> 151817 | ... AH14: =+BN14+CT14 -> 13217 | AI14: 11475.19 | AJ14: 45405.72 | AK14: 24312.84 | AL14: 116264.36 | AM14: 25024.78 | AN14: 172605.04 | AO14: 6314.56 | AP14: 32272 | AQ14: 39545 | AR14: 109738 | AS14: 50058 | AT14: 143680 | AY14: 8523.05 | AZ14: 96401 | BA14: 62714 | BB14: 8531 | BC14: 41480 | BD14: =1706909.82/12 -> 142242.49 | BE14: 52856 | BF14: 151817 | BG14: 67182 | BH14: 13191 | BI14: 21859 | BJ14: 52874 | BK14: 48966.6 | BL14: 57685 | BM14: 124904 | BN14: =158604/12 -> 13217 | BO14: 2930 | BP14: 6761 | BQ14: 5094 | BR14: 8401 | BS14: 4818 | BT14: 21475 | BU14: 817.48 | BV14: 4288 | BW14: 3991 | BX14: 25604 | BY14: 58634 | BZ14: 70256 | CA14: 7659 | CB14: 27276 | CE14: 5651.67 | CF14: 26840 | CG14: 28572.23 | CI14: 47885 | CJ14: =2802244/12 -> 233520.33 | CM14: 6900 | CN14: 4564 | CO14: 11775
A15: 43466 | B15: 12741.37 | C15: 55090.91 | D15: 32527.21 | E15: 97054.64 | F15: 28044.78 | G15: 186908.58 | H15: 7229.34 | I15: 36838 | J15: 56056.557 | K15: 139173.98 | L15: 99875.77 | M15: 253793.01 | N15: 18312.28 | O15: 21422.52 | P15: 35512 | S15: 14204.56 | T15: 114493 | U15: 91743.45 | V15: 9115 | W15: 81217 | X15: 356800 | Y15: 82751.34 | Z15: 136081 | AA15: 75133 | AB15: 11631 | AC15: 33634 | AD15: 48451 | AE15: 66821.32 | AF15: 65909.56 | AG15: 129656 | AH15: 38867.5 | AI15: 9273.17 | AJ15: 43702.83 | AK15: 23361 | AL15: 83297.79 | AM15: 20929.3 | AN15: 159734.55 | AO15: 6816.64 | AP15: 32033.7 | AQ15: 36684.5 | AR15: 101781.6 | AS15: 48591.5 | AT15: 154440 | AY15: 8874.05 | AZ15: 86242 | BA15: 61792.11 | BB15: 9115 | BC15: 31108 | BD15: 124039 | BE15: 50598.34 | BF15: 126294 | BG15: 70360 | BH15: 7242 | BI15: 21859 | BJ15: 48451 | BK15: 43480.03 | BL15: 50049.62 | BM15: 67808 | BN15: 15795.5 | BO15: 3468.2 | BP15: 11388.08 | BQ15: 9166.21 | BR15: 13756.85 | BS15: 7115.48 | BT15: 27174.03 | BU15: 412.7 | BV15: 4804.3 | BW15: 19372.057 | BX15: 37392.38 | BY15: 51284.27 | BZ15: 99353.01 | CA15: 18312.28 | CB15: 21422.52 | CD15: 35512 | CE15: 5330.51 | CF15: 28251 | CG15: 29951.34 | CI15: 50109 | CJ15: 232761 | CK15: 32153 | CL15: 9787 | CM15: 4773 | CN15: 4389 | CO15: 11775 | CQ15: 23341.29 | CR15: 15859.94 | CS15: 61848 | CT15: 23072 | CU15: =SUM(AI15:BC15)+SUM(BO15:CI15)+'HH ALICORP'!B18 -> 1398546 | CV15: =SUM(AI15:BC15) -> 917777.74 | CW15: =+SUM(BO15:CI15) -> 473576.22 | CX15: =+CU15+BD15+CJ15 -> 1755346
A16: 43497 | B16: 15303.35 | C16: 51564.61 | D16: 30434.65 | E16: 114370.94 | F16: 26996.37 | G16: 173813.22 | H16: 7052.68 | I16: 31116.98 | J16: 59316.227 | K16: 147144.02 | L16: 108002.77 | M16: 255059.01 | N16: 20254.17 | O16: 23149.79 | P16: 35368 | S16: 12425.47 | T16: 116220 | U16: 84098.39 | V16: 9115 | W16: 76275 | X16: 366348 | Y16: 73958.46 | Z16: 159380 | AA16: 67481 | AB16: 24984 | AC16: 33634 | AD16: 50125 | AE16: 56964.67 | AF16: 62591.37 | AG16: 107104 | AH16: 29970.5 | AI16: 9546.3 | AJ16: 44858 | AK16: 23928.15 | AL16: 101113.06 | AM16: 20977.85 | AN16: 147398.72 | AO16: 6832.5 | AP16: 29844.92 | AQ16: 37805.53 | AR16: 101366.1 | AS16: 48586 | AT16: 158144 | AY16: 8134.5 | AZ16: 94040 | BA16: 62252.85 | BB16: 9115 | BC16: 27785 | BD16: 135949 | BE16: 42598.46 | BF16: 149956 | BG16: 62501 | BH16: 16686 | BI16: 21859 | BJ16: 50125 | BK16: 45100 | BL16: 47671.43 | BM16: 62944 | BN16: 14812 | BO16: 5757.05 | BP16: 6706.61 | BQ16: 6506.5 | BR16: 13257.88 | BS16: 6018.52 | BT16: 26414.5 | BU16: 220.18 | BV16: 1272.06 | BW16: 21510.697 | BX16: 45777.92 | BY16: 59416.77 | BZ16: 96915.01 | CA16: 20254.17 | CB16: 23149.79 | CD16: 35368 | CE16: 4290.97 | CF16: 22180 | CG16: 21845.54 | CI16: 48490 | CJ16: 230399 | CK16: 31360 | CL16: 9424 | CM16: 4980 | CN16: 8298 | CO16: 11775 | CQ16: 11864.67 | CR16: 14919.94 | CS16: 44160 | CT16: 15158.5 | CU16: =SUM(AI16:BC16)+SUM(BO16:CI16)+'HH ALICORP'!B19 -> 1416931.1 | CV16: =SUM(AI16:BC16) -> 931728.48 | CW16: =+SUM(BO16:CI16) -> 465352.17 | CX16: =+CU16+BD16+CJ16 -> 1783279.1
A17: 43525 | B17: 16143.98 | C17: 39097.65 | D17: 26847.91 | E17: 108041.35 | F17: 30695.04 | G17: 171271.33 | H17: 5808.91 | I17: 32825.92 | J17: 64132.104 | K17: 145649.56 | L17: 93480.66 | M17: 285566.16 | N17: 18420.95 | O17: 18941.49 | P17: 35512 | S17: 13371.87 | T17: 126535 | U17: 94260 | V17: 9115 | W17: 77439 | X17: 400850 | Y17: 75854.95 | Z17: 139768 | AA17: 75340 | AB17: 24984 | AC17: 33634 | AD17: 50877 | AE17: 75466.73 | AF17: 62579.32 | AG17: 126241 | AH17: 24382 | AI17: 8729.03 | AJ17: 30269.5 | AK17: 20994.5 | AL17: 93679.9 | AM17: 18484.5 | AN17: 140863.11 | AO17: 5619.5 | AP17: 28231.25 | AQ17: 36304.5 | AR17: 95822.5 | AS17: 45032.86 | AT17: 178124 | AY17: 8904.87 | AZ17: 104732 | BA17: 65929 | BB17: 9115 | BC17: 35644 | BD17: 163425 | BE17: 45450.95 | BF17: 126460 | BG17: 70360 | BH17: 16686 | BI17: 21859 | BJ17: 50877 | BK17: 49463.53 | BL17: 42212.82 | BM17: 67328 | BN17: 16778 | BO17: 7414.95 | BP17: 8828.15 | BQ17: 5853.41 | BR17: 14361.45 | BS17: 12210.54 | BT17: 30408.22 | BU17: 189.41 | BV17: 4594.67 | BW17: 27827.604 | BX17: 49827.06 | BY17: 48447.8 | BZ17: 107442.16 | CA17: 18420.95 | CB17: 18941.49 | CD17: 35512 | CE17: 4467 | CF17: 21803 | CG17: 28331 | CI17: 41795 | CJ17: 237425 | CK17: 30404 | CL17: 13308 | CM17: 4980 | CN17: 8298 | CO17: 11775 | CQ17: 26003.2 | CR17: 20366.5 | CS17: 58913 | CT17: 7604 | CU17: =SUM(AI17:BC17)+SUM(BO17:CI17)+'HH ALICORP'!B20 -> 1414219.9 | CV17: =SUM(AI17:BC17) -> 926480.02 | CW17: =+SUM(BO17:CI17) -> 486675.86 | CX17: =+CU17+BD17+CJ17 -> 1815069.9
A18: 43556 | B18: 17438.05 | C18: 44556.37 | D18: 32356.33 | E18: 115980.07 | F18: 36630.15 | G18: 189567.01 | H18: 6418.11 | I18: 32723.62 | J18: 66258.804 | K18: 153044.53 | L18: 96391.18 | M18: 280130.57 | N18: 24387.56 | O18: 18426.03 | P18: 35464 | S18: 11811.93 | T18: 131549 | U18: 93011 | V18: 9115 | W18: 78761 | X18: 347017 | Y18: 85705.49 | Z18: 144427 | AA18: 75340 | AB18: 26671 | AC18: 38234 | AD18: 50877 | AE18: 76830.67 | AF18: 67543.51 | AG18: 126569 | AH18: 23999 | AI18: 10257.75 | AJ18: 34251 | AK18: 24848.25 | AL18: 101182.98 | AM18: 21915.83 | AN18: 158686.86 | AO18: 6414.41 | AP18: 30106.55 | AQ18: 41243.5 | AR18: 105270.8 | AS18: 49014.5 | AT18: 182260 | AY18: 7955.47 | AZ18: 111335 | BA18: 65253 | BB18: 9115 | BC18: 39557 | BD18: 135456 | BE18: 48053.49 | BF18: 136480 | BG18: 70360 | BH18: 18373 | BI18: 22900 | BJ18: 50877 | BK18: 49330.19 | BL18: 46151.01 | BM18: 73268 | BN18: 16874 | BO18: 7180.3 | BP18: 10305.37 | BQ18: 7508.08 | BR18: 14797.09 | BS18: 14714.32 | BT18: 30880.15 | BU18: 3.7 | BV18: 2617.07 | BW18: 25015.304 | BX18: 47773.73 | BY18: 47376.68 | BZ18: 97870.57 | CA18: 24387.56 | CB18: 18426.03 | CD18: 35464 | CE18: 3856.46 | CF18: 20214 | CG18: 27758 | CI18: 39204 | CJ18: 211561 | CK18: 37652 | CL18: 7947 | CM18: 4980 | CN18: 8298 | CO18: 15334 | CQ18: 27500.48 | CR18: 21392.5 | CS18: 53301 | CT18: 7125 | CU18: =SUM(AI18:BC18)+SUM(BO18:CI18)+'HH ALICORP'!B21 -> 1475820.3 | CV18: =SUM(AI18:BC18) -> 998667.9 | CW18: =+SUM(BO18:CI18) -> 475352.41 | CX18: =+CU18+BD18+CJ18 -> 1822837.3
A19: 43586 | B19: 17655.34 | C19: 40037.9 | D19: 30201.05 | E19: 116401.33 | F19: 37465.38 | G19: 176712.56 | H19: 6830.57 | I19: 30985.91 | J19: 63760.278 | K19: 149453.97 | L19: 108091.66 | M19: 310471.82 | N19: 26049.13 | O19: 23966.14 | P19: 35512 | S19: 13103.85 | T19: 132999 | U19: 99243 | V19: 9115 | W19: 86768 | X19: 464065 | Y19: 107539 | Z19: 135013 | AA19: 77350 | AB19: 26671 | AC19: 38234 | AD19: 50877 | AE19: 70970.39 | AF19: 68237.49 | AG19: 113246 | AH19: 25017.5 | AI19: 8740.25 | AJ19: 32484 | AK19: 23003.5 | AL19: 98963.83 | AM19: 21100.5 | AN19: 145852.16 | AO19: 6555.12 | AP19: 26400.5 | AQ19: 38889 | AR19: 99315.75 | AS19: 49154.7 | AT19: 186956 | AY19: 9086.52 | AZ19: 116159 | BA19: 66089 | BB19: 9115 | BC19: 37377 | BD19: 143894 | BE19: 53578 | BF19: 125379 | BG19: 70360 | BH19: 18373 | BI19: 22900 | BJ19: 50877 | BK19: 45247.97 | BL19: 47735.99 | BM19: 68848 | BN19: 17417.5 | BO19: 8915.09 | BP19: 7553.9 | BQ19: 7197.55 | BR19: 17437.5 | BS19: 16364.88 | BT19: 30860.4 | BU19: 275.45 | BV19: 4585.41 | BW19: 24871.278 | BX19: 50138.22 | BY19: 58936.96 | BZ19: 123515.82 | CA19: 26049.13 | CB19: 23966.14 | CD19: 35512 | CE19: 4017.33 | CF19: 16840 | CG19: 33154 | CI19: 49391 | CJ19: 320171 | CK19: 53961 | CL19: 9634 | CM19: 6990 | CN19: 8298 | CO19: 15334 | CQ19: 25722.42 | CR19: 20501.5 | CS19: 44398 | CT19: 7600 | CU19: =SUM(AI19:BC19)+SUM(BO19:CI19)+'HH ALICORP'!B22 -> 1791331.9 | CV19: =SUM(AI19:BC19) -> 975241.83 | CW19: =+SUM(BO19:CI19) -> 539582.06 | CX19: =+CU19+BD19+CJ19 -> 2255396.9
A20: 43617 | B20: 17893.21 | C20: 40930.86 | D20: 28967.33 | E20: 112925.89 | F20: 30213.007 | G20: 193288.28 | H20: 7010.18 | I20: 36715.94 | J20: 66018.033 | K20: 157272.11 | L20: 107165.28 | M20: 293072.11 | N20: 22551.1 | O20: 23353.99 | P20: 35464 | S20: 12871.3 | T20: 162064 | U20: 96067.77 | V20: 10131 | W20: 74149 | X20: 464065 | Y20: 81239.84 | Z20: 160594 | AA20: 77350 | AB20: 26671 | AC20: 36314 | AD20: 50877 | AE20: 75067.38 | AF20: 67267.14 | AG20: 91013 | AH20: 28955 | AI20: 9848.65 | AJ20: 33098.32 | AK20: 24238.85 | AL20: 102201.28 | AM20: 21245.8 | AN20: 157909.18 | AO20: 6969 | AP20: 30897.92 | AQ20: 41271 | AR20: 106546.25 | AS20: 51217 | AT20: 192816 | AY20: 8540.65 | AZ20: 132249 | BA20: 66852.5 | BB20: 10131 | BC20: 31404 | BD20: 143894 | BE20: 45211.84 | BF20: 137720 | BG20: 70360 | BH20: 18373 | BI20: 22900 | BJ20: 50877 | BK20: 39593.78 | BL20: 48147.82 | BM20: 60268 | BN20: 10279 | BO20: 8044.56 | BP20: 7832.54 | BQ20: 4728.48 | BR20: 10724.61 | BS20: 8967.2075 | BT20: 35379.1 | BU20: 41.18 | BV20: 5818.02 | BW20: 24747.033 | BX20: 50725.86 | BY20: 55948.28 | BZ20: 100256.11 | CA20: 22551.1 | CB20: 23353.99 | CD20: 35464 | CE20: 4330.65 | CF20: 29815 | CG20: 29215.27 | CI20: 42745 | CJ20: 320171 | CK20: 36028 | CL20: 22874 | CM20: 6990 | CN20: 8298 | CO20: 13414 | CQ20: 35473.6 | CR20: 19119.32 | CS20: 30745 | CT20: 18676 | CU20: =SUM(AI20:BC20)+SUM(BO20:CI20)+'HH ALICORP'!B23 -> 1528124.4 | CV20: =SUM(AI20:BC20) -> 1027436.4 | CW20: =+SUM(BO20:CI20) -> 500687.99 | CX20: =+CU20+BD20+CJ20 -> 1992189.4
A21: 43647 | B21: 11935.6 | C21: 42162.16 | D21: 32158.19 | E21: 121021.75 | F21: 32866.05 | G21: 203915.38 | H21: 5891 | I21: 38108.63 | J21: 61605.101 | K21: 158932.42 | L21: 112642.24 | M21: 298868.93 | N21: 24146.14 | O21: 21815.08 | P21: 35512 | S21: 14594.17 | T21: 216072 | U21: 99632 | V21: 9115 | W21: 70733 | X21: 464065 | Y21: 87759.89 | Z21: 147924 | AA21: 77350 | AB21: 26671 | AC21: 36314 | AD21: 31224 | AE21: 82373.98 | AF21: 69496 | AG21: 84325 | AH21: 20995 | AI21: 10439.08 | AJ21: 33805.75 | AK21: 24813.25 | AL21: 111264.41 | AM21: 22324.17 | AN21: 162327.02 | AO21: 5891 | AP21: 33009.83 | AQ21: 41390.85 | AR21: 109722.2 | AS21: 49859.75 | AT21: 196944 | AY21: 9023.55 | AZ21: 190728 | BA21: 73084 | BB21: 9115 | BC21: 30044 | BD21: 143894 | BE21: 52955.89 | BF21: 126100 | BG21: 70360 | BH21: 18373 | BI21: 22900 | BJ21: 31224 | BK21: 42751.64 | BL21: 46641 | BM21: 51376 | BN21: 11289 | BO21: 1496.52 | BP21: 8356.41 | BQ21: 7344.94 | BR21: 9757.34 | BS21: 10541.88 | BT21: 41588.36 | BU21: 0 | BV21: 5098.8 | BW21: 20214.251 | BX21: 49210.22 | BY21: 62782.49 | BZ21: 101924.93 | CA21: 24146.14 | CB21: 21815.08 | CD21: 35512 | CE21: 5570.62 | CF21: 25344 | CG21: 26548 | CI21: 40689 | CJ21: 320171 | CK21: 34804 | CL21: 21824 | CM21: 6990 | CN21: 8298 | CO21: 13414 | CQ21: 39622.34 | CR21: 22855 | CS21: 32949 | CT21: 9706 | CU21: =SUM(AI21:BC21)+SUM(BO21:CI21)+'HH ALICORP'!B24 -> 1611726.8 | CV21: =SUM(AI21:BC21) -> 1113785.9 | CW21: =+SUM(BO21:CI21) -> 497940.98 | CX21: =+CU21+BD21+CJ21 -> 2075791.8
A22: 43678 | B22: 18627.57 | C22: 39058.65 | D22: 31620.21 | E22: 112484.86 | F22: 28070.38 | G22: 196681.09 | H22: 6256 | I22: 44855.43 | J22: 57589.076 | K22: 163347.97 | L22: 109164.99 | M22: 314681.18 | N22: 24227.49 | O22: 15513.46 | P22: 35512 | S22: 14221.21 | T22: 217077 | U22: 98843 | V22: 10941 | W22: 73188.6 | X22: 464065 | Y22: 90149.53 | Z22: 159366 | AA22: 77350 | AB22: 26856 | AC22: 38457 | AD22: 77179 | AE22: 80022.98 | AF22: 67244 | AG22: 83492 | AH22: 20995 | AI22: 10587.5 | AJ22: 32879.5 | AK22: 24745.58 | AL22: 103792.27 | AM22: 20969.27 | AN22: 160112.2 | AO22: 6256 | AP22: 32578.75 | AQ22: 38579.5 | AR22: 106455.25 | AS22: 47966.1 | AT22: 203364 | AY22: 9474.94 | AZ22: 192395 | BA22: 72884 | BB22: 10941 | BC22: 31011.6 | BD22: 143894 | BE22: 52005.53 | BF22: 139574 | BG22: 70360 | BH22: 18558 | BI22: 23043 | BJ22: 77179 | BK22: 48597 | BL22: 44510 | BM22: 50570 | BN22: 11289 | BO22: 8040.07 | BP22: 6179.15 | BQ22: 6874.63 | BR22: 8692.59 | BS22: 7101.11 | BT22: 36568.89 | BU22: 0 | BV22: 12276.68 | BW22: 19009.576 | BX22: 56892.72 | BY22: 61198.89 | BZ22: 111317.18 | CA22: 24227.49 | CB22: 15513.46 | CD22: 35512 | CE22: 4746.27 | CF22: 24682 | CG22: 25959 | CI22: 42177 | CJ22: 320171 | CK22: 38144 | CL22: 19792 | CM22: 6990 | CN22: 8298 | CO22: 15414 | CQ22: 31425.98 | CR22: 22734 | CS22: 32922 | CT22: 9706 | CU22: =SUM(AI22:BC22)+SUM(BO22:CI22)+'HH ALICORP'!B25 -> 2428082.3 | CV22: =SUM(AI22:BC22) -> 1104992.5 | CW22: =+SUM(BO22:CI22) -> 506968.71 | CX22: =+CU22+BD22+CJ22 -> 2892147.3
A23: 43709 | B23: 19534.06 | C23: 42040.16 | D23: 34580.08 | E23: 115340.66 | F23: 33147.38 | G23: 205765.01 | H23: 6355.85 | I23: 47046.86 | J23: 61076.637 | K23: 172026.84 | L23: 112495.19 | M23: 321809.76 | N23: 22889.84 | O23: 18094.15 | P23: 35464 | S23: 12774.96 | T23: 205172 | U23: 98007 | V23: 11118 | W23: 72269.46 | X23: 466891 | Y23: 75305.49 | Z23: 144347.84 | AA23: 77350 | AB23: 26856 | AC23: 38457 | AD23: 70913 | AE23: 73893 | AF23: 77920 | AG23: 75190 | AH23: 20995 | AI23: 11748.5 | AJ23: 34127.87 | AK23: 24773.17 | AL23: 107415.05 | AM23: 23409.17 | AN23: 169056.15 | AO23: 6215.5 | AP23: 33491.16 | AQ23: 43541.85 | AR23: 117099.53 | AS23: 50257.5 | AT23: 211520 | AY23: 8956.16 | AZ23: 180855 | BA23: 72000 | BB23: 11118 | BC23: 32243.46 | BD23: 157437 | BE23: 48761.49 | BF23: 123817 | BG23: 70360 | BH23: 18558 | BI23: 23043 | BJ23: 70913 | BK23: 48038 | BL23: 52427 | BM23: 48152 | BN23: 11289 | BO23: 7785.56 | BP23: 7912.29 | BQ23: 9806.91 | BR23: 7925.61 | BS23: 9738.21 | BT23: 36708.86 | BU23: 140.35 | BV23: 13555.7 | BW23: 17534.787 | BX23: 54927.31 | BY23: 62237.69 | BZ23: 110289.76 | CA23: 22889.84 | CB23: 18094.15 | CD23: 35464 | CE23: 3818.8 | CF23: 24317 | CG23: 26007 | CI23: 40026 | CJ23: 309454 | CK23: 26544 | CL23: 20530.84 | CM23: 6990 | CN23: 8298 | CO23: 15414 | CQ23: 25855 | CR23: 25493 | CS23: 27038 | CT23: 9706 | CU23: =SUM(AI23:BC23)+SUM(BO23:CI23)+'HH ALICORP'!B26 -> 1647007.9 | CV23: =SUM(AI23:BC23) -> 1137828.1 | CW23: =+SUM(BO23:CI23) -> 509179.83 | CX23: =+CU23+BD23+CJ23 -> 2113898.9
A24: 43739 | B24: 17847 | C24: 41489.06 | D24: 31234.16 | E24: 109780.26 | F24: 35601.25 | G24: 199244.07 | H24: 6068.91 | I24: 40420.5 | J24: 66460.102 | K24: 161655.52 | L24: 108915.08 | M24: 340116.86 | N24: 25227.64 | O24: 11670.99 | P24: 35512 | S24: 13982.54 | T24: 226171 | U24: 101132 | V24: 11574 | W24: 68921 | X24: 386604 | Y24: 89303.36 | Z24: 153856 | AA24: 77350 | AB24: 26856 | AC24: 38457 | AD24: 68045 | AE24: 62220.27 | AF24: 68652 | AG24: 60898 | AH24: 20995 | AI24: 10586.78 | AJ24: 33052.25 | AK24: 24548.15 | AL24: 102017.94 | AM24: 21934.17 | AN24: 162173.8 | AO24: 6022 | AP24: 29844.5 | AQ24: 40976 | AR24: 112652.5 | AS24: 48707.5 | AT24: 218564 | AY24: 9825.92 | AZ24: 201868 | BA24: 71850 | BB24: 11574 | BC24: 27239 | BD24: 141700 | BE24: 55663.36 | BF24: 134797 | BG24: 70360 | BH24: 18558 | BI24: 23043 | BJ24: 68045 | BK24: 47018.27 | BL24: 44908 | BM24: 46306 | BN24: 11289 | BO24: 7260.22 | BP24: 8436.81 | BQ24: 6686.01 | BR24: 7762.32 | BS24: 13667.08 | BT24: 37070.27 | BU24: 46.91 | BV24: 10576 | BW24: 25484.102 | BX24: 49003.02 | BY24: 60207.58 | BZ24: 121552.86 | CA24: 25227.64 | CB24: 11670.99 | CD24: 35512 | CE24: 4156.62 | CF24: 24303 | CG24: 29282 | CI24: 41682 | CJ24: 244904 | CK24: 33640 | CL24: 19059 | CM24: 6990 | CN24: 8298 | CO24: 15414 | CQ24: 15202 | CR24: 23744 | CS24: 14592 | CT24: 9706 | CU24: =SUM(AI24:BC24)+SUM(BO24:CI24)+'HH ALICORP'!B27 -> 1661376.9 | CV24: =SUM(AI24:BC24) -> 1133436.5 | CW24: =+SUM(BO24:CI24) -> 519587.43 | CX24: =+CU24+BD24+CJ24 -> 2047980.9
A25: 43770 | B25: 17455.16 | C25: 39324.49 | D25: 32590.55 | E25: 114521.84 | F25: 29149.05 | G25: 199740.82 | H25: 7168.12 | I25: 44582.48 | J25: 62174.352 | K25: 172772.14 | L25: 112148.2 | M25: 337293.34 | N25: 23582.43 | O25: 28845.54 | P25: 35464 | S25: 13401.98 | T25: 212523 | U25: 100035 | V25: 10878 | W25: 69681 | X25: 394556 | Y25: 96303.36 | Z25: 147888 | AA25: 77350 | AB25: 26856 | AC25: 38457 | AD25: 77415 | AE25: 55019 | AF25: 62492.56 | AG25: 68269 | AH25: 20995 | AI25: 10408 | AJ25: 33195.5 | AK25: 26029.31 | AL25: 103843.31 | AM25: 22567.08 | AN25: 168783.96 | AO25: 6926.5 | AP25: 31832.5 | AQ25: 39425.8 | AR25: 118298 | AS25: 51891.5 | AT25: 223852 | AY25: 9430.9 | AZ25: 189082 | BA25: 71030 | BB25: 10878 | BC25: 26624 | BD25: 148613 | BE25: 58663.36 | BF25: 129589 | BG25: 70360 | BH25: 18558 | BI25: 23043 | BJ25: 77415 | BK25: 40356 | BL25: 42552 | BM25: 45292 | BN25: 11289 | BO25: 7047.16 | BP25: 6128.99 | BQ25: 6561.24 | BR25: 10678.53 | BS25: 6581.97 | BT25: 30956.86 | BU25: 241.62 | BV25: 12749.98 | BW25: 22748.552 | BX25: 54474.14 | BY25: 60256.7 | BZ25: 113441.34 | CA25: 23582.43 | CB25: 28845.54 | CD25: 35464 | CE25: 3971.08 | CF25: 23441 | CG25: 29005 | CI25: 43057 | CJ25: 245943 | CK25: 37640 | CL25: 18299 | CM25: 6990 | CN25: 8298 | CO25: 15414 | CQ25: 14663 | CR25: 19940.56 | CS25: 22977 | CT25: 9706 | CU25: =SUM(AI25:BC25)+SUM(BO25:CI25)+'HH ALICORP'!B28 -> 1678702.7 | CV25: =SUM(AI25:BC25) -> 1144098.4 | CW25: =+SUM(BO25:CI25) -> 519233.13 | CX25: =+CU25+BD25+CJ25 -> 2073258.7
A26: 43800 | B26: 17257.33 | C26: 42773.4 | D26: 32355.56 | E26: 100745.77 | F26: 28603.39 | G26: 186556.61 | H26: 6882.85 | I26: 42633.51 | J26: 59370.736 | K26: 164322.74 | L26: 113383.09 | M26: 337228.95 | N26: 24319.48 | O26: 28612.84 | P26: 35512 | S26: 12287.94 | T26: 143259 | U26: 101659 | V26: 11890 | W26: 65963 | X26: 360869 | Y26: 85555 | Z26: 142473 | AA26: 77350 | AB26: 26856 | AC26: 38457 | AD26: 74485 | AE26: 66338 | AF26: 74702 | AG26: 73077 | AH26: 26863 | AI26: 11467.34 | AJ26: 32668 | AK26: 25257.42 | AL26: 91730.33 | AM26: 22097.33 | AN26: 161421.42 | AO26: 6824 | AP26: 29773.5 | AQ26: 40678.5 | AR26: 120611.8 | AS26: 53052.5 | AT26: 227252 | AY26: 8223.59 | AZ26: 118496 | BA26: 74768 | BB26: 11890 | BC26: 25403 | BD26: 127988 | BE26: 52915 | BF26: 123929 | BG26: 70360 | BH26: 18558 | BI26: 23043 | BJ26: 74485 | BK26: 42967 | BL26: 46944 | BM26: 45084 | BN26: 11289 | BO26: 5789.99 | BP26: 10105.4 | BQ26: 7098.14 | BR26: 9015.44 | BS26: 6506.06 | BT26: 25135.19 | BU26: 58.85 | BV26: 12860.01 | BW26: 18692.236 | BX26: 43710.94 | BY26: 60330.59 | BZ26: 109976.95 | CA26: 24319.48 | CB26: 28612.84 | CD26: 35512 | CE26: 4064.35 | CF26: 24763 | CG26: 26891 | CI26: 40560 | CJ26: 232881 | CK26: 32640 | CL26: 18544 | CM26: 6990 | CN26: 8298 | CO26: 15414 | CQ26: 23371 | CR26: 27758 | CS26: 27993 | CT26: 15574 | CU26: =SUM(AI26:BC26)+SUM(BO26:CI26)+'HH ALICORP'!B29 -> 1555617.2 | CV26: =SUM(AI26:BC26) -> 1061614.7 | CW26: =+SUM(BO26:CI26) -> 494002.47 | CX26: =+CU26+BD26+CJ26 -> 1916486.2
A27: 43831 | B27: =+AI27+BO27 -> 15843.8 | C27: =+AJ27+BP27 -> 39711.99 | D27: =+AK27+BQ27 -> 29876.86 | E27: =+AL27+BR27 -> 88026.91 | F27: =+AM27+BS27 -> 28828.72 | G27: =+AN27+BT27 -> 182626.42 | H27: =+AO27+BU27 -> 5962 | I27: =+AP27+BV27 -> 40528.73 | ... O27: =+AV27+CB27 -> 37275.65 | P27: =+AW27+CD27 -> 35512 | S27: =+AY27+CE27 -> 10189.34 | T27: =+AZ27+CF27 -> 130846 | U27: =+BA27+CG27 -> 126835.89 | V27: =+BB27+CH27 -> 10633.7 | W27: =+BC27+CI27 -> 55463 | X27: =+BD27+CJ27 -> 383393 | Y27: =+BE27+CK27 -> 89206.99 | Z27: =+BF27+CL27 -> 156697 | ... AH27: =+BN27+CT27 -> 17782 | AI27: 10109 | AJ27: 30079.5 | AK27: 23082.5 | AL27: 76413.25 | AM27: 18942.25 | AN27: 152135.75 | AO27: 5962 | AP27: 28389 | AQ27: 37735 | AR27: 114360.17 | AS27: 51537.38 | AT27: 232588 | AY27: 7698.55 | AZ27: 109415 | BA27: 72793.48 | BB27: 10633.7 | BC27: 22142 | BD27: 145736 | BE27: 57053.99 | BF27: 135117 | BG27: 70360 | BH27: 7242 | BI27: 21859 | BJ27: 53990 | BK27: 42587.41 | BL27: 47539 | BM27: 79961 | BN27: 12348 | BO27: 5734.8 | BP27: 9632.49 | BQ27: 6794.36 | BR27: 11613.66 | BS27: 9886.47 | BT27: 30490.67 | BU27: 0 | BV27: 12139.73 | BW27: 20572.48 | BX27: 60304.56 | BY27: 50391.63 | BZ27: 109527.8 | CA27: 27715.01 | CB27: 37275.65 | CD27: 35512 | CE27: 2490.79 | CF27: 21431 | CG27: 54042.41 | CI27: 33321 | CJ27: 237657 | CK27: 32153 | CL27: 21580 | CM27: 4773 | CN27: 4389 | CO27: 11775 | CP27: 24535 | CQ27: 40098.032 | CR27: 26957.54 | CS27: 28299 | CT27: 5434 | CU27: =SUM(AI27:BC27)+SUM(BO27:CI27)+'HH ALICORP'!B30 -> 1542893 | CV27: =SUM(AI27:BC27) -> 1004016.5 | CW27: =+SUM(BO27:CI27) -> 538876.51 | CX27: =+CU27+BD27+CJ27 -> 1926286
A28: 43862 | B28: =+AI28+BO28 -> 19958.59 | C28: =+AJ28+BP28 -> 37267.37 | D28: =+AK28+BQ28 -> 37527.28 | E28: =+AL28+BR28 -> 109103.83 | F28: =+AM28+BS28 -> 24702.68 | G28: =+AN28+BT28 -> 186432.33 | H28: =+AO28+BU28 -> 5675.65 | I28: =+AP28+BV28 -> 40508.59 | ... O28: =+AV28+CB28 -> 46069.62 | P28: =+AW28+CD28 -> 35512 | S28: =+AY28+CE28 -> 9812.9 | T28: =+AZ28+CF28 -> 110165 | U28: =+BA28+CG28 -> 99722.53 | V28: =+BB28+CH28 -> 10775.43 | W28: =+BC28+CI28 -> 54612 | X28: =+BD28+CJ28 -> 470855 | Y28: =+BE28+CK28 -> 89412.43 | Z28: =+BF28+CL28 -> 194939 | ... AH28: =+BN28+CT28 -> 21385 | AI28: 12053.16 | AJ28: 28215.7 | AK28: 25405.33 | AL28: 94499.11 | AM28: 20499.25 | AN28: 160428.57 | AO28: 5604 | AP28: 24658.5 | AQ28: 38833.5 | AR28: 117392.26 | AS28: 50145.5 | AT28: 257632 | AY28: 7585.9 | AZ28: 91396 | BA28: 72978 | BB28: 10775.43 | BC28: 23514 | BD28: 124679 | BE28: 55787.43 | BF28: 169638 | BG28: 70360 | BH28: 16686 | BI28: 21859 | BJ28: 53376 | BK28: 42877.29 | BL28: 48882.67 | BM28: 91566 | BN28: 14074 | BO28: 7905.43 | BP28: 9051.67 | BQ28: 12121.95 | BR28: 14604.72 | BS28: 4203.43 | BT28: 26003.76 | BU28: 71.65 | BV28: 15850.09 | BW28: 18941.49 | BX28: 52931.24 | BY28: 56108.92 | BZ28: 100971.72 | CA28: 21459.93 | CB28: 46069.62 | CD28: 35512 | CE28: 2227 | CF28: 18769 | CG28: 26744.53 | CI28: 31098 | CJ28: 346176 | CK28: 33625 | CL28: 25301 | CM28: 4773 | CN28: 8298 | CO28: 11775 | CP28: 35641 | CQ28: 23970.45 | CR28: 26089.02 | CS28: 32070 | CT28: 7311 | CU28: =SUM(AI28:BC28)+SUM(BO28:CI28)+'HH ALICORP'!C30 -> 1542262.4 | CV28: =SUM(AI28:BC28) -> 1041616.2 | CW28: =+SUM(BO28:CI28) -> 500646.15 | CX28: =+CU28+BD28+CJ28 -> 2013117.4
A29: 43891 | B29: =+AI29+BO29 -> 15879.31 | C29: =+AJ29+BP29 -> 34914.91 | D29: =+AK29+BQ29 -> 30941.81 | E29: =+AL29+BR29 -> 105574.45 | F29: =+AM29+BS29 -> 26454.85 | G29: =+AN29+BT29 -> 170779.09 | H29: =+AO29+BU29 -> 6712.89 | I29: =+AP29+BV29 -> 46101.63 | ... O29: =+AV29+CB29 -> 20564.08 | P29: =+AW29+CD29 -> 35512 | S29: =+AY29+CE29 -> 10603.99 | T29: =+AZ29+CF29 -> 109272 | U29: =+BA29+CG29 -> 91989.1 | V29: =+BB29+CH29 -> 10738.07 | W29: =+BC29+CI29 -> 56620 | X29: =+BD29+CJ29 -> 431330 | Y29: =+BE29+CK29 -> 81527.71 | Z29: =+BF29+CL29 -> 182091 | ... AH29: =+BN29+CT29 -> 26343 | AI29: 11376.42 | AJ29: 28441.66 | AK29: 23817.51 | AL29: 96857.93 | AM29: 20592 | AN29: 148742.11 | AO29: 6566 | AP29: 28824.83 | AQ29: 38407.5 | AR29: 114548.49 | AS29: 52360.45 | AT29: 268220 | AY29: 8056.67 | AZ29: 91915 | BA29: 73991.5 | BB29: 10738.07 | BC29: 24092 | BD29: 132509 | BE29: 64715.21 | BF29: 156982 | BG29: 70360 | BH29: 16686 | BI29: 21859 | BJ29: 53303 | BK29: 34813.24 | BL29: 49915.97 | BM29: 96508 | BN29: 17548 | BO29: 4502.89 | BP29: 6473.25 | BQ29: 7124.3 | BR29: 8716.52 | BS29: 5862.85 | BT29: 22036.98 | BU29: 146.89 | BV29: 17276.8 | BW29: 24520.73 | BX29: 55810.56 | BY29: 52420.11 | BZ29: 104751.65 | CA29: 17148.45 | CB29: 20564.08 | CD29: 35512 | CE29: 2547.32 | CF29: 17357 | CG29: 17997.6 | CI29: 32528 | CJ29: 298821 | CK29: 16812.5 | CL29: 25109 | CM29: 4980 | CN29: 8298 | CO29: 11775 | CP29: 17051 | CQ29: 24865.37 | CR29: 24562.65 | CS29: 17554 | CT29: 8795 | CU29: =SUM(AI29:BC29)+SUM(BO29:CI29)+'HH ALICORP'!D30 -> 1500846.1 | CV29: =SUM(AI29:BC29) -> 1047548.1 | CW29: =+SUM(BO29:CI29) -> 453297.98 | CX29: =+CU29+BD29+CJ29 -> 1932176.1
A30: 43922 | B30: =+AI30+BO30 -> 14050.18 | C30: =+AJ30+BP30 -> 33185 | D30: =+AK30+BQ30 -> 30249.63 | E30: =+AL30+BR30 -> 59478.58 | F30: =+AM30+BS30 -> 26723.26 | G30: =+AN30+BT30 -> 123472.4 | H30: =+AO30+BU30 -> 5716.29 | I30: =+AP30+BV30 -> 31254.56 | ... O30: =+AV30+CB30 -> 1890.18 | P30: =+AW30+CD30 -> 35248 | S30: =+AY30+CE30 -> 10962.01 | T30: =+AZ30+CF30 -> 63430 | U30: =+BA30+CG30 -> 97478.6 | V30: =+BB30+CH30 -> 7728.5 | W30: =+BC30+CI30 -> 57082 | X30: =+BD30+CJ30 -> 431330 | Y30: =+BE30+CK30 -> 61340.55 | Z30: =+BF30+CL30 -> 194616 | ... AH30: =+BN30+CT30 -> 18569.5 | AI30: 9880.25 | AJ30: 28538 | AK30: 24697.33 | AL30: 56633.77 | AM30: 23995.75 | AN30: 111084 | AO30: 5592.5 | AP30: 25863.1 | AQ30: 40351 | AR30: 114406 | AS30: 55141.9 | AT30: 272196 | AY30: 8355.4 | AZ30: 43589 | BA30: 78446 | BB30: 7728.5 | BC30: 24698 | BD30: 132509 | BE30: 52934.3 | BF30: 170319 | BG30: 59624 | BH30: 17725 | BI30: 20524 | BJ30: 53487 | BK30: 40565.89 | BL30: 47901.61 | BM30: 75771.5 | BN30: 13656.5 | BO30: 4169.93 | BP30: 4647 | BQ30: 5552.3 | BR30: 2844.81 | BS30: 2727.51 | BT30: 12388.4 | BU30: 123.79 | BV30: 5391.46 | BW30: 18104.79 | BX30: 50801.56 | BY30: 39565.87 | BZ30: 84369.74 | CA30: 14332.1 | CB30: 1890.18 | CD30: 35248 | CE30: 2606.61 | CF30: 19841 | CG30: 19032.6 | CI30: 32384 | CJ30: 298821 | CK30: 8406.25 | CL30: 24297 | CM30: 9500 | CN30: 12000 | CO30: 15334 | CP30: 16214 | CQ30: 39809.522 | CR30: 17816.92 | CS30: 20009 | CT30: 4913 | CU30: =SUM(AI30:BC30)+SUM(BO30:CI30)+'HH ALICORP'!E30 -> 1287218.2 | CV30: =SUM(AI30:BC30) -> 931196.5 | CW30: =+SUM(BO30:CI30) -> 356021.65 | CX30: =+CU30+BD30+CJ30 -> 1718548.2
A31: 43952 | B31: =+AI31+BO31 -> 10857.41 | C31: =+AJ31+BP31 -> 28100.46 | D31: =+AK31+BQ31 -> 26723.44 | E31: =+AL31+BR31 -> 42046.92 | F31: =+AM31+BS31 -> 19663.5 | G31: =+AN31+BT31 -> 102350.17 | H31: =+AO31+BU31 -> 4028.13 | I31: =+AP31+BV31 -> 23017.56 | ... O31: =+AV31+CB31 -> 7943.36 | P31: =+AW31+CD31 -> 35248 | S31: =+AY31+CE31 -> 10591.53 | T31: =+AZ31+CF31 -> 85920 | U31: =+BA31+CG31 -> 102161.65 | V31: =+BB31+CH31 -> 8083.87 | W31: =+BC31+CI31 -> 57077.73 | X31: =+BD31+CJ31 -> 431330 | Y31: =+BE31+CK31 -> 81850.36 | Z31: =+BF31+CL31 -> 187171 | ... AH31: =+BN31+CT31 -> 18623.5 | AI31: 5548 | AJ31: 21638 | AK31: 20456 | AL31: 37669.5 | AM31: 11858 | AN31: 88286.75 | AO31: 2294 | AP31: 17098.5 | AQ31: 41093.5 | AR31: 102530 | AS31: 52901.77 | AT31: 278460 | AY31: 7672.23 | AZ31: 64780 | BA31: 74314.5 | BB31: 8083.87 | BC31: 22881.73 | BD31: 132509 | BE31: 63814.36 | BF31: 162922 | BG31: 59624 | BH31: 17725 | BI31: 20524 | BJ31: 53790 | BK31: 41788.23 | BL31: 52052.4 | BM31: 49700 | BN31: 13023.5 | BO31: 5309.41 | BP31: 6462.46 | BQ31: 6267.44 | BR31: 4377.42 | BS31: 7805.5 | BT31: 14063.42 | BU31: 1734.13 | BV31: 5919.06 | BW31: 20798.18 | BX31: 50801.56 | BY31: 43659.56 | BZ31: 95102.79 | CA31: 17212.86 | CB31: 7943.36 | CD31: 35248 | CE31: 2919.3 | CF31: 21140 | CG31: 27847.15 | CI31: 34196 | CJ31: 298821 | CK31: 18036 | CL31: 24249 | CM31: 9500 | CN31: 12000 | CO31: 15334 | CP31: 18275 | CQ31: 41254.348 | CR31: 23887.071 | CS31: 22334 | CT31: 5600 | CU31: =SUM(AI31:BC31)+SUM(BO31:CI31)+'HH ALICORP'!F30 -> 1266373.9 | CV31: =SUM(AI31:BC31) -> 857566.35 | CW31: =+SUM(BO31:CI31) -> 408807.6 | CX31: =+CU31+BD31+CJ31 -> 1697703.9
A32: 43983 | B32: =+AI32+BO32 -> 14416.71 | C32: =+AJ32+BP32 -> 28907.77 | D32: =+AK32+BQ32 -> 29770.93 | E32: =+AL32+BR32 -> 55729.35 | F32: =+AM32+BS32 -> 23629.22 | G32: =+AN32+BT32 -> 150383.74 | H32: =+AO32+BU32 -> 7107.67 | I32: =+AP32+BV32 -> 40414.06 | ... O32: =+AV32+CB32 -> 9207.27 | P32: =+AW32+CD32 -> 35248 | S32: =+AY32+CE32 -> 11051.76 | T32: =+AZ32+CF32 -> 115653 | U32: =+BA32+CG32 -> 113936.22 | V32: =+BB32+CH32 -> 6320.29 | W32: =+BC32+CI32 -> 60753 | X32: =+BD32+CJ32 -> 431330 | Y32: =+BE32+CK32 -> 100899.11 | Z32: =+BF32+CL32 -> 186617 | ... AH32: =+BN32+CT32 -> 17463.5 | AI32: 9616.5 | AJ32: 23155 | AK32: 23621 | AL32: 48553 | AM32: 15341.75 | AN32: 126463.65 | AO32: 6521 | AP32: 30322 | AQ32: 44761 | AR32: 115255.75 | AS32: 57877.16 | AT32: 283528 | AY32: 7674.03 | AZ32: 96247 | BA32: 77944.5 | BB32: 6320.29 | BC32: 24866 | BD32: 132509 | BE32: 71055.11 | BF32: 165020 | BG32: 59624 | BH32: 18373 | BI32: 20524 | BJ32: 56798 | BK32: 36541.63 | BL32: 57504.42 | BM32: 50094 | BN32: 12603.5 | BO32: 4800.21 | BP32: 5752.77 | BQ32: 6149.93 | BR32: 7176.35 | BS32: 8287.47 | BT32: 23920.09 | BU32: 586.67 | BV32: 10092.06 | BW32: 18280.11 | BX32: 50801.56 | BY32: 50169.42 | BZ32: 107338.4 | CA32: 15911.91 | CB32: 9207.27 | CD32: 35248 | CE32: 3377.73 | CF32: 19406 | CG32: 35991.72 | CI32: 35887 | CJ32: 298821 | CK32: 29844 | CL32: 21597 | CM32: 9500 | CN32: 12000 | CO32: 13414 | CP32: 18048 | CQ32: 28349.72 | CR32: 29395.223 | CS32: 23958 | CT32: 4860 | CU32: =SUM(AI32:BC32)+SUM(BO32:CI32)+'HH ALICORP'!G30 -> 1446452.3 | CV32: =SUM(AI32:BC32) -> 998067.63 | CW32: =+SUM(BO32:CI32) -> 448384.67 | CX32: =+CU32+BD32+CJ32 -> 1877782.3
A33: 44013 | B33: =+AI33+BO33 -> 15945.17 | C33: =+AJ33+BP33 -> 38224.67 | D33: =+AK33+BQ33 -> 35296.44 | E33: =+AL33+BR33 -> 74711.59 | F33: =+AM33+BS33 -> 31995.8 | G33: =+AN33+BT33 -> 181066.35 | H33: =+AO33+BU33 -> 8673.19 | I33: =+AP33+BV33 -> 47299.38 | ... O33: =+AV33+CB33 -> 22734.98 | P33: =+AW33+CD33 -> 35248 | S33: =+AY33+CE33 -> 11914.85 | T33: =+AZ33+CF33 -> 172729 | U33: =+BA33+CG33 -> 110473.8 | V33: =+BB33+CH33 -> 6663.67 | W33: =+BC33+CI33 -> 63759 | X33: =+BD33+CJ33 -> 431330 | Y33: =+BE33+CK33 -> 98070.28 | Z33: =+BF33+CL33 -> 194068 | ... AH33: =+BN33+CT33 -> 20974.5 | AI33: 11227.5 | AJ33: 29065.5 | AK33: 26199.5 | AL33: 67138.05 | AM33: 21675 | AN33: 152611.5 | AO33: 8376 | AP33: 37703 | AQ33: 41358 | AR33: 115961.5 | AS33: 51759.9 | AT33: 286320 | AY33: 7767.21 | AZ33: 147195 | BA33: 73229.5 | BB33: 6663.67 | BC33: 25254 | BD33: 132509 | BE33: 67162.28 | BF33: 168247 | BG33: 59624 | BH33: 18373 | BI33: 20524 | BJ33: 56393 | BK33: 41465.36 | BL33: 51880.89 | BM33: 56007 | BN33: 15846.5 | BO33: 4717.67 | BP33: 9159.17 | BQ33: 9096.94 | BR33: 7573.54 | BS33: 10320.8 | BT33: 28454.85 | BU33: 297.19 | BV33: 9596.38 | BW33: 21307.66 | BX33: 50801.56 | BY33: 62156.9 | BZ33: 115952.66 | CA33: 16649.43 | CB33: 22734.98 | CD33: 35248 | CE33: 4147.64 | CF33: 25534 | CG33: 37244.3 | CI33: 38505 | CJ33: 298821 | CK33: 30908 | CL33: 25821 | CM33: 9500 | CN33: 12000 | CO33: 13414 | CP33: 20020 | CQ33: 30344.18 | CR33: 36383.345 | CS33: 22828 | CT33: 5128 | CU33: =SUM(AI33:BC33)+SUM(BO33:CI33)+'HH ALICORP'!H30 -> 1619003.5 | CV33: =SUM(AI33:BC33) -> 1109504.8 | CW33: =+SUM(BO33:CI33) -> 509498.67 | CX33: =+CU33+BD33+CJ33 -> 2050333.5
A34: 44044 | B34: =+AI34+BO34 -> 27269.08 | C34: =+AJ34+BP34 -> 46069.52 | D34: =+AK34+BQ34 -> 37710.61 | E34: =+AL34+BR34 -> 118782.08 | F34: =+AM34+BS34 -> 40958.77 | G34: =+AN34+BT34 -> 230542.99 | H34: =+AO34+BU34 -> 11427.47 | I34: =+AP34+BV34 -> 52728.11 | ... O34: =+AV34+CB34 -> 28933.92 | P34: =+AW34+CD34 -> 35248 | S34: =+AY34+CE34 -> 12244.56 | T34: =+AZ34+CF34 -> 162430 | U34: =+BA34+CG34 -> 107298.45 | V34: =+BB34+CH34 -> 7637.84 | W34: =+BC34+CI34 -> 71077 | X34: =+BD34+CJ34 -> 431330 | Y34: =+BE34+CK34 -> 90869.08 | Z34: =+BF34+CL34 -> 187202 | ... AH34: =+BN34+CT34 -> 17110 | AI34: 16699.5 | AJ34: 37853.5 | AK34: 31744.5 | AL34: 108858.6 | AM34: 29741.5 | AN34: 199866.5 | AO34: 11052 | AP34: 42387 | AQ34: 52680.2 | AR34: 156286.5 | AS34: 60136.4 | AT34: 288592 | AY34: 8058.88 | AZ34: 136681 | BA34: 68551.5 | BB34: 7637.84 | BC34: 31574 | BD34: 132509 | BE34: 62119.08 | BF34: 168220 | BG34: 59624 | BH34: 18558 | BI34: 20667 | BJ34: 55567 | BK34: 45756 | BL34: 49522.2 | BM34: 58203.5 | BN34: 10723 | BO34: 10569.58 | BP34: 8216.02 | BQ34: 5966.11 | BR34: 9923.48 | BS34: 11217.27 | BT34: 30676.49 | BU34: 375.47 | BV34: 10341.11 | BW34: 20585.22 | BX34: 50801.56 | BY34: 57513.11 | BZ34: 135260.03 | CA34: 15940.74 | CB34: 28933.92 | CD34: 35248 | CE34: 4185.68 | CF34: 25749 | CG34: 38746.95 | CI34: 39503 | CJ34: 298821 | CK34: 28750 | CL34: 18982 | CM34: 9500 | CN34: 12000 | CO34: 13414 | CP34: 22035 | CQ34: 62519.55 | CR34: 30978 | CS34: 23950 | CT34: 6387 | CU34: =SUM(AI34:BC34)+SUM(BO34:CI34)+'HH ALICORP'!I30 -> 1828154.2 | CV34: =SUM(AI34:BC34) -> 1288401.4 | CW34: =+SUM(BO34:CI34) -> 539752.74 | CX34: =+CU34+BD34+CJ34 -> 2259484.2
A35: 44075 | B35: =+AI35+BO35 -> 26147.64 | C35: =+AJ35+BP35 -> 38798.39 | D35: =+AK35+BQ35 -> 37737.16 | E35: =+AL35+BR35 -> 99723.94 | F35: =+AM35+BS35 -> 34633.05 | G35: =+AN35+BT35 -> 206418.95 | H35: =+AO35+BU35 -> 8876.24 | I35: =+AP35+BV35 -> 44398.68 | ... O35: =+AV35+CB35 -> 32364.74 | P35: =+AW35+CD35 -> 35248 | S35: =+AY35+CE35 -> 12256.21 | T35: =+AZ35+CF35 -> 172318 | U35: =+BA35+CG35 -> 119126.57 | V35: =+BB35+CH35 -> 9508.03 | W35: =+BC35+CI35 -> 63466.87 | X35: =+BD35+CJ35 -> 431330 | Y35: =+BE35+CK35 -> 92260.27 | Z35: =+BF35+CL35 -> 181154 | ... AH35: =+BN35+CT35 -> 21435 | AI35: 14153.5 | AJ35: 32845.5 | AK35: 27022.5 | AL35: 88994.65 | AM35: 23206.5 | AN35: 176451.45 | AO35: 8360 | AP35: 33134 | AQ35: 44701 | AR35: 123946 | AS35: 53572.03 | AT35: 291396 | AY35: 8200.78 | AZ35: 147367 | BA35: 70616.5 | BB35: 9508.03 | BC35: 24684.87 | BD35: 132509 | BE35: 65641.27 | BF35: 162606 | BG35: 59624 | BH35: 18558 | BI35: 20667 | BJ35: 53353 | BK35: 46899.71 | BL35: 59596.3 | BM35: 57505.5 | BN35: 14128 | BO35: 11994.14 | BP35: 5952.89 | BQ35: 10714.66 | BR35: 10729.29 | BS35: 11426.55 | BT35: 29967.5 | BU35: 516.24 | BV35: 11264.68 | BW35: 26223.56 | BX35: 50801.56 | BY35: 65878.58 | BZ35: 134287.94 | CA35: 14781.62 | CB35: 32364.74 | CD35: 35248 | CE35: 4055.43 | CF35: 24951 | CG35: 48510.07 | CI35: 38782 | CJ35: 298821 | CK35: 26619 | CL35: 18548 | CM35: 9500 | CN35: 12000 | CO35: 15414 | CP35: 34589 | CQ35: 33022.358 | CR35: 35734 | CS35: 27889 | CT35: 7307 | CU35: =SUM(AI35:BC35)+SUM(BO35:CI35)+'HH ALICORP'!J30 -> 1746610.8 | CV35: =SUM(AI35:BC35) -> 1178160.3 | CW35: =+SUM(BO35:CI35) -> 568450.45 | CX35: =+CU35+BD35+CJ35 -> 2177940.8
A36: 44105 | B36: =+AI36+BO36 -> 23595.23 | C36: =+AJ36+BP36 -> 36030.09 | D36: =+AK36+BQ36 -> 37299.38 | E36: =+AL36+BR36 -> 105267 | F36: =+AM36+BS36 -> 30599.51 | G36: =+AN36+BT36 -> 196473.69 | H36: =+AO36+BU36 -> 9326 | I36: =+AP36+BV36 -> 36169.07 | ... O36: =+AV36+CB36 -> 36684.68 | P36: =+AW36+CD36 -> 35248 | S36: =+AY36+CE36 -> 12898.81 | T36: =+AZ36+CF36 -> 190034 | U36: =+BA36+CG36 -> 125971.52 | V36: =+BB36+CH36 -> 9525.59 | W36: =+BC36+CI36 -> 59032 | X36: =+BD36+CJ36 -> 430395 | Y36: =+BE36+CK36 -> 96253.36 | Z36: =+BF36+CL36 -> 180589 | ... AH36: =+BN36+CT36 -> 22255.56 | AI36: 14437 | AJ36: 31289.5 | AK36: 28121.5 | AL36: 94406.87 | AM36: 20401.75 | AN36: 175318.5 | AO36: 9326 | AP36: 31260 | AQ36: 47014.5 | AR36: 124106 | AS36: 55444.6 | AT36: 247932 | AY36: 8016.93 | AZ36: 162669 | BA36: 73589.5 | BB36: 9525.59 | BC36: 22591 | BD36: 132509 | BE36: 66989.36 | BF36: 161394 | BG36: 59624 | BH36: 18558 | BI36: 20667 | BJ36: 54002 | BK36: 42405.38 | BL36: 56133.03 | BM36: 54671 | BN36: 14398.3 | BO36: 9158.23 | BP36: 4740.59 | BQ36: 9177.88 | BR36: 10860.13 | BS36: 10197.76 | BT36: 21155.19 | BU36: 0 | BV36: 4909.07 | BW36: 25450.59 | BX36: 50801.56 | BY36: 66894.11 | BZ36: 125985.76 | CA36: 14777.33 | CB36: 36684.68 | CD36: 35248 | CE36: 4881.88 | CF36: 27365 | CG36: 52382.02 | CI36: 36441 | CJ36: =298821-935 -> 297886 | CK36: 29264 | CL36: 19195 | CM36: 9500 | CN36: 12000 | CO36: 15414 | CP36: 20311 | CQ36: 28065.62 | CR36: 37018 | CS36: 27889 | CT36: 7857.26 | CU36: =SUM(AI36:BC36)+SUM(BO36:CI36)+'HH ALICORP'!K30 -> 1702561 | CV36: =SUM(AI36:BC36) -> 1155450.2 | CW36: =+SUM(BO36:CI36) -> 547110.78 | CX36: =+CU36+BD36+CJ36 -> 2132956
A37: 44136 | B37: =+AI37+BO37 -> 18604.12 | C37: =+AJ37+BP37 -> 38902.08 | D37: =+AK37+BQ37 -> 34482.25 | E37: =+AL37+BR37 -> 101650.6 | F37: =+AM37+BS37 -> 38549.68 | G37: =+AN37+BT37 -> 217894.14 | H37: =+AO37+BU37 -> 8347.29 | I37: =+AP37+BV37 -> 26640.67 | ... O37: =+AV37+CB37 -> 50053.21 | P37: =+AW37+CD37 -> 35248 | S37: =+AY37+CE37 -> 12343.51 | T37: =+AZ37+CF37 -> 162711 | U37: =+BA37+CG37 -> 120623.78 | V37: =+BB37+CH37 -> 9068 | W37: =+BC37+CI37 -> 63736 | X37: =+BD37+CJ37 -> 554443 | Y37: =+BE37+CK37 -> 103150.29 | Z37: =+BF37+CL37 -> 185085 | ... AH37: =+BN37+CT37 -> 22694.65 | AI37: 13237.5 | AJ37: 31296.5 | AK37: 27779 | AL37: 90072.45 | AM37: 26548.25 | AN37: 183679 | AO37: 8332 | AP37: 21438 | AQ37: 44240.5 | AR37: 123423 | AS37: 54284.17 | AT37: 303592 | AY37: 8149.26 | AZ37: 138378 | BA37: 66993 | BB37: 9068 | BC37: 24722 | BD37: 132509 | BE37: 65354.29 | BF37: 159406 | BG37: 59624 | BH37: 18558 | BI37: 20667 | BJ37: 49922 | BK37: 43847.23 | BL37: 50934.59 | BM37: 51688.5 | BN37: 16869 | BO37: 5366.62 | BP37: 7605.58 | BQ37: 6703.25 | BR37: 11578.15 | BS37: 12001.43 | BT37: 34215.14 | BU37: 15.29 | BV37: 5202.67 | BW37: 24260.21 | BX37: 50801.56 | BY37: 66028.12 | BZ37: 143202.95 | CA37: 14665.84 | CB37: 50053.21 | CD37: 35248 | CE37: 4194.25 | CF37: 24333 | CG37: 53630.78 | CI37: 39014 | CJ37: 421934 | CK37: 37796 | CL37: 25679 | CM37: 9500 | CN37: 12000 | CO37: 15414 | CP37: 23457 | CQ37: 29582.626 | CR37: 38920.83 | CS37: 27889 | CT37: 5825.65 | CU37: =SUM(AI37:BC37)+SUM(BO37:CI37)+'HH ALICORP'!L30 -> 1763352.7 | CV37: =SUM(AI37:BC37) -> 1175232.6 | CW37: =+SUM(BO37:CI37) -> 588120.05 | CX37: =+CU37+BD37+CJ37 -> 2317795.7
A38: 44166 | B38: =+AI38+BO38 -> 18995.47 | C38: =+AJ38+BP38 -> 38955.23 | D38: =+AK38+BQ38 -> 33580.03 | E38: =+AL38+BR38 -> 73494.41 | F38: =+AM38+BS38 -> 37481.64 | G38: =+AN38+BT38 -> 201327.63 | H38: =+AO38+BU38 -> 7702.7 | I38: =+AP38+BV38 -> 38736.52 | ... O38: =+AV38+CB38 -> 57252.11 | P38: =+AW38+CD38 -> 35248 | S38: =+AY38+CE38 -> 10128.63 | T38: =+AZ38+CF38 -> 116562 | U38: =+BA38+CG38 -> 128463.37 | V38: =+BB38+CH38 -> 9535 | W38: =+BC38+CI38 -> 61660 | X38: =+BD38+CJ38 -> 893537 | Y38: =+BE38+CK38 -> 105370.16 | Z38: =+BF38+CL38 -> 192225 | ... AH38: =+BN38+CT38 -> 23364.04 | AI38: 12694 | AJ38: 29885 | AK38: 26205.5 | AL38: 66726.83 | AM38: 22451.75 | AN38: 173740.25 | AO38: 7643 | AP38: 30198.5 | AQ38: 40350 | AR38: 123879.5 | AS38: 54419.51 | AT38: 307456 | AY38: 6919.28 | AZ38: 90408 | BA38: 65680.5 | BB38: 9535 | BC38: 24534 | BD38: 132509 | BE38: 69797.16 | BF38: 166348 | BG38: 59624 | BH38: 18558 | BI38: 20667 | BJ38: 62219 | BK38: 44515.22 | BL38: 49446 | BM38: 38236.5 | BN38: 16307.5 | BO38: 6301.47 | BP38: 9070.23 | BQ38: 7374.53 | BR38: 6767.58 | BS38: 15029.89 | BT38: 27587.38 | BU38: 59.7 | BV38: 8538.02 | BW38: 42857 | BX38: 50801.56 | BY38: 67327.56 | BZ38: 149937.4 | CA38: 16552.39 | CB38: 57252.11 | CD38: 35248 | CE38: 3209.35 | CF38: 26154 | CG38: 62782.87 | CI38: 37126 | CJ38: 761028 | CK38: 35573 | CL38: 25877 | CM38: 9500 | CN38: 12000 | CO38: 15414 | CP38: 23241 | CQ38: 31329.241 | CR38: 35398.79 | CS38: 27889 | CT38: 7056.54 | CU38: =SUM(AI38:BC38)+SUM(BO38:CI38)+'HH ALICORP'!M30 -> 1722703.7 | CV38: =SUM(AI38:BC38) -> 1092726.6 | CW38: =+SUM(BO38:CI38) -> 629977.04 | CX38: =+CU38+BD38+CJ38 -> 2616240.7
A39: 44197 | B39: =+AI39+BO39 -> 15881.33 | C39: =+AJ39+BP39 -> 36554.18 | D39: =+AK39+BQ39 -> 32411.82 | E39: =+AL39+BR39 -> 84525.09 | F39: =+AM39+BS39 -> 33071.91 | G39: =+AN39+BT39 -> 201150.08 | H39: =+AO39+BU39 -> 8812.54 | I39: =+AP39+BV39 -> 33121.66 | ... Q39: =+AX39+CD39 -> 35424 | S39: =+AY39+CE39 -> 10824.103 | T39: =+AZ39+CF39 -> 132634 | U39: =+BA39+CG39 -> 141773.33 | V39: =+BB39+CH39 -> 9644 | W39: =+BC39+CI39 -> 57733 | X39: =+BD39+CJ39 -> 618399 | Y39: =+BE39+CK39 -> 81497.37 | Z39: =+BF39+CL39 -> 145507 | ... AH39: =+BN39+CT39 -> 20008.16 | AI39: 8024.5 | AJ39: 29116.5 | AK39: 26368 | AL39: 76698 | AM39: 19559.25 | AN39: 170341.2 | AO39: 8509 | AP39: 22027.5 | AQ39: 38780.5 | AR39: 116389.5 | AS39: 53905 | AT39: 311132 | AW39: 17024 | AY39: 7397.57 | AZ39: 113191 | BA39: 71594 | BB39: 8888 | BC39: 21612 | BD39: 145736 | BE39: 63763.37 | BF39: 119341 | BG39: 70360 | BH39: 7242 | BI39: 23376 | BJ39: 61599 | BK39: 44416.27 | BL39: 49157.63 | BM39: 38780 | BN39: 11442 | BO39: 7856.83 | BP39: 7437.68 | BQ39: 6043.82 | BR39: 7827.09 | BS39: 13512.66 | BT39: 30808.88 | BU39: 303.54 | BV39: 11094.16 | BW39: 19689.89 | BX39: 55589.47 | BY39: 70040.63 | BZ39: 141759.28 | CA39: 17729.96 | CB39: 66223.3 | CD39: 35424 | CE39: 3426.5333 | CF39: 19443 | CG39: 70179.33 | CH39: 756 | CI39: 36121 | CJ39: 472663 | CK39: 17734 | CL39: 26166 | CM39: 4773 | CN39: 4389 | CO39: 11775 | CP39: 18565 | CQ39: 20853.808 | CR39: 34796.87 | CS39: 18432 | CT39: 8566.16
A40: 44228 | B40: =+AI40+BO40 -> 19673.64 | C40: =+AJ40+BP40 -> 35088.35 | D40: =+AK40+BQ40 -> 33628.33 | E40: =+AL40+BR40 -> 62918.78 | F40: =+AM40+BS40 -> 33364.81 | G40: =+AN40+BT40 -> 156959.16 | H40: =+AO40+BU40 -> 7715.05 | I40: =+AP40+BV40 -> 25233.8 | ... Q40: =+AX40+CD40 -> 35424 | S40: =+AY40+CE40 -> 10628.82 | T40: =+AZ40+CF40 -> 124114 | U40: =+BA40+CG40 -> 133369.2 | V40: =+BB40+CH40 -> 7897 | W40: =+BC40+CI40 -> 58814 | X40: =+BD40+CJ40 -> 618399 | Y40: =+BE40+CK40 -> 105838 | Z40: =+BF40+CL40 -> 226744 | ... AH40: =+BN40+CT40 -> 19969.46 | AI40: 12071.5 | AJ40: 26887 | AK40: 23600.5 | AL40: 58778.25 | AM40: 20013.5 | AN40: 130807 | AO40: 7484 | AP40: 13259 | AQ40: 35592.5 | AR40: 110264.83 | AS40: 50779.5 | AT40: 318392 | AW40: 14929 | AY40: 7314.32 | AZ40: 101249 | BA40: 64999 | BB40: 6949 | BC40: 20876 | BD40: 145736 | BE40: 63616 | BF40: 200518 | BG40: 70360 | BH40: 16686 | BI40: 23376 | BJ40: 55637 | BK40: 45421.65 | BL40: 43239 | BM40: 41237.5 | BN40: 9038 | BO40: 7602.14 | BP40: 8201.35 | BQ40: 10027.83 | BR40: 4140.53 | BS40: 13351.31 | BT40: 26152.16 | BU40: 231.05 | BV40: 11974.8 | BW40: 19776.9 | BX40: 52298.79 | BY40: 60675.72 | BZ40: 130243.34 | CA40: 13105.31 | CB40: 104418.46 | CD40: 35424 | CE40: 3314.5 | CF40: 22865 | CG40: 68370.2 | CH40: 948 | CI40: 37938 | CJ40: 472663 | CK40: 42222 | CL40: 26226 | CM40: 4773 | CN40: 8298 | CO40: 11775 | CP40: 19464 | CQ40: 22782.94 | CR40: 33757.5 | CS40: 18432 | CT40: 10931.46
A41: 44256 | B41: =+AI41+BO41 -> 23029.59 | C41: =+AJ41+BP41 -> 39744.17 | D41: =+AK41+BQ41 -> 33200.98 | E41: =+AL41+BR41 -> 89832.77 | F41: =+AM41+BS41 -> 36846.34 | G41: =+AN41+BT41 -> 204517.32 | H41: =+AO41+BU41 -> 8203.34 | I41: =+AP41+BV41 -> 32485.57 | ... Q41: =+AX41+CD41 -> 35424 | S41: =+AY41+CE41 -> 11512.97 | T41: =+AZ41+CF41 -> 127496 | U41: =+BA41+CG41 -> 149864.43 | V41: =+BB41+CH41 -> 8743.65 | W41: =+BC41+CI41 -> 63440.6 | X41: =+BD41+CJ41 -> 639697 | Y41: =+BE41+CK41 -> 120717.08 | Z41: =+BF41+CL41 -> 158737 | ... AH41: =+BN41+CT41 -> 17810.92 | AI41: 13871.5 | AJ41: 30410 | AK41: 25745.5 | AL41: 85365.5 | AM41: 23213.25 | AN41: 170442.95 | AO41: 8034 | AP41: 21116 | AQ41: 42367 | AR41: 129506.5 | AS41: 56409.9 | AT41: 327332 | AW41: 17599 | AY41: 7728.07 | AZ41: 101249 | BA41: 74373.5 | BB41: 7507.65 | BC41: 22710.6 | BD41: 145736 | BE41: 76118.08 | BF41: 130567 | BG41: 70360 | BH41: 16686 | BI41: 23376 | BJ41: 59419 | BK41: 35926.89 | BL41: 49241.6 | BM41: 60662.5 | BN41: 9256.5 | BO41: 9158.09 | BP41: 9334.17 | BQ41: 7455.48 | BR41: 4467.27 | BS41: 13633.09 | BT41: 34074.37 | BU41: 169.34 | BV41: 11369.57 | BW41: 27766.42 | BX41: 57859.41 | BY41: 63969.46 | BZ41: 137847.51 | CA41: 14213.61 | CB41: 82283.29 | CD41: 35424 | CE41: 3784.9 | CF41: 26247 | CG41: 75490.93 | CH41: 1236 | CI41: 40730 | CJ41: 493961 | CK41: 44599 | CL41: 28170 | CM41: 4980 | CN41: 8298 | CO41: 11775 | CP41: 19665 | CQ41: 65009.778 | CR41: 34749 | CS41: 18432 | CT41: 8554.42
A42: 44287 | B42: =+AI42+BO42 -> 18285.23 | C42: =+AJ42+BP42 -> 35289.74 | D42: =+AK42+BQ42 -> 31956.17 | E42: =+AL42+BR42 -> 68880.39 | F42: =+AM42+BS42 -> 30539.3 | G42: =+AN42+BT42 -> 167346.98 | H42: =+AO42+BU42 -> 6174.1 | I42: =+AP42+BV42 -> 30085.17 | ... Q42: =+AX42+CD42 -> 35424 | S42: =+AY42+CE42 -> 9416.75 | T42: =+AZ42+CF42 -> 121235.38 | U42: =+BA42+CG42 -> 135201.2 | V42: =+BB42+CH42 -> 7977.24 | W42: =+BC42+CI42 -> 61827 | X42: =+BD42+CJ42 -> 643778 | Y42: =+BE42+CK42 -> 121512 | Z42: =+BF42+CL42 -> 183797 | ... AH42: =+BN42+CT42 -> 19599.85 | AI42: 9776 | AJ42: 27708.5 | AK42: 22035 | AL42: 66869.67 | AM42: 19916 | AN42: 138392 | AO42: 5144 | AP42: 20268 | AQ42: 37159.5 | AR42: 124721.5 | AS42: 51261 | AT42: 327812 | AW42: 14840.5 | AY42: 6097.7 | AZ42: 85411.38 | BA42: 72388.6 | BB42: 7089.24 | BC42: 22898 | BD42: 145736 | BE42: 74225 | BF42: 153403 | BG42: 70360 | BH42: 18373 | BI42: 23376 | BJ42: 51522 | BK42: 45330.47 | BL42: 48917.2 | BM42: 66303.5 | BN42: 11988 | BO42: 8509.23 | BP42: 7581.24 | BQ42: 9921.17 | BR42: 2010.72 | BS42: 10623.3 | BT42: 28954.98 | BU42: 1030.1 | BV42: 9817.17 | BW42: 18515.17 | BX42: 61213.74 | BY42: 59110.08 | BZ42: 128482.31 | CA42: 13585.42 | CB42: 55655.62 | CD42: 35424 | CE42: 3319.05 | CF42: 35824 | CG42: 62812.6 | CH42: 888 | CI42: 38929 | CJ42: 498042 | CK42: 47287 | CL42: 30394 | CM42: 9500 | CN42: 12000 | CO42: 15334 | CP42: 22628 | CQ42: 57320.222 | CR42: 31157 | CS42: 13640 | CT42: 7611.85
A43: 44317 | B43: =+AI43+BO43 -> 20048.28 | C43: =+AJ43+BP43 -> 34599.86 | D43: =+AK43+BQ43 -> 32039.71 | E43: =+AL43+BR43 -> 71470.78 | F43: =+AM43+BS43 -> 36182.95 | G43: =+AN43+BT43 -> 188033.27 | H43: =+AO43+BU43 -> 7121.16 | I43: =+AP43+BV43 -> 40308.55 | ... Q43: =+AX43+CD43 -> 35424 | S43: =+AY43+CE43 -> 10560.14 | T43: =+AZ43+CF43 -> 139473.06 | U43: =+BA43+CG43 -> 131354.8 | V43: =+BB43+CH43 -> 9789.47 | W43: =+BC43+CI43 -> 60353 | X43: =+BD43+CJ43 -> 599311 | Y43: =+BE43+CK43 -> 117458.31 | Z43: =+BF43+CL43 -> 158817 | ... AH43: =+BN43+CT43 -> 18813.09 | AI43: 12150 | AJ43: 28204.5 | AK43: 23460 | AL43: 65013.3 | AM43: 23625 | AN43: 155352.25 | AO43: 7064 | AP43: 27263 | AQ43: 35236 | AR43: 133165.5 | AS43: 52612.06 | AT43: 333004 | AW43: 14985 | AY43: 7044.46 | AZ43: 101627.06 | BA43: 75458.8 | BB43: 8061.47 | BC43: 22553 | BD43: 145736 | BE43: 71515.31 | BF43: 130029 | BG43: 80360 | BH43: 18373 | BI43: 23376 | BJ43: 53580 | BK43: 45305.55 | BL43: 41210 | BM43: 55415 | BN43: 11450.5 | BO43: 7898.28 | BP43: 6395.36 | BQ43: 8579.71 | BR43: 6457.48 | BS43: 12557.95 | BT43: 32681.02 | BU43: 57.16 | BV43: 13045.55 | BW43: 19762.14 | BX43: 67109.37 | BY43: 61249.31 | BZ43: 134392.55 | CA43: 13650.17 | CB43: 68068.96 | CD43: 35424 | CE43: 3515.68 | CF43: 37846 | CG43: 55896 | CH43: 1728 | CI43: 37800 | CJ43: 453575 | CK43: 45943 | CL43: 28788 | CM43: 9500 | CN43: 12000 | CO43: 15334 | CP43: 26417 | CQ43: 33520.71 | CR43: 35813.9 | CS43: 12880 | CT43: 7362.59
A44: 44348 | B44: =+AI44+BO44 -> 20059.67 | C44: =+AJ44+BP44 -> 35986.23 | D44: =+AK44+BQ44 -> 37433.7 | E44: =+AL44+BR44 -> 75124.32 | F44: =+AM44+BS44 -> 34211.68 | G44: =+AN44+BT44 -> 184882.3 | H44: =+AO44+BU44 -> 7927.99 | I44: =+AP44+BV44 -> 40347.9 | ... Q44: =+AX44+CD44 -> 35424 | S44: =+AY44+CE44 -> 11659.35 | T44: =+AZ44+CF44 -> 146447.89 | U44: =+BA44+CG44 -> 133973.15 | V44: =+BB44+CH44 -> 8563.37 | W44: =+BC44+CI44 -> 62426 | X44: =+BD44+CJ44 -> 676468 | Y44: =+BE44+CK44 -> 123021.48 | Z44: =+BF44+CL44 -> 168316 | ... AH44: =+BN44+CT44 -> 18805.06 | AI44: 13080 | AJ44: 28597.5 | AK44: 26456.5 | AL44: 65892.6 | AM44: 24371 | AN44: 159405.75 | AO44: 7624 | AP44: 28194 | AQ44: 36194.5 | AR44: 133756.5 | AS44: 53254.55 | AT44: 333592 | AW44: 15799.76 | AY44: 7920.78 | AZ44: 115194.89 | BA44: 76764.95 | BB44: 7699.37 | BC44: 22993 | BD44: 145736 | BE44: 76847.48 | BF44: 141174 | BG44: 80360 | BH44: 18373 | BI44: 23376 | BJ44: 53188 | BK44: 37159.54 | BL44: 46048.5 | BM44: 42787.5 | BN44: 10464.5 | BO44: 6979.67 | BP44: 7388.73 | BQ44: 10977.2 | BR44: 9231.72 | BS44: 9840.68 | BT44: 25476.55 | BU44: 303.99 | BV44: 12153.9 | BW44: 18135.33 | BX44: 63417.06 | BY44: 58128.52 | BZ44: 126310.27 | CA44: 14814.67 | CB44: 50405.96 | CD44: 35424 | CE44: 3738.57 | CF44: 31253 | CG44: 57208.2 | CH44: 864 | CI44: 39433 | CJ44: 530732 | CK44: 46174 | CL44: 27142 | CM44: 9500 | CN44: 12000 | CO44: 13414 | CP44: 26014 | CQ44: 31167.517 | CR44: 27245 | CS44: 18587 | CT44: 8340.56
A45: 44378 | B45: =+AI45+BO45 -> 14831.62 | C45: =+AJ45+BP45 -> 33210.46 | D45: =+AK45+BQ45 -> 39051.66 | E45: =+AL45+BR45 -> 72824.55 | F45: =+AM45+BS45 -> 34431.58 | G45: =+AN45+BT45 -> 189514.16 | H45: =+AO45+BU45 -> 7236.23 | I45: =+AP45+BV45 -> 40003.2 | ... Q45: =+AX45+CD45 -> 35424 | S45: =+AY45+CE45 -> 12485.05 | T45: =+AZ45+CF45 -> 181325.71 | U45: =+BA45+CG45 -> 120618.87 | V45: =+BB45+CH45 -> 8544.02 | W45: =+BC45+CI45 -> 59775 | X45: =+BD45+CJ45 -> 587880 | Y45: =+BE45+CK45 -> 120903.54 | Z45: =+BF45+CL45 -> 173695 | ... AH45: =+BN45+CT45 -> 17177.03 | AI45: 11017 | AJ45: 28886.5 | AK45: 24671.5 | AL45: 67668.62 | AM45: 22220.5 | AN45: 161249.4 | AO45: 7152 | AP45: 27169 | AQ45: 37987.5 | AR45: 134518 | AS45: 53187.63 | AT45: 333128 | AW45: 16555.5 | AY45: 7868.27 | AZ45: 149438.71 | BA45: 75422.67 | BB45: 7872.02 | BC45: 23178 | BD45: 145736 | BE45: 73916.54 | BF45: 142191 | BG45: 80360 | BH45: 18373 | BI45: 23376 | BJ45: 57968 | BK45: 37079.04 | BL45: 44458.2 | BM45: 47763 | BN45: 9555.5 | BO45: 3814.62 | BP45: 4323.96 | BQ45: 14380.16 | BR45: 5155.93 | BS45: 12211.08 | BT45: 28264.76 | BU45: 84.23 | BV45: 12834.2 | BW45: 18983.73 | BX45: 61609.11 | BY45: 54815.94 | BZ45: 121262.86 | CA45: 14460 | CB45: 52733 | CD45: 35424 | CE45: 4616.78 | CF45: 31887 | CG45: 45196.2 | CH45: 672 | CI45: 36597 | CJ45: 442144 | CK45: 46987 | CL45: 31504 | CM45: 9500 | CN45: 12000 | CO45: 13414 | CP45: 18380 | CQ45: 30044.839 | CR45: 30845 | CS45: 20478 | CT45: 7621.53
A46: 44409 | B46: =+AI46+BO46 -> 15388.85 | C46: =+AJ46+BP46 -> 30694.23 | D46: =+AK46+BQ46 -> 33866.19 | E46: =+AL46+BR46 -> 76671.62 | F46: =+AM46+BS46 -> 30290.27 | G46: =+AN46+BT46 -> 191590.43 | H46: =+AO46+BU46 -> 5397.29 | I46: =+AP46+BV46 -> 40545.93 | ... Q46: =+AX46+CD46 -> 35424 | S46: =+AY46+CE46 -> 10838.09 | T46: =+AZ46+CF46 -> 179238.67 | U46: =+BA46+CG46 -> 119115 | V46: =+BB46+CH46 -> 8427.77 | W46: =+BC46+CI46 -> 56891 | X46: =+BD46+CJ46 -> 545710 | Y46: =+BE46+CK46 -> 143487.77 | Z46: =+BF46+CL46 -> 167610 | ... AH46: =+BN46+CT46 -> 16673.27 | AI46: 11008.5 | AJ46: 27191 | AK46: 23698 | AL46: 69072 | AM46: 23230 | AN46: 156375.9 | AO46: 5228 | AP46: 27115 | AQ46: 36036.5 | AR46: 133396 | AS46: 52343.76 | AT46: 331676 | AW46: 15163.65 | AY46: 7800.69 | AZ46: 145232.67 | BA46: 77758.75 | BB46: 7659.77 | BC46: 21805 | BD46: 145736 | BE46: 85023.77 | BF46: 136563 | BG46: 80360 | BH46: 18558 | BI46: 23043 | BJ46: 57528 | BK46: 39663.48 | BL46: 47373 | BM46: 56261.5 | BN46: 10086.5 | BO46: 4380.35 | BP46: 3503.23 | BQ46: 10168.19 | BR46: 7599.62 | BS46: 7060.27 | BT46: 35214.53 | BU46: 169.29 | BV46: 13430.93 | BW46: 22334.45 | BX46: 61202.61 | BY46: 63108.41 | BZ46: 119415.59 | CA46: 12718 | CB46: 51573.32 | CD46: 35424 | CE46: 3037.4 | CF46: 34006 | CG46: 41356.25 | CH46: 768 | CI46: 35086 | CJ46: 399974 | CK46: 58464 | CL46: 31047 | CM46: 9500 | CN46: 12000 | CO46: 13414 | CP46: 18453 | CQ46: 39923.414 | CR46: 31446 | CS46: 17891 | CT46: 6586.77
A47: 44440 | B47: =+AI47+BO47 -> 15864.93 | C47: =+AJ47+BP47 -> 33935.14 | D47: =+AK47+BQ47 -> 31861.05 | E47: =+AL47+BR47 -> 71660.84 | F47: =+AM47+BS47 -> 29518.4 | G47: =+AN47+BT47 -> 182218.26 | H47: =+AO47+BU47 -> 6318.69 | I47: =+AP47+BV47 -> 43587.49 | ... Q47: =+AX47+CD47 -> 35424 | S47: =+AY47+CE47 -> 11275.3 | T47: =+AZ47+CF47 -> 179754.95 | U47: =+BA47+CG47 -> 112747.5 | V47: =+BB47+CH47 -> 9749.15 | W47: =+BC47+CI47 -> 56421 | X47: =+BD47+CJ47 -> 495200 | Y47: =+BE47+CK47 -> 133774 | Z47: =+BF47+CL47 -> 170080 | ... AH47: =+BN47+CT47 -> 21210.33 | AI47: 10899.5 | AJ47: 29960 | AK47: 24087.5 | AL47: 65689.92 | AM47: 23249.5 | AN47: 156290.7 | AO47: 5551 | AP47: 30163 | AQ47: 38985 | AR47: 141550.5 | AS47: 54312.28 | AT47: 330936 | AW47: 16532.46 | AY47: 8100.33 | AZ47: 140166.95 | BA47: 77572.5 | BB47: 8597.15 | BC47: 21686 | BD47: 145736 | BE47: 84489 | BF47: 137602 | BG47: 80360 | BH47: 18558 | BI47: 23043 | BJ47: 58400 | BK47: 40617.44 | BL47: 49558.6 | BM47: 54591.5 | BN47: 12252.5 | BO47: 4965.43 | BP47: 3975.14 | BQ47: 7773.55 | BR47: 5970.92 | BS47: 6268.9 | BT47: 25927.56 | BU47: 767.69 | BV47: 13424.49 | BW47: 24895.29 | BX47: 51541.23 | BY47: 60109.9 | BZ47: 117870.88 | CA47: 13090.05 | CB47: 38597.13 | CD47: 35424 | CE47: 3174.97 | CF47: 39588 | CG47: 35175 | CH47: 1152 | CI47: 34735 | CJ47: 349464 | CK47: 49285 | CL47: 32478 | CM47: 9500 | CN47: 12000 | CO47: 15414 | CP47: 15775 | CQ47: 77244 | CR47: 27399.5 | CS47: 20018 | CT47: 8957.83
A48: 44470 | B48: =+AI48+BO48 -> 17824.46 | C48: =+AJ48+BP48 -> 34709.32 | D48: =+AK48+BQ48 -> 31509.51 | E48: =+AL48+BR48 -> 68908.43 | F48: =+AM48+BS48 -> 31580.3 | G48: =+AN48+BT48 -> 178490.65 | H48: =+AO48+BU48 -> 4633.85 | I48: =+AP48+BV48 -> 37880.04 | ... Q48: =+AX48+CD48 -> 35424 | S48: =+AY48+CE48 -> 10781.98 | T48: =+AZ48+CF48 -> 171527 | U48: =+BA48+CG48 -> 111160.52 | V48: =+BB48+CH48 -> 9475.87 | W48: =+BC48+CI48 -> 47603 | X48: =+BD48+CJ48 -> 495199 | Y48: =+BE48+CK48 -> 125873.66 | Z48: =+BF48+CL48 -> 0 | ... AH48: =+BN48+CT48 -> 20959.1 | AI48: 12167 | AJ48: 30803 | AK48: 23442.5 | AL48: 65442.29 | AM48: 23649 | AN48: 152553.5 | AO48: 4412 | AP48: 27264 | AQ48: 39042.5 | AR48: 136404.5 | AS48: 53179.63 | AT48: 325152 | AW48: 16275.21 | AY48: 8001.75 | AZ48: 137287 | BA48: 76007.3 | BB48: 8611.87 | BC48: 17779 | BD48: 145736 | BE48: 84661.66 | BF48: 0 | BG48: 80360 | BH48: 18558 | BI48: 23043 | BJ48: 74298 | BK48: 41831.55 | BL48: 54390.7 | BM48: 53430 | BN48: 11734.5 | BO48: 5657.46 | BP48: 3906.32 | BQ48: 8067.01 | BR48: 3466.14 | BS48: 7931.3 | BT48: 25937.15 | BU48: 221.85 | BV48: 10616.04 | BW48: 21474.15 | BX48: 57152.52 | BY48: 55110.45 | BZ48: 119862.45 | CA48: 14830.72 | CB48: 38976.53 | CD48: 35424 | CE48: 2780.23 | CF48: 34240 | CG48: 35153.22 | CH48: 864 | CI48: 29824 | CJ48: 349463 | CK48: 41212 | CL48: 0 | CM48: 9500 | CN48: 12000 | CO48: 15414 | CP48: 16628 | CQ48: 48233.106 | CR48: 32678.5 | CS48: 21458 | CT48: 9224.6
A49: 44501 | B49: =+AI49+BO49 -> 18724.57 | C49: =+AJ49+BP49 -> 38546.09 | D49: =+AK49+BQ49 -> 33586.11 | E49: =+AL49+BR49 -> 71118.57 | F49: =+AM49+BS49 -> 30525.18 | G49: =+AN49+BT49 -> 182743.22 | H49: =+AO49+BU49 -> 4343.33 | I49: =+AP49+BV49 -> 33138.83 | ... Q49: =+AX49+CD49 -> 35424 | S49: =+AY49+CE49 -> 11520.03 | T49: =+AZ49+CF49 -> 186838 | U49: =+BA49+CG49 -> 112138.27 | V49: =+BB49+CH49 -> 9635.55 | W49: =+BC49+CI49 -> 54766 | X49: =+BD49+CJ49 -> 433641 | Y49: =+BE49+CK49 -> 126360.41 | Z49: =+BF49+CL49 -> 0 | ... AH49: =+BN49+CT49 -> 23297.2 | AI49: 12390 | AJ49: 30210 | AK49: 25185 | AL49: 69147.72 | AM49: 21630.5 | AN49: 150299.35 | AO49: 4176 | AP49: 22891 | AQ49: 37664.5 | AR49: 138730.15 | AS49: 52027.13 | AT49: 308160 | AW49: 16436.98 | AY49: 8347.83 | AZ49: 149700 | BA49: 75101 | BB49: 8483.55 | BC49: 19727 | BD49: 145736 | BE49: 83932.41 | BF49: 0 | BG49: 80360 | BH49: 18558 | BI49: 23043 | BJ49: 57404 | BK49: 42474.05 | BL49: 52229.3 | BM49: 43368.5 | BN49: 13967.8 | BO49: 6334.57 | BP49: 8336.09 | BQ49: 8401.11 | BR49: 1970.85 | BS49: 8894.68 | BT49: 32443.87 | BU49: 167.33 | BV49: 10247.83 | BW49: 20574.07 | BX49: 54818.22 | BY49: 59691.13 | BZ49: 116416.33 | CA49: 13897 | CB49: 44689.3 | CD49: 35424 | CE49: 3172.2 | CF49: 37138 | CG49: 37037.27 | CH49: 1152 | CI49: 35039 | CJ49: 287905 | CK49: 42428 | CL49: 0 | CM49: 9500 | CN49: 12000 | CO49: 15414 | CP49: 18350 | CQ49: 59063.844 | CR49: 34090.5 | CS49: 21537 | CT49: 9329.4
A50: 44531 | B50: =+AI50+BO50 -> 13057.02 | C50: =+AJ50+BP50 -> 41066.85 | D50: =+AK50+BQ50 -> 30595.17 | E50: =+AL50+BR50 -> 58756.57 | F50: =+AM50+BS50 -> 33916.54 | G50: =+AN50+BT50 -> 175452.41 | H50: =+AO50+BU50 -> 7540.59 | I50: =+AP50+BV50 -> 37361.82 | ... Q50: =+AX50+CD50 -> 35424 | S50: =+AY50+CE50 -> 10771.36 | T50: =+AZ50+CF50 -> 130237 | U50: =+BA50+CG50 -> 108297 | V50: =+BB50+CH50 -> 8455.76 | W50: =+BC50+CI50 -> 53170 | X50: =+BD50+CJ50 -> 452937 | Y50: =+BE50+CK50 -> 115668.28 | Z50: =+BF50+CL50 -> 0 | ... AH50: =+BN50+CT50 -> 18013.49 | AI50: 9297.5 | AJ50: 30799.5 | AK50: 24432 | AL50: 56673.85 | AM50: 21850 | AN50: 150112.02 | AO50: 6727 | AP50: 27069 | AQ50: 37220.6 | AR50: 126198.5 | AS50: 52540.47 | AT50: 292796 | AW50: 15453.29 | AY50: 7098.13 | AZ50: 101972 | BA50: 68733 | BB50: 7303.76 | BC50: 19560 | BD50: 145736 | BE50: 83308.28 | BF50: 0 | BG50: 0 | BH50: 0 | BI50: 0 | BJ50: 55506 | BK50: 41328.33 | BL50: 43967 | BM50: 45062.5 | BN50: 9751 | BO50: 3759.52 | BP50: 10267.35 | BQ50: 6163.17 | BR50: 2082.72 | BS50: 12066.54 | BT50: 25340.39 | BU50: 813.59 | BV50: 10292.82 | BW50: 18463.9 | BX50: 55055.66 | BY50: 56039.46 | BZ50: 109023.16 | CA50: 13956 | CB50: 38187.7 | CD50: 35424 | CE50: 3673.23 | CF50: 28265 | CG50: 39564 | CH50: 1152 | CI50: 33610 | CJ50: 307201 | CK50: 32360 | CP50: 17784 | CQ50: 59063.844 | CR50: 32550 | CS50: 22104 | CT50: 8262.49
A51: 44562 | B51: =+AI51+BO51 -> 15361.9 | C51: =+AJ51+BP51 -> 29379.2 | D51: =+AK51+BQ51 -> 33818.09 | E51: =+AL51+BR51 -> 64568.43 | F51: =+AM51+BS51 -> 29025.15 | G51: =+AN51+BT51 -> 162717.99 | H51: =+AO51+BU51 -> 5847.26 | I51: =+AP51+BV51 -> 35862.11 | ... Q51: =+AX51+CD51 -> 6348 | S51: =+AY51+CE51 -> 10277.29 | T51: =+AZ51+CF51 -> 131152.6 | U51: =+BA51+CG51 -> 98837 | V51: =+BB51+CH51 -> 7088.32 | W51: =+BC51+CI51 -> 49703 | X51: =+BD51+CJ51 -> 463482 | Y51: =+BE51+CK51 -> 102984 | Z51: =+BF51+CL51 -> 0 | ... AH51: =+BN51+CT51 -> 20632.08 | AI51: 8573 | AJ51: 24502 | AK51: 22338 | AL51: 57497.26 | AM51: 21258.5 | AN51: 135534.45 | AO51: 5576 | AP51: 26055 | AQ51: 34590 | AR51: 117160 | AS51: 49216.78 | AT51: 286844 | AW51: 15189.9 | AY51: 6910.11 | AZ51: 104609.6 | BA51: 68376 | BB51: 6708.32 | BC51: 17220 | BD51: 145736 | BE51: 74800 | BF51: 0 | BG51: 0 | BH51: 0 | BI51: 0 | BJ51: 61739 | BK51: 42557 | BL51: 41245 | BM51: 41895.5 | BN51: 12355.5 | BO51: 6788.9 | BP51: 4877.2 | BQ51: 11480.09 | BR51: 7071.17 | BS51: 7766.65 | BT51: 27183.54 | BU51: 271.26 | BV51: 9807.11 | BW51: 10541.9 | BX51: 46775.35 | BY51: 68455.21 | BZ51: 112477.01 | CA51: 14345 | CB51: 34672.67 | CD51: 6348 | CE51: 3367.18 | CF51: 26543 | CG51: 30461 | CH51: 380 | CI51: 32483 | CJ51: 317746 | CK51: 28184 | CL51: 0 | CM51: 0 | CN51: 0 | CO51: 0 | CP51: 18326 | CQ51: 46082 | CR51: 30564 | CS51: 18841 | CT51: 8276.58 | CU51: 1470254.2 | CV51: 1008158.9 | CW51: 462095.24 | CX51: 1933736.2 | CY51: 424865.58 | CZ51: 463482
A52: 44593 | B52: =+AI52+BO52 -> 16298.78 | C52: =+AJ52+BP52 -> 33663.45 | D52: =+AK52+BQ52 -> 38794.55 | E52: =+AL52+BR52 -> 66695.28 | F52: =+AM52+BS52 -> 33676.56 | G52: =+AN52+BT52 -> 182405.64 | H52: =+AO52+BU52 -> 7417.21 | I52: =+AP52+BV52 -> 35442.92 | ... Q52: =+AX52+CD52 -> 6348 | S52: =+AY52+CE52 -> 10710.02 | T52: =+AZ52+CF52 -> 122698.32 | U52: =+BA52+CG52 -> 109277.5 | V52: =+BB52+CH52 -> 10127.26 | W52: =+BC52+CI52 -> 48034 | X52: =+BD52+CJ52 -> 475783 | Y52: =+BE52+CK52 -> 100842 | Z52: =+BF52+CL52 -> 0 | ... AH52: =+BN52+CT52 -> 20151.21 | AI52: 9997.5 | AJ52: 28068.5 | AK52: 29769 | AL52: 62715.07 | AM52: 23720.5 | AN52: 145028.55 | AO52: 7386 | AP52: 24361 | AQ52: 34251 | AR52: 117734 | AS52: 47701.5 | AT52: 275640 | AW52: 15687.12 | AY52: 7146.99 | AZ52: 96480.32 | BA52: 66902.5 | BB52: 7609.26 | BC52: 16262 | BD52: 145736 | BE52: 78857 | BF52: 0 | BG52: 0 | BH52: 0 | BI52: 0 | BJ52: 54090 | BK52: 42702 | BL52: 45748 | BM52: 60166.5 | BN52: 9892.5 | BO52: 6301.28 | BP52: 5594.95 | BQ52: 9025.55 | BR52: 3980.21 | BS52: 9956.06 | BT52: 37377.09 | BU52: 31.21 | BV52: 11081.92 | BW52: 12151.29 | BX52: 39701.1 | BY52: 66340.66 | BZ52: 110128.86 | CA52: 12801 | CB52: 30391 | CD52: 6348 | CE52: 3563.03 | CF52: 26218 | CG52: 42375 | CH52: 2518 | CI52: 31772 | CJ52: 330047 | CK52: 21985 | CL52: 0 | CM52: 0 | CN52: 0 | CO52: 0 | CP52: 18041 | CQ52: 44163 | CR52: 36425.5 | CS52: 19882 | CT52: 10258.71 | CU52: 1484117 | CV52: 1016460.8 | CW52: 467656.21 | CX52: 1959900 | CY52: 442211.21 | CZ52: 475783
A53: 44621 | B53: =+AI53+BO53 -> 4291.61 | C53: =+AJ53+BP53 -> 39401.079 | D53: =+AK53+BQ53 -> 48273.07 | E53: =+AL53+BR53 -> 71979.998 | F53: =+AM53+BS53 -> 39506.139 | G53: =+AN53+BT53 -> 190206.98 | H53: =+AO53+BU53 -> 8789.66 | I53: =+AP53+BV53 -> 40967.73 | ... Q53: =+AX53+CD53 -> 6348 | S53: =+AY53+CE53 -> 13486.29 | T53: =+AZ53+CF53 -> 115372.52 | U53: =+BA53+CG53 -> 107315 | V53: =+BB53+CH53 -> 9380.82 | W53: =+BC53+CI53 -> 49561 | X53: =+BD53+CJ53 -> 475783 | Y53: =+BE53+CK53 -> 101810.55 | Z53: =+BF53+CL53 -> 0 | ... AH53: =+BN53+CT53 -> 22993.66 | AI53: 676 | AJ53: 29781.5 | AK53: 34444 | AL53: 70320.85 | AM53: 25167.5 | AN53: 147344.97 | AO53: 8353 | AP53: 28758 | AQ53: 38152.5 | AR53: 131156 | AS53: 44650.97 | AT53: 270968 | AW53: 16902.73 | AY53: 9364.58 | AZ53: 86970.52 | BA53: 72075 | BB53: 7876.82 | BC53: 19594 | BD53: 145736 | BE53: 79379.55 | BF53: 0 | BG53: 0 | BH53: 0 | BI53: 0 | BJ53: 62154 | BK53: 49581 | BL53: 50597.51 | BM53: 70056 | BN53: 10952 | BO53: 3615.61 | BP53: 9619.5787 | BQ53: 13829.07 | BR53: 1659.1483 | BS53: 14338.639 | BT53: 42862.012 | BU53: 436.66 | BV53: 12209.73 | BW53: 14723.98 | BX53: 48131.658 | BY53: 66867.76 | BZ53: 120236.82 | CA53: 14219 | CB53: 32476.81 | CD53: 6348 | CE53: 4121.71 | CF53: 28402 | CG53: 35240 | CH53: 1504 | CI53: 29967 | CJ53: 330047 | CK53: 22431 | CL53: 0 | CM53: 0 | CN53: 0 | CO53: 0 | CP53: 22529 | CQ53: 50497.42 | CR53: 37534.5 | CS53: 38345 | CT53: 12041.66 | CU53: 1543366.1 | CV53: 1042556.9 | CW53: 500809.18 | CX53: 2019149.1 | CY53: 506098.64 | CZ53: 475783
A54: 44652 | B54: =+AI54+BO54 -> 4077.86 | C54: =+AJ54+BP54 -> 35301.36 | D54: =+AK54+BQ54 -> 42489.7 | E54: =+AL54+BR54 -> 73557.26 | F54: =+AM54+BS54 -> 34325.67 | G54: =+AN54+BT54 -> 181813.98 | H54: =+AO54+BU54 -> 8554.32 | I54: =+AP54+BV54 -> 28952.51 | ... Q54: =+AX54+CD54 -> 6348 | S54: =+AY54+CE54 -> 11601.7 | T54: =+AZ54+CF54 -> 122432.03 | U54: =+BA54+CG54 -> 95637.5 | V54: =+BB54+CH54 -> 8155.95 | W54: =+BC54+CI54 -> 40126 | X54: =+BD54+CJ54 -> 497721 | Y54: =+BE54+CK54 -> 100006.51 | Z54: =+BF54+CL54 -> 0 | ... AH54: =+BN54+CT54 -> 21636.612 | AI54: 200 | AJ54: 28345 | AK54: 33297.5 | AL54: 71005.2 | AM54: 24925.5 | AN54: 146686.75 | AO54: 8353 | AP54: 18208.5 | AQ54: 37120 | AR54: 124480.17 | AS54: 50091.46 | AT54: 264900 | AW54: 14974.65 | AY54: 7900.15 | AZ54: 96263.03 | BA54: 64861.5 | BB54: 6831.95 | BC54: 11931 | BD54: 145736 | BE54: 79221.51 | BF54: 0 | BG54: 0 | BH54: 0 | BI54: 0 | BJ54: 53469 | BK54: 43140.84 | BL54: 50337.64 | BM54: 68334.5 | BN54: 9213 | BO54: 3877.86 | BP54: 6956.36 | BQ54: 9192.2 | BR54: 2552.06 | BS54: 9400.17 | BT54: 35127.23 | BU54: 201.32 | BV54: 10744.01 | BW54: 11760.09 | BX54: 49951.59 | BY54: 62422.25 | BZ54: 103175.86 | CA54: 13095 | CB54: 29929.4 | CD54: 6348 | CE54: 3701.55 | CF54: 26169 | CG54: 30776 | CH54: 1324 | CI54: 28195 | CJ54: 351985 | CK54: 20785 | CL54: 0 | CM54: 0 | CN54: 0 | CO54: 0 | CP54: 22693 | CQ54: 38158.41 | CR54: 36597.4 | CS54: 21419 | CT54: 12423.612 | CU54: 1455274.3 | CV54: 1010375.4 | CW54: 444898.95 | CX54: 1952995.3 | CY54: 455792.91 | CZ54: 497721
A55: 44682 | B55: =+AI55+BO55 -> 4892.55 | C55: =+AJ55+BP55 -> 35750.75 | D55: =+AK55+BQ55 -> 39235.56 | E55: =+AL55+BR55 -> 78936.13 | F55: =+AM55+BS55 -> 38359.43 | G55: =+AN55+BT55 -> 187378.27 | H55: =+AO55+BU55 -> 8640.41 | I55: =+AP55+BV55 -> 29391.02 | ... Q55: =+AX55+CD55 -> 6348 | S55: =+AY55+CE55 -> 11779.35 | T55: =+AZ55+CF55 -> 144002.93 | U55: =+BA55+CG55 -> 103548 | V55: =+BB55+CH55 -> 9857.16 | W55: =+BC55+CI55 -> 50709 | X55: =+BD55+CJ55 -> 497721 | Y55: =+BE55+CK55 -> 101652.51 | Z55: =+BF55+CL55 -> 0 | ... AH55: =+BN55+CT55 -> 29888.18 | AI55: 0 | AJ55: 28425 | AK55: 29482 | AL55: 73889.65 | AM55: 26624.5 | AN55: 156341.55 | AO55: 8353 | AP55: 19049 | AQ55: 37621 | AR55: 130524.5 | AS55: 51824.13 | AT55: 262764 | AW55: 16769.96 | AY55: 8216.85 | AZ55: 114359.93 | BA55: 70051 | BB55: 8481.16 | BC55: 20448 | BD55: 145736 | BE55: 80221.51 | BF55: 0 | BG55: 0 | BH55: 0 | BI55: 0 | BJ55: 55876 | BK55: 37240 | BL55: 46867.3 | BM55: 65755 | BN55: 14558 | BO55: 4892.55 | BP55: 7325.75 | BQ55: 9753.56 | BR55: 5046.48 | BS55: 11734.93 | BT55: 31036.72 | BU55: 287.41 | BV55: 10342.02 | BW55: 8131.08 | BX55: 52241.36 | BY55: 61922.42 | BZ55: 115823.43 | CA55: 15011.93 | CB55: 28308.62 | CD55: 6348 | CE55: 3562.5 | CF55: 29643 | CG55: 33497 | CH55: 1376 | CI55: 30261 | CJ55: 351985 | CK55: 21431 | CL55: 0 | CM55: 0 | CN55: 0 | CO55: 0 | CP55: 21466 | CQ55: 30749 | CR55: 40238.5 | CS55: 25609 | CT55: 15330.18 | CU55: 1529771 | CV55: 1063225.2 | CW55: 466545.76 | CX55: 2027492 | CY55: 455341.49 | CZ55: 497721
A56: 44713 | B56: =+AI56+BO56 -> 3701.16 | C56: =+AJ56+BP56 -> 34602.25 | D56: =+AK56+BQ56 -> 34824.66 | E56: =+AL56+BR56 -> 80386.3 | F56: =+AM56+BS56 -> 34794.07 | G56: =+AN56+BT56 -> 195250.23 | H56: =+AO56+BU56 -> 10080.93 | I56: =+AP56+BV56 -> 32038.71 | ... Q56: =+AX56+CD56 -> 6348 | S56: =+AY56+CE56 -> 11829.12 | T56: =+AZ56+CF56 -> 173720.05 | U56: =+BA56+CG56 -> 101423 | V56: =+BB56+CH56 -> 10856.8 | W56: =+BC56+CI56 -> 49776 | X56: =+BD56+CJ56 -> 670563 | Y56: =+BE56+CK56 -> 106435.68 | Z56: =+BF56+CL56 -> 0 | ... AH56: =+BN56+CT56 -> 29220.51 | AI56: 0 | AJ56: 27268.25 | AK56: 27927.5 | AL56: 77038.64 | AM56: 26061 | AN56: 158472.3 | AO56: 8353 | AP56: 17875 | AQ56: 38836 | AR56: 125905.27 | AS56: 51062 | AT56: 265892 | AW56: 16163.76 | AY56: 8110.3 | AZ56: 142496.05 | BA56: 68904 | BB56: 9321.8 | BC56: 20264 | BD56: 145736 | BE56: 85075.68 | BF56: 0 | BG56: 0 | BH56: 0 | BI56: 0 | BJ56: 50306 | BK56: 38413.21 | BL56: 49920.53 | BM56: 47660 | BN56: 13442 | BO56: 3701.16 | BP56: 7334 | BQ56: 6897.16 | BR56: 3347.66 | BS56: 8733.07 | BT56: 36777.93 | BU56: 1727.93 | BV56: 14163.71 | BW56: 11751.68 | BX56: 47104.85 | BY56: 63742.13 | BZ56: 108135.3 | CA56: 14756.9 | CB56: 12783.61 | CD56: 6348 | CE56: 3718.82 | CF56: 31224 | CG56: 32519 | CH56: 1535 | CI56: 29512 | CJ56: 524827 | CK56: 21360 | CL56: 0 | CM56: 0 | CN56: 0 | CO56: 0 | CP56: 22875 | CQ56: 33139.29 | CR56: 39512 | CS56: 21702 | CT56: 15778.51 | CU56: 1535764.8 | CV56: 1089950.9 | CW56: 445813.91 | CX56: 2206327.8 | CY56: 439184.22 | CZ56: 670563
